Workbook
Name channel_analysis: 'SM Dec 2019 vs 2018'!$A$1:$L$9
Name reservations_summary_report__15: Sheet4!$A$1:$AD$818

Sheet VA
A1: As at 30 August 2011
A2: V&A HOTEL
A3: 2011 | B3: BUDGET | G3: Opera
A4: August | B4: 2331 | C4: =(B4/2914)*100 -> 79.993137 | D4: 3030300 | E4: =D4/B4 -> 1300 | F4: =SUM(#REF!-(QV!F6+DH!F6)) -> #REF! | G4: =(F4/2914)*100 -> #REF! | H4: =SUM(#REF!-(QV!H6+DH!H6)) -> #REF! | I4: =H4/F4 -> #REF!
A5: September | B5: 2035 | C5: =(B5/2820)*100 -> 72.163121 | D5: 3376065 | E5: =D5/B5 -> 1659 | F5: =SUM(#REF!-(QV!F7+DH!F7)) -> #REF! | G5: =(F5/2820)*100 -> #REF! | H5: =SUM(#REF!-(QV!H7+DH!H7)) -> #REF! | I5: =H5/F5 -> #REF!
A6: October | B6: 2374 | C6: =(B6/2914)*100 -> 81.468771 | D6: 4118671 | E6: =D6/B6 -> 1734.9078 | F6: =SUM(#REF!-(QV!F8+DH!F8)) -> #REF! | G6: =(F6/2914)*100 -> #REF! | H6: =SUM(#REF!-(QV!H8+DH!H8)) -> #REF! | I6: =H6/F6 -> #REF!
A7: November | B7: 2369 | C7: =(B7/2820)*100 -> 84.007092 | D7: 4492365 | E7: =D7/B7 -> 1896.3128 | F7: =SUM(#REF!-(QV!F9+DH!F9)) -> #REF! | G7: =(F7/2820)*100 -> #REF! | H7: =SUM(#REF!-(QV!H9+DH!H9)) -> #REF! | I7: =H7/F7 -> #REF!
A8: December | B8: 2040 | C8: =(B8/2914)*100 -> 70.006863 | D8: 4006414 | E8: =D8/B8 -> 1963.9284 | F8: =SUM(#REF!-(QV!F10+DH!F10)) -> #REF! | G8: =(F8/2914)*100 -> #REF! | H8: =SUM(#REF!-(QV!H10+DH!H10)) -> #REF! | I8: =H8/F8 -> #REF!
A9: January | B9: 2001 | C9: =(B9/2914)*100 -> 68.668497 | D9: 3694124 | E9: =D9/B9 -> 1846.1389 | F9: =SUM(#REF!-(QV!F11+DH!F11)) -> #REF! | G9: =(F9/2914)*100 -> #REF! | H9: =SUM(#REF!-(QV!H11+DH!H11)) -> #REF! | I9: =H9/F9 -> #REF!
A10: January | B10: 1984 | C10: =(B10/3100)*100 -> 64 | D10: 4130004 | E10: =D10/B10 -> 2081.6552 | F10: =1268-1 -> 1267 | G10: =(F10/3100)*100 -> 40.870968 | H10: 2229977 | I10: =H10/F10 -> 1760.045 | J10: 2253 | K10: =(J10/3100)*100 -> 72.677419 | L10: 4153012 | M10: =L10/J10 -> 1843.3253 | N10: =1890-39 -> 1851 | O10: =(N10/3100)*100 -> 59.709677 | P10: 3697397.3 | Q10: =P10/N10 -> 1997.5134
A11: 2011 | B11: Revenue | D11: Room Nights
B12: Opera/ Budget | D12: Opera/ Budget
A13: August | C13: =H4-D4 -> #REF! | E13: =F4-B4 -> #REF!
A14: September | C14: =H5-D5 -> #REF! | E14: =F5-B5 -> #REF!
A15: October | C15: =H6-D6 -> #REF! | E15: =F6-B6 -> #REF!
A16: November | C16: =H7-D7 -> #REF! | E16: =F7-B7 -> #REF!
A17: December | C17: =H8-D8 -> #REF! | E17: =F8-B8 -> #REF!
A18: January | C18: =H9-D9 -> #REF! | E18: =F9-B9 -> #REF!
A19: 2011 | B19: As at 10 Aug | C19: Opera | F19: As at 23 Aug | G19: Opera | J19: As at 23 Aug | K19: Opera | N19: Pick Up since 10 Aug | Q19: Pick Up since 23 Aug
D20: REV | F20: RM NITES | G20: OCC % | H20: REV | I20: AVR Rate | J20: RM NITES | K20: OCC % | L20: REV | M20: AVR Rate | N20: Revenue | Q20: Revenue
A21: August | D21: 2478432 | F21: =SUM(#REF!-(QV!F25+DH!F25)) -> #REF! | G21: =(F21/2914)*100 -> #REF! | H21: =SUM(#REF!-(QV!H25+DH!H25)) -> #REF! | I21: =H21/F21 -> #REF! | J21: =SUM(#REF!-(QV!J25+DH!J25)) -> #REF! | K21: =(J21/2914)*100 -> #REF! | L21: =SUM(#REF!-(QV!L25+DH!L25)) -> #REF! | M21: =L21/J21 -> #REF! | N21: =L21-H21 -> #REF! | P21: =J21-F21 -> #REF! | Q21: =O21-K21 -> #REF!
A22: September | D22: 2297652 | F22: =SUM(#REF!-(QV!F26+DH!F26)) -> #REF! | G22: =(F22/2820)*100 -> #REF! | H22: =SUM(#REF!-(QV!H26+DH!H26)) -> #REF! | I22: =H22/F22 -> #REF! | J22: =SUM(#REF!-(QV!J26+DH!J26)) -> #REF! | K22: =(J22/2820)*100 -> #REF! | L22: =SUM(#REF!-(QV!L26+DH!L26)) -> #REF! | M22: =L22/J22 -> #REF! | N22: =L22-H22 -> #REF! | P22: =J22-F22 -> #REF! | Q22: =O22-K22 -> #REF!
A23: October | D23: 3064307 | F23: =SUM(#REF!-(QV!F27+DH!F27)) -> #REF! | G23: =(F23/2914)*100 -> #REF! | H23: =SUM(#REF!-(QV!H27+DH!H27)) -> #REF! | I23: =H23/F23 -> #REF! | J23: =SUM(#REF!-(QV!J27+DH!J27)) -> #REF! | K23: =(J23/2914)*100 -> #REF! | L23: =SUM(#REF!-(QV!L27+DH!L27)) -> #REF! | M23: =L23/J23 -> #REF! | N23: =L23-H23 -> #REF! | P23: =J23-F23 -> #REF! | Q23: =O23-K23 -> #REF!
A24: November | D24: 3585143 | F24: =SUM(#REF!-(QV!F28+DH!F28)) -> #REF! | G24: =(F24/2820)*100 -> #REF! | H24: =SUM(#REF!-(QV!H28+DH!H28)) -> #REF! | I24: =H24/F24 -> #REF! | J24: =SUM(#REF!-(QV!J28+DH!J28)) -> #REF! | K24: =(J24/2820)*100 -> #REF! | L24: =SUM(#REF!-(QV!L28+DH!L28)) -> #REF! | M24: =L24/J24 -> #REF! | N24: =L24-H24 -> #REF! | P24: =J24-F24 -> #REF! | Q24: =O24-K24 -> #REF!
A25: December | D25: 3659400 | F25: =SUM(#REF!-(QV!F29+DH!F29)) -> #REF! | G25: =(F25/2914)*100 -> #REF! | H25: =SUM(#REF!-(QV!H29+DH!H29)) -> #REF! | I25: =H25/F25 -> #REF! | J25: =SUM(#REF!-(QV!J29+DH!J29)) -> #REF! | K25: =(J25/2914)*100 -> #REF! | L25: =SUM(#REF!-(QV!L29+DH!L29)) -> #REF! | M25: =L25/J25 -> #REF! | N25: =L25-H25 -> #REF! | P25: =J25-F25 -> #REF! | Q25: =O25-K25 -> #REF!
A26: January | D26: 2613748 | F26: =SUM(#REF!-(QV!F30+DH!F30)) -> #REF! | G26: =(F26/2914)*100 -> #REF! | H26: =SUM(#REF!-(QV!H30+DH!H30)) -> #REF! | I26: =H26/F26 -> #REF! | J26: =SUM(#REF!-(QV!J30+DH!J30)) -> #REF! | K26: =(J26/2914)*100 -> #REF! | L26: =SUM(#REF!-(QV!L30+DH!L30)) -> #REF! | M26: =L26/J26 -> #REF! | N26: =L26-H26 -> #REF! | P26: =J26-F26 -> #REF! | Q26: =O26-K26 -> #REF!
A27: QUEEN VICTORIA HOTEL
A28: 2011 | B28: BUDGET | G28: Opera
A29: August | B29: 565 | C29: =(B29/1085)*100 -> 52.073733 | D29: 847500 | E29: =D29/B29 -> 1500 | F29: 531 | G29: =(F29/1085)*100 -> 48.940092 | H29: 556849 | I29: =H29/F29 -> 1048.6798
A30: September | B30: 688 | C30: =(B30/1050)*100 -> 65.52381 | D30: 1344286 | E30: =D30/B30 -> 1953.9041 | F30: 347 | G30: =(F30/1050)*100 -> 33.047619 | H30: 725946 | I30: =H30/F30 -> 2092.0634
A31: October | B31: 821 | C31: =(B31/1085)*100 -> 75.668203 | D31: 1623204 | E31: =D31/B31 -> 1977.106 | F31: 202 | G31: =(F31/1085)*100 -> 18.617512 | H31: 396659 | I31: =H31/F31 -> 1963.6584
A32: November | B32: 850 | C32: =(B32/1050)*100 -> 80.952381 | D32: 1602112 | E32: =D32/B32 -> 1884.8376 | F32: 511 | G32: =(F32/1050)*100 -> 48.666667 | H32: 974081 | I32: =H32/F32 -> 1906.225
A33: December | B33: 705 | C33: =(B33/1085)*100 -> 64.976959 | D33: 1618503 | E33: =D33/B33 -> 2295.7489 | F33: 517 | G33: =(F33/1085)*100 -> 47.64977 | H33: 916435 | I33: =H33/F33 -> 1772.6015
A34: January | B34: 762 | C34: =(B34/1085)*100 -> 70.230415 | D34: 1493506 | E34: =D34/B34 -> 1959.9816 | F34: 317 | G34: =(F34/1085)*100 -> 29.21659 | H34: 455018 | I34: =H34/F34 -> 1435.388
A35: 2011 | B35: Revenue | D35: Room Nights
B36: Opera/ Budget | D36: Opera/ Budget
A37: August | C37: =H29-D29 -> -290651 | E37: =F29-B29 -> -34
A38: September | C38: =H30-D30 -> -618340 | E38: =F30-B30 -> -341
A39: October | C39: =H31-D31 -> -1226545 | E39: =F31-B31 -> -619
A40: November | C40: =H32-D32 -> -628031 | E40: =F32-B32 -> -339
A41: December | C41: =H33-D33 -> -702068 | E41: =F33-B33 -> -188
A42: January | C42: =H34-D34 -> -1038488 | E42: =F34-B34 -> -445
A43: 2011 | B43: As at 10 Aug | C43: Opera | F43: As at 23 Aug | G43: Opera | J43: As at 23 Aug | K43: Opera | N43: Pick Up since 10 Aug | Q43: Pick Up since 23 Aug
D44: REV | F44: RM NITES | G44: OCC % | H44: REV | I44: AVR Rate | J44: RM NITES | K44: OCC % | L44: REV | M44: AVR Rate | N44: Revenue | Q44: Revenue
A45: August | D45: 236039 | F45: 531 | G45: =(F45/1085)*100 -> 48.940092 | H45: 556849 | I45: =H45/F45 -> 1048.6798 | J45: 531 | K45: =(J45/1085)*100 -> 48.940092 | L45: 556849 | M45: =L45/J45 -> 1048.6798 | N45: =L45-H45 -> 0 | P45: =J45-F45 -> 0 | Q45: =O45-K45 -> -48.940092
A46: September | D46: 544244 | F46: 347 | G46: =(F46/1050)*100 -> 33.047619 | H46: 725946 | I46: =H46/F46 -> 2092.0634 | J46: 347 | K46: =(J46/1050)*100 -> 33.047619 | L46: 725946 | M46: =L46/J46 -> 2092.0634 | N46: =L46-H46 -> 0 | P46: =J46-F46 -> 0 | Q46: =O46-K46 -> -33.047619
A47: October | D47: 301903 | F47: 202 | G47: =(F47/1085)*100 -> 18.617512 | H47: 396659 | I47: =H47/F47 -> 1963.6584 | J47: 202 | K47: =(J47/1085)*100 -> 18.617512 | L47: 396659 | M47: =L47/J47 -> 1963.6584 | N47: =L47-H47 -> 0 | P47: =J47-F47 -> 0 | Q47: =O47-K47 -> -18.617512
A48: November | D48: 713164 | F48: 511 | G48: =(F48/1050)*100 -> 48.666667 | H48: 974081 | I48: =H48/F48 -> 1906.225 | J48: 511 | K48: =(J48/1050)*100 -> 48.666667 | L48: 974081 | M48: =L48/J48 -> 1906.225 | N48: =L48-H48 -> 0 | P48: =J48-F48 -> 0 | Q48: =O48-K48 -> -48.666667
A49: December | D49: 898118 | F49: 517 | G49: =(F49/1085)*100 -> 47.64977 | H49: 916435 | I49: =H49/F49 -> 1772.6015 | J49: 517 | K49: =(J49/1085)*100 -> 47.64977 | L49: 916435 | M49: =L49/J49 -> 1772.6015 | N49: =L49-H49 -> 0 | P49: =J49-F49 -> 0 | Q49: =O49-K49 -> -47.64977
A50: January | D50: 441440 | F50: 317 | G50: =(F50/1085)*100 -> 29.21659 | H50: 455018 | I50: =H50/F50 -> 1435.388 | J50: 317 | K50: =(J50/1085)*100 -> 29.21659 | L50: 455018 | M50: =L50/J50 -> 1435.388 | N50: =L50-H50 -> 0 | P50: =J50-F50 -> 0 | Q50: =O50-K50 -> -29.21659
A51: DOCK HOUSE HOTEL
A52: 2011 | B52: BUDGET | G52: Opera
A53: August | B53: 127.5 | C53: =(B53/186)*100 -> 68.548387 | D53: 225293 | E53: =D53/B53 -> 1767.0039 | F53: 104 | G53: =(F53/186)*100 -> 55.913978 | H53: 142701 | I53: =H53/F53 -> 1372.125
A54: September | B54: 135 | C54: =(B54/180)*100 -> 75 | D54: 329721 | E54: =D54/B54 -> 2442.3778 | F54: 76 | G54: =(F54/180)*100 -> 42.222222 | H54: 165081 | I54: =H54/F54 -> 2172.1184
A55: October | B55: 151.3 | C55: =(B55/186)*100 -> 81.344086 | D55: 373888 | E55: =D55/B55 -> 2471.1699 | F55: 71 | G55: =(F55/186)*100 -> 38.172043 | H55: 206440 | I55: =H55/F55 -> 2907.6056
A56: November | B56: 135 | C56: =(B56/180)*100 -> 75 | D56: 318066 | E56: =D56/B56 -> 2356.0444 | F56: 71 | G56: =(F56/180)*100 -> 39.444444 | H56: 159019 | I56: =H56/F56 -> 2239.7042
A57: December | B57: 151.2 | C57: =(B57/186)*100 -> 81.290323 | D57: 434040 | E57: =D57/B57 -> 2870.6349 | F57: 56 | G57: =(F57/186)*100 -> 30.107527 | H57: 195885 | I57: =H57/F57 -> 3497.9464
A58: January | B58: 140 | C58: =(B58/186)*100 -> 75.268817 | D58: 342997 | E58: =D58/B58 -> 2449.9786 | F58: 46 | G58: =(F58/186)*100 -> 24.731183 | H58: 159918 | I58: =H58/F58 -> 3476.4783
A59: 2011 | B59: Revenue | D59: Room Nights
B60: Opera/ Budget | D60: Opera/ Budget
A61: August | C61: =H53-D53 -> -82592 | E61: =F53-B53 -> -23.5
A62: September | C62: =H54-D54 -> -164640 | E62: =F54-B54 -> -59
A63: October | C63: =H55-D55 -> -167448 | E63: =F55-B55 -> -80.3
A64: November | C64: =H56-D56 -> -159047 | E64: =F56-B56 -> -64
A65: December | C65: =H57-D57 -> -238155 | E65: =F57-B57 -> -95.2
A66: January | C66: =H58-D58 -> -183079 | E66: =F58-B58 -> -94
A67: 2011 | B67: As at 10 Aug | C67: Opera | F67: As at 23 Aug | G67: Opera | J67: As at 23 Aug | K67: Opera | N67: Pick Up since 10 Aug | Q67: Pick Up since 23 Aug
D68: REV | F68: RM NITES | G68: OCC % | H68: REV | I68: AVR Rate | J68: RM NITES | K68: OCC % | L68: REV | M68: AVR Rate | N68: Revenue | Q68: Revenue
A69: August | D69: 103623 | F69: 104 | G69: =(F69/186)*100 -> 55.913978 | H69: 142701 | I69: =H69/F69 -> 1372.125 | J69: 104 | K69: =(J69/186)*100 -> 55.913978 | L69: 142701 | M69: =L69/J69 -> 1372.125 | N69: =L69-H69 -> 0 | P69: =J69-F69 -> 0 | Q69: =O69-K69 -> -55.913978
A70: September | D70: 149866 | F70: 76 | G70: =(F70/180)*100 -> 42.222222 | H70: 165081 | I70: =H70/F70 -> 2172.1184 | J70: 76 | K70: =(J70/180)*100 -> 42.222222 | L70: 165081 | M70: =L70/J70 -> 2172.1184 | N70: =L70-H70 -> 0 | P70: =J70-F70 -> 0 | Q70: =O70-K70 -> -42.222222
A71: October | D71: 187725 | F71: 71 | G71: =(F71/186)*100 -> 38.172043 | H71: 206440 | I71: =H71/F71 -> 2907.6056 | J71: 71 | K71: =(J71/186)*100 -> 38.172043 | L71: 206440 | M71: =L71/J71 -> 2907.6056 | N71: =L71-H71 -> 0 | P71: =J71-F71 -> 0 | Q71: =O71-K71 -> -38.172043
A72: November | D72: 244345 | F72: 71 | G72: =(F72/180)*100 -> 39.444444 | H72: 159019 | I72: =H72/F72 -> 2239.7042 | J72: 71 | K72: =(J72/180)*100 -> 39.444444 | L72: 159019 | M72: =L72/J72 -> 2239.7042 | N72: =L72-H72 -> 0 | P72: =J72-F72 -> 0 | Q72: =O72-K72 -> -39.444444
A73: December | D73: 276122 | F73: 56 | G73: =(F73/186)*100 -> 30.107527 | H73: 195885 | I73: =H73/F73 -> 3497.9464 | J73: 56 | K73: =(J73/186)*100 -> 30.107527 | L73: 195885 | M73: =L73/J73 -> 3497.9464 | N73: =L73-H73 -> 0 | P73: =J73-F73 -> 0 | Q73: =O73-K73 -> -30.107527
A74: January | D74: 70050 | F74: 46 | G74: =(F74/186)*100 -> 24.731183 | H74: 159918 | I74: =H74/F74 -> 3476.4783 | J74: 46 | K74: =(J74/186)*100 -> 24.731183 | L74: 159918 | M74: =L74/J74 -> 3476.4783 | N74: =L74-H74 -> 0 | P74: =J74-F74 -> 0 | Q74: =O74-K74 -> -24.731183

Sheet QV
A1: As at 30 August 2011
A3: QUEEN VICTORIA HOTEL
A5: 2011 | B5: BUDGET | G5: Opera
A6: August | B6: 565 | C6: =(B6/1085)*100 -> 52.073733 | D6: 847500 | E6: =D6/B6 -> 1500 | F6: 531 | G6: =(F6/1085)*100 -> 48.940092 | H6: 556849 | I6: =H6/F6 -> 1048.6798
A7: September | B7: 688 | C7: =(B7/1050)*100 -> 65.52381 | D7: 1344286 | E7: =D7/B7 -> 1953.9041 | F7: 347 | G7: =(F7/1050)*100 -> 33.047619 | H7: 725946 | I7: =H7/F7 -> 2092.0634
A8: October | B8: 821 | C8: =(B8/1085)*100 -> 75.668203 | D8: 1623204 | E8: =D8/B8 -> 1977.106 | F8: 202 | G8: =(F8/1085)*100 -> 18.617512 | H8: 396659 | I8: =H8/F8 -> 1963.6584
A9: November | B9: 850 | C9: =(B9/1050)*100 -> 80.952381 | D9: 1602112 | E9: =D9/B9 -> 1884.8376 | F9: 511 | G9: =(F9/1050)*100 -> 48.666667 | H9: 974081 | I9: =H9/F9 -> 1906.225
A10: December | B10: 705 | C10: =(B10/1085)*100 -> 64.976959 | D10: 1618503 | E10: =D10/B10 -> 2295.7489 | F10: 517 | G10: =(F10/1085)*100 -> 47.64977 | H10: 916435 | I10: =H10/F10 -> 1772.6015
A11: January | B11: 762 | C11: =(B11/1085)*100 -> 70.230415 | D11: 1493506 | E11: =D11/B11 -> 1959.9816 | F11: 317 | G11: =(F11/1085)*100 -> 29.21659 | H11: 455018 | I11: =H11/F11 -> 1435.388
A12: January | B12: 1984 | C12: =(B12/3100)*100 -> 64 | D12: 4130004 | E12: =D12/B12 -> 2081.6552 | F12: =1268-1 -> 1267 | G12: =(F12/3100)*100 -> 40.870968 | H12: 2229977 | I12: =H12/F12 -> 1760.045 | J12: 2253 | K12: =(J12/3100)*100 -> 72.677419 | L12: 4153012 | M12: =L12/J12 -> 1843.3253 | N12: =1890-39 -> 1851 | O12: =(N12/3100)*100 -> 59.709677 | P12: 3697397.3 | Q12: =P12/N12 -> 1997.5134
A14: 2011 | B14: Revenue | D14: Room Nights
B15: Opera/ Budget | D15: Opera/ Budget
A16: August | C16: =H6-D6 -> -290651 | E16: =F6-B6 -> -34
A17: September | C17: =H7-D7 -> -618340 | E17: =F7-B7 -> -341
A18: October | C18: =H8-D8 -> -1226545 | E18: =F8-B8 -> -619
A19: November | C19: =H9-D9 -> -628031 | E19: =F9-B9 -> -339
A20: December | C20: =H10-D10 -> -702068 | E20: =F10-B10 -> -188
A21: January | C21: =H11-D11 -> -1038488 | E21: =F11-B11 -> -445
A23: 2011 | B23: As at 10 Aug | C23: Opera | F23: As at 23 Aug | G23: Opera | J23: As at 23 Aug | K23: Opera | N23: Pick Up since 10 Aug | Q23: Pick Up since 23 Aug
D24: REV | F24: RM NITES | G24: OCC % | H24: REV | I24: AVR Rate | J24: RM NITES | K24: OCC % | L24: REV | M24: AVR Rate | N24: Revenue | Q24: Revenue
A25: August | D25: 236039 | F25: 531 | G25: =(F25/1085)*100 -> 48.940092 | H25: 556849 | I25: =H25/F25 -> 1048.6798 | J25: 531 | K25: =(J25/1085)*100 -> 48.940092 | L25: 556849 | M25: =L25/J25 -> 1048.6798 | N25: =L25-H25 -> 0 | P25: =J25-F25 -> 0 | Q25: =O25-K25 -> -48.940092
A26: September | D26: 544244 | F26: 347 | G26: =(F26/1050)*100 -> 33.047619 | H26: 725946 | I26: =H26/F26 -> 2092.0634 | J26: 347 | K26: =(J26/1050)*100 -> 33.047619 | L26: 725946 | M26: =L26/J26 -> 2092.0634 | N26: =L26-H26 -> 0 | P26: =J26-F26 -> 0 | Q26: =O26-K26 -> -33.047619
A27: October | D27: 301903 | F27: 202 | G27: =(F27/1085)*100 -> 18.617512 | H27: 396659 | I27: =H27/F27 -> 1963.6584 | J27: 202 | K27: =(J27/1085)*100 -> 18.617512 | L27: 396659 | M27: =L27/J27 -> 1963.6584 | N27: =L27-H27 -> 0 | P27: =J27-F27 -> 0 | Q27: =O27-K27 -> -18.617512
A28: November | D28: 713164 | F28: 511 | G28: =(F28/1050)*100 -> 48.666667 | H28: 974081 | I28: =H28/F28 -> 1906.225 | J28: 511 | K28: =(J28/1050)*100 -> 48.666667 | L28: 974081 | M28: =L28/J28 -> 1906.225 | N28: =L28-H28 -> 0 | P28: =J28-F28 -> 0 | Q28: =O28-K28 -> -48.666667
A29: December | D29: 898118 | F29: 517 | G29: =(F29/1085)*100 -> 47.64977 | H29: 916435 | I29: =H29/F29 -> 1772.6015 | J29: 517 | K29: =(J29/1085)*100 -> 47.64977 | L29: 916435 | M29: =L29/J29 -> 1772.6015 | N29: =L29-H29 -> 0 | P29: =J29-F29 -> 0 | Q29: =O29-K29 -> -47.64977
A30: January | D30: 441440 | F30: 317 | G30: =(F30/1085)*100 -> 29.21659 | H30: 455018 | I30: =H30/F30 -> 1435.388 | J30: 317 | K30: =(J30/1085)*100 -> 29.21659 | L30: 455018 | M30: =L30/J30 -> 1435.388 | N30: =L30-H30 -> 0 | P30: =J30-F30 -> 0 | Q30: =O30-K30 -> -29.21659

Sheet DH
A1: As at 30 August 2011
A3: DOCK HOUSE HOTEL
A5: 2011 | B5: BUDGET | G5: Opera
A6: August | B6: 127.5 | C6: =(B6/186)*100 -> 68.548387 | D6: 225293 | E6: =D6/B6 -> 1767.0039 | F6: 104 | G6: =(F6/186)*100 -> 55.913978 | H6: 142701 | I6: =H6/F6 -> 1372.125
A7: September | B7: 135 | C7: =(B7/180)*100 -> 75 | D7: 329721 | E7: =D7/B7 -> 2442.3778 | F7: 76 | G7: =(F7/180)*100 -> 42.222222 | H7: 165081 | I7: =H7/F7 -> 2172.1184
A8: October | B8: 151.3 | C8: =(B8/186)*100 -> 81.344086 | D8: 373888 | E8: =D8/B8 -> 2471.1699 | F8: 71 | G8: =(F8/186)*100 -> 38.172043 | H8: 206440 | I8: =H8/F8 -> 2907.6056
A9: November | B9: 135 | C9: =(B9/180)*100 -> 75 | D9: 318066 | E9: =D9/B9 -> 2356.0444 | F9: 71 | G9: =(F9/180)*100 -> 39.444444 | H9: 159019 | I9: =H9/F9 -> 2239.7042
A10: December | B10: 151.2 | C10: =(B10/186)*100 -> 81.290323 | D10: 434040 | E10: =D10/B10 -> 2870.6349 | F10: 56 | G10: =(F10/186)*100 -> 30.107527 | H10: 195885 | I10: =H10/F10 -> 3497.9464
A11: January | B11: 140 | C11: =(B11/186)*100 -> 75.268817 | D11: 342997 | E11: =D11/B11 -> 2449.9786 | F11: 46 | G11: =(F11/186)*100 -> 24.731183 | H11: 159918 | I11: =H11/F11 -> 3476.4783
A12: January | B12: 1984 | C12: =(B12/3100)*100 -> 64 | D12: 4130004 | E12: =D12/B12 -> 2081.6552 | F12: =1268-1 -> 1267 | G12: =(F12/3100)*100 -> 40.870968 | H12: 2229977 | I12: =H12/F12 -> 1760.045 | J12: 2253 | K12: =(J12/3100)*100 -> 72.677419 | L12: 4153012 | M12: =L12/J12 -> 1843.3253 | N12: =1890-39 -> 1851 | O12: =(N12/3100)*100 -> 59.709677 | P12: 3697397.3 | Q12: =P12/N12 -> 1997.5134
A14: 2011 | B14: Revenue | D14: Room Nights
B15: Opera/ Budget | D15: Opera/ Budget
A16: August | C16: =H6-D6 -> -82592 | E16: =F6-B6 -> -23.5
A17: September | C17: =H7-D7 -> -164640 | E17: =F7-B7 -> -59
A18: October | C18: =H8-D8 -> -167448 | E18: =F8-B8 -> -80.3
A19: November | C19: =H9-D9 -> -159047 | E19: =F9-B9 -> -64
A20: December | C20: =H10-D10 -> -238155 | E20: =F10-B10 -> -95.2
A21: January | C21: =H11-D11 -> -183079 | E21: =F11-B11 -> -94
A23: 2011 | B23: As at 10 Aug | C23: Opera | F23: As at 23 Aug | G23: Opera | J23: As at 23 Aug | K23: Opera | N23: Pick Up since 10 Aug | Q23: Pick Up since 23 Aug
D24: REV | F24: RM NITES | G24: OCC % | H24: REV | I24: AVR Rate | J24: RM NITES | K24: OCC % | L24: REV | M24: AVR Rate | N24: Revenue | Q24: Revenue
A25: August | D25: 103623 | F25: 104 | G25: =(F25/186)*100 -> 55.913978 | H25: 142701 | I25: =H25/F25 -> 1372.125 | J25: 104 | K25: =(J25/186)*100 -> 55.913978 | L25: 142701 | M25: =L25/J25 -> 1372.125 | N25: =L25-H25 -> 0 | P25: =J25-F25 -> 0 | Q25: =O25-K25 -> -55.913978
A26: September | D26: 149866 | F26: 76 | G26: =(F26/180)*100 -> 42.222222 | H26: 165081 | I26: =H26/F26 -> 2172.1184 | J26: 76 | K26: =(J26/180)*100 -> 42.222222 | L26: 165081 | M26: =L26/J26 -> 2172.1184 | N26: =L26-H26 -> 0 | P26: =J26-F26 -> 0 | Q26: =O26-K26 -> -42.222222
A27: October | D27: 187725 | F27: 71 | G27: =(F27/186)*100 -> 38.172043 | H27: 206440 | I27: =H27/F27 -> 2907.6056 | J27: 71 | K27: =(J27/186)*100 -> 38.172043 | L27: 206440 | M27: =L27/J27 -> 2907.6056 | N27: =L27-H27 -> 0 | P27: =J27-F27 -> 0 | Q27: =O27-K27 -> -38.172043
A28: November | D28: 244345 | F28: 71 | G28: =(F28/180)*100 -> 39.444444 | H28: 159019 | I28: =H28/F28 -> 2239.7042 | J28: 71 | K28: =(J28/180)*100 -> 39.444444 | L28: 159019 | M28: =L28/J28 -> 2239.7042 | N28: =L28-H28 -> 0 | P28: =J28-F28 -> 0 | Q28: =O28-K28 -> -39.444444
A29: December | D29: 276122 | F29: 56 | G29: =(F29/186)*100 -> 30.107527 | H29: 195885 | I29: =H29/F29 -> 3497.9464 | J29: 56 | K29: =(J29/186)*100 -> 30.107527 | L29: 195885 | M29: =L29/J29 -> 3497.9464 | N29: =L29-H29 -> 0 | P29: =J29-F29 -> 0 | Q29: =O29-K29 -> -30.107527
A30: January | D30: 70050 | F30: 46 | G30: =(F30/186)*100 -> 24.731183 | H30: 159918 | I30: =H30/F30 -> 3476.4783 | J30: 46 | K30: =(J30/186)*100 -> 24.731183 | L30: 159918 | M30: =L30/J30 -> 3476.4783 | N30: =L30-H30 -> 0 | P30: =J30-F30 -> 0 | Q30: =O30-K30 -> -24.731183

Sheet Online Res
B1: V&A | C1: AH | D1: LS
A2: 40689 | B2: 33 res
A3: 40690 | B3: 17 res
A4: 40691 | B4: 4 res
A5: 40692 | B5: 1 res
A6: 40693 | B6: 11 res -
A7: 40694 | B7: 26 res | C7: 5
A8: 40695 | B8: 21 res | C8: 3
A9: 40696 | B9: 26 res * | C9: 9
A10: 40697 | B10: 18 res | C10: 1
A11: 40698 | B11: 10 res
A12: 40699 | C12: 11
A13: 40700 | B13: 35 res | C13: 5
A14: 40701 | B14: 21 res | C14: 6
A15: 40702 | B15: 11 res
A16: 40703 | B16: 40 res
A17: 40704 | B17: 18 res | C17: 9
A18: 40705 | B18: 14 res | C18: 7
A19: 40706 | B19: 3 res
A20: 40707 | B20: 42 res | C20: 9
A21: 40708 | B21: 18 res - | C21: 15
A22: 40709 | B22: 28 res | C22: 6
A23: 40710 | B23: 14 res | C23: 3
A24: 40711 | B24: 20 res | C24: 8
A25: 40712 | B25: 19 res | C25: 3
A26: 40713
A27: 40714 | B27: 34 res | C27: 7

Sheet Web Comparison
A1: mid July
C2: WOTIF 1N | D2: WOTIF 1N+ | E2: EXPEDIA 1N | F2: EXPEDIA 3N | G2: BOOKING 1N | H2: BOOKING 3N
A3: V&A | C3: 1640 | D3: 1640 | E3: 1640 | F3: 1097 * | G3: 1640 * | H3: 1093 * | I3: * ranking : 1
A4: DH | C4: 2430 | D4: 2430 | E4: 2430 | F4: 1810 | G4: 2430 | H4: 1810
A5: QV | C5: 1875 | D5: 1875 | E5: 1875 | F5: 1875 | G5: 1875 | H5: 1875
A6: AH | C6: 995 | D6: 995 | E6: 995 | F6: 669 ** | G6: 995 | H6: 663 | I6: ** ranking : 4
A7: LS | E7: 800 | F7: 666 | G7: 800 | H7: 650
A8: Bantry Bay Luxury Suites | D8: 1100 | E8: 955 | F8: 636 | G8: 955 | H8: 955
A9: Cape Royale | C9: 1430 | D9: 1430 | E9: 1435 | F9: 1435 | G9: 1400 | H9: 1400
A10: Commodore | C10: 2180 | D10: 2180 | E10: 1600 | F10: 1493 | G10: 1700 | H10: 1490
A11: Pepper Club | D11: 1216 | H11: 1600
A12: Radisson | C12: 2310 | D12: 2310 | E12: 2310 | F12: 2310 | G12: 2310 | H12: 2310
A13: TAJ | C13: 2150 | D13: 2150 | G13: 2150 | H13: 2150
A14: Westin | C14: 1589 | D14: 1112 | F14: 994 | G14: 1409 | H14: 1127.2
A15: President | C15: 1140 (1660) | D15: 1140 (1660) | G15: 1160 | H15: 996
A16: Breakwater | C16: 1295 | D16: 1101 | E16: 971 | G16: 970 | H16: 976
A17: Hilton | E17: 738 | G17: 816 | H17: 738
A18: Vineyard | C18: 945

Sheet All
A1: AMBASSADOR
B2: BUDGET | C2: OPERA | D2: OCC % | E2: IDEAS | F2: LAST YEAR | G2: REVENUE | I2: P/UP SINCE 25/10 | J2: P/UP SINCE 13/9
C3: as @ 01/11 | G3: Opera/ Budget | H3: Ideas/ Budget | I3: REV | J3: REV
A4: Nov | B4: 2000656 | C4: =#REF! -> #REF! | D4: =#REF! -> #REF! | E4: =#REF! -> #REF! | F4: 1874949 | G4: =#REF! -> #REF! | H4: =#REF! -> #REF! | I4: =#REF! -> #REF! | J4: =#REF! -> #REF!
A5: Dec | B5: 2672018 | C5: =#REF! -> #REF! | D5: =#REF! -> #REF! | E5: =#REF! -> #REF! | F5: 2544779 | G5: =#REF! -> #REF! | H5: =#REF! -> #REF! | I5: =#REF! -> #REF! | J5: =#REF! -> #REF!
A6: Jan | B6: 2329289 | C6: =#REF! -> #REF! | D6: =#REF! -> #REF! | E6: =#REF! -> #REF! | F6: 2194352 | G6: =#REF! -> #REF! | H6: =#REF! -> #REF! | I6: =#REF! -> #REF! | J6: =#REF! -> #REF!
A7: Feb | B7: 2200750 | C7: =#REF! -> #REF! | D7: =#REF! -> #REF! | E7: =#REF! -> #REF! | F7: 2397167 | G7: =#REF! -> #REF! | H7: =#REF! -> #REF! | I7: =#REF! -> #REF! | J7: =#REF! -> #REF!
A8: Mar | C8: =#REF! -> #REF! | D8: =#REF! -> #REF! | E8: =#REF! -> #REF! | F8: 2261197 | I8: =#REF! -> #REF! | J8: =#REF! -> #REF!
A9: April | C9: =#REF! -> #REF! | D9: =#REF! -> #REF! | E9: =#REF! -> #REF! | F9: 1605796 | J9: =#REF! -> #REF!
A10: V&A PROPERTIES COMBINED
B11: BUDGET | C11: OPERA | D11: OCC % | E11: IDEAS | F11: LAST YEAR | G11: REVENUE | I11: P/UP SINCE 25/10 | J11: P/UP SINCE 13/9
C12: as @ 01/11 | G12: Opera/ Budget | H12: Ideas/ Budget | I12: REV | J12: REV
A13: Nov | B13: 6412543 | C13: =#REF! -> #REF! | D13: =#REF! -> #REF! | E13: =#REF! -> #REF! | F13: 4679927 | G13: =#REF! -> #REF! | H13: =#REF! -> #REF! | I13: =#REF! -> #REF! | J13: =#REF! -> #REF!
A14: Dec | B14: 6058957 | C14: =#REF! -> #REF! | D14: =#REF! -> #REF! | E14: =#REF! -> #REF! | F14: 3963564 | G14: =#REF! -> #REF! | H14: =#REF! -> #REF! | I14: =#REF! -> #REF! | J14: =#REF! -> #REF!
A15: Jan | B15: 5530627 | C15: =#REF! -> #REF! | D15: =#REF! -> #REF! | E15: =#REF! -> #REF! | F15: 3786131 | G15: =#REF! -> #REF! | H15: =#REF! -> #REF! | I15: =#REF! -> #REF! | J15: =#REF! -> #REF!
A16: Feb | B16: 7074513 | C16: =#REF! -> #REF! | D16: =#REF! -> #REF! | E16: =#REF! -> #REF! | F16: 5065519 | G16: =#REF! -> #REF! | H16: =#REF! -> #REF! | I16: =#REF! -> #REF! | J16: =#REF! -> #REF!
A17: Mar | C17: =#REF! -> #REF! | D17: =#REF! -> #REF! | E17: =#REF! -> #REF! | F17: 4445403 | I17: =#REF! -> #REF! | J17: =#REF! -> #REF!
A18: April | C18: =#REF! -> #REF! | D18: =#REF! -> #REF! | E18: =#REF! -> #REF! | F18: 3899614 | J18: =#REF! -> #REF!
A19: LA SPLENDIDA
B20: BUDGET | C20: HOTELIER | D20: OCC % | E20: LAST YEAR | G20: REVENUE | I20: P/UP SINCE 25/10 | J20: P/UP SINCE 13/9
B21: as @ 01/11 | G21: Hotelier/ Budget | I21: REV | J21: REV
A22: Nov | B22: 296280 | C22: =#REF! -> #REF! | D22: =#REF! -> #REF! | E22: 254742 | G22: =#REF! -> #REF! | I22: =#REF! -> #REF! | J22: =#REF! -> #REF!
A23: Dec | B23: 321780 | C23: =#REF! -> #REF! | D23: =#REF! -> #REF! | E23: 324829 | G23: =#REF! -> #REF! | I23: =#REF! -> #REF! | J23: =#REF! -> #REF!
A24: Jan | B24: 312852 | C24: =#REF! -> #REF! | D24: =#REF! -> #REF! | E24: 330355 | G24: =#REF! -> #REF! | I24: =#REF! -> #REF! | J24: =#REF! -> #REF!
A25: Feb | B25: 280560 | C25: =#REF! -> #REF! | D25: =#REF! -> #REF! | E25: 479590 | G25: =#REF! -> #REF! | I25: =#REF! -> #REF! | J25: =#REF! -> #REF!
A26: Mar | C26: =#REF! -> #REF! | D26: =#REF! -> #REF! | E26: 481432 | I26: =#REF! -> #REF! | J26: =#REF! -> #REF!
A27: April | C27: =#REF! -> #REF! | D27: =#REF! -> #REF! | E27: 359095 | J27: =#REF! -> #REF!
A28: AH: | B28: Great pick up for November in the last 7 days : R297k - AVR dropped by R48
B29: December also good pick in the last 7 days, however, AVR dropped by R57
A30: VA: | B30: Pick up November slower than previously reported
B31: Good pick up in Dec R286k in the last 7 days and AVR up by R10
B32: Great pick up for Jan R317k as well as AVR up by R14
A33: LS: | B33: Great pick in in the last 7 days, R32k over budget already
B34: Steady pick up Dec & Jan

Sheet 09.12.19
A1: Devonvale Revenue Report 09 December 2019
B2: OTB @ 09 Dec 2019 | C2: Target | D2: LY Actual | E2: OTB vrs Target | G2: Target vrs LY | I2: Variance last 7 days | J2: as @ 03 June 2014 | K2: Variance last 14 days | L2: OTB @ 25 Nov 2019 | M2: Actual vrs LY | O2: as @ 8 Nov 2017 | P2: Variance 2018 vrs 2017 | Q2: OTB @ 8 Nov 2018 | R2: Variance OTB vrs LY OTB | S2: OTB @ 20 Dec 2018 | T2: Variance
A3: Mar | B3: 976369 | C3: =(D3*1.175) -> 940156.28 | D3: 800133 | E3: =B3-C3 -> 36212.725 | F3: =(B3-C3)/C3 -> 0.038517772 | G3: =(C3-D3) -> 140023.28 | H3: =(C3-D3)/D3 -> 0.175 | I3: =B3-J3 -> 815149 | J3: 161220 | L3: 976369 | M3: =B3-D3 -> 176236 | N3: =(B3-D3)/D3 -> 0.22025838 | O3: 1191028
A4: Apr | B4: 766954 | C4: =(D4*1.175) -> 589504.55 | D4: 501706 | E4: =B4-C4 -> 177449.45 | F4: =(B4-C4)/C4 -> 0.30101456 | G4: =(C4-D4) -> 87798.55 | H4: =(C4-D4)/D4 -> 0.175 | I4: =B4-J4 -> 605734 | J4: 161220 | L4: 766954 | M4: =B4-D4 -> 265248 | N4: =(B4-D4)/D4 -> 0.5286921 | O4: 1245578
A5: May | B5: 644339 | C5: =(D5*1.175) -> 621985.08 | D5: 529349 | E5: =B5-C5 -> 22353.925 | F5: =(B5-C5)/C5 -> 0.035939649 | G5: =(C5-D5) -> 92636.075 | H5: =(C5-D5)/D5 -> 0.175 | I5: =B5-J5 -> 483119 | J5: 161220 | L5: 644339 | M5: =B5-D5 -> 114990 | N5: =(B5-D5)/D5 -> 0.21722909 | O5: 1488076
A6: Jun | B6: 530924 | C6: =(D6*1.175) -> 427825.73 | D6: 364107 | E6: =B6-C6 -> 103098.27 | F6: =(B6-C6)/C6 -> 0.24098194 | G6: =(C6-D6) -> 63718.725 | H6: =(C6-D6)/D6 -> 0.175 | I6: =B6-J6 -> 369704 | J6: 161220 | L6: 530924 | M6: =B6-D6 -> 166817 | N6: =(B6-D6)/D6 -> 0.45815378 | O6: 1449686
A7: July | B7: 658052 | C7: =(D7*1.175) -> 519911.65 | D7: 442478 | E7: =B7-C7 -> 138140.35 | F7: =(B7-C7)/C7 -> 0.26569966 | G7: =(C7-D7) -> 77433.65 | H7: =(C7-D7)/D7 -> 0.175 | I7: =B7-J7 -> 496832 | J7: 161220 | L7: 658052 | M7: =B7-D7 -> 215574 | N7: =(B7-D7)/D7 -> 0.4871971 | O7: 770876
A8: Aug | B8: 648180 | C8: =(D8*1.175) -> 513073.15 | D8: 436658 | E8: =B8-C8 -> 135106.85 | F8: =(B8-C8)/C8 -> 0.26332863 | G8: =(C8-D8) -> 76415.15 | H8: =(C8-D8)/D8 -> 0.175 | I8: =B8-J8 -> 438056 | J8: 210124 | L8: 648180 | M8: =B8-D8 -> 211522 | N8: =(B8-D8)/D8 -> 0.48441114 | O8: 570574
A9: Sept | B9: =310920.68+365482.43 -> 676403.11 | C9: =(D9*1.175) -> 639303.4 | D9: 544088 | E9: =B9-C9 -> 37099.71 | F9: =(B9-C9)/C9 -> 0.05803146 | G9: =(C9-D9) -> 95215.4 | H9: =(C9-D9)/D9 -> 0.175 | I9: =B9-J9 -> 387627.11 | J9: 288776 | L9: =310920.68+365482.43 -> 676403.11 | M9: =B9-D9 -> 132315.11 | N9: =(B9-D9)/D9 -> 0.24318697
A10: Oct | B10: 910865 | C10: =(D10*1.175) -> 747056.78 | D10: 635793 | E10: =B10-C10 -> 163808.22 | F10: =(B10-C10)/C10 -> 0.21927145 | G10: =(C10-D10) -> 111263.78 | H10: =(C10-D10)/D10 -> 0.175 | I10: =B10-J10 -> 697139 | J10: 213726 | L10: 910865 | M10: =B10-D10 -> 275072 | N10: =(B10-D10)/D10 -> 0.43264396
A11: Nov | B11: 1045436 | C11: =(D11*1.175) -> 905782.83 | D11: 770879 | E11: =B11-C11 -> 139653.17 | F11: =(B11-C11)/C11 -> 0.15417954 | G11: =(C11-D11) -> 134903.83 | H11: =(C11-D11)/D11 -> 0.175 | I11: =B11-J11 -> 884526 | J11: 160910 | L11: 1045436 | M11: =B11-D11 -> 274557 | N11: =(B11-D11)/D11 -> 0.35616095
A12: Dec | B12: 1178518 | C12: =(D12*1.175) -> 1112324.3 | D12: 946659 | E12: =B12-C12 -> 66193.675 | F12: =(B12-C12)/C12 -> 0.05950933 | G12: =(C12-D12) -> 165665.32 | H12: =(C12-D12)/D12 -> 0.175 | L12: 1178518 | M12: =B12-D12 -> 231859 | N12: =(B12-D12)/D12 -> 0.24492346
A13: Jan | B13: 1117894 | C13: =(D13*1.175) -> 1100221.8 | D13: 936359 | E13: =B13-C13 -> 17672.175 | F13: =(B13-C13)/C13 -> 0.016062375 | G13: =(C13-D13) -> 163862.82 | H13: =(C13-D13)/D13 -> 0.175 | L13: 1117894 | M13: =B13-D13 -> 181535 | N13: =(B13-D13)/D13 -> 0.19387329
A14: Feb | B14: 1103333 | C14: =(D14*1.175) -> 1065344.3 | D14: 906676 | E14: =B14-C14 -> 37988.7 | F14: =(B14-C14)/C14 -> 0.035658613 | G14: =(C14-D14) -> 158668.3 | H14: =(C14-D14)/D14 -> 0.175 | L14: 1103333 | M14: =B14-D14 -> 196657 | N14: =(B14-D14)/D14 -> 0.21689887
A15: Fin Year | B15: =SUM(B3:B14) -> 10257267 | C15: =SUM(C3:C14) -> 9182489.9 | D15: =SUM(D3:D14) -> 7814885 | E15: =SUM(E3:E14) -> 1074777.2 | G15: =SUM(G3:G14) -> 1367604.9 | H15: =(C15-D15)/D15 -> 0.175 | L15: =SUM(L3:L14) -> 10257267 | M15: =B15-D15 -> 2442382.1 | N15: =(B15-D15)/D15 -> 0.3125295
A16: Oct | B16: 1187356 | C16: =D16*1.1 -> 1007437.2 | D16: 915852 | E16: =B16-C16 -> 179918.8 | F16: =(B16-C16)/C16 -> 0.17859059 | G16: =(C16-D16) -> 91585.2 | H16: =(C16-D16)/D16 -> 0.1 | L16: 1187356 | M16: =B16-D16 -> 271504 | N16: =(B16-D16)/D16 -> 0.29644964
A17: Nov | B17: 1465604 | C17: =D17*1.1 -> 1517958.2 | D17: 1379962 | E17: =B17-C17 -> -52354.2 | F17: =(B17-C17)/C17 -> -0.034489883 | G17: =(C17-D17) -> 137996.2 | H17: =(C17-D17)/D17 -> 0.1 | L17: 1465604 | M17: =B17-D17 -> 85642 | N17: =(B17-D17)/D17 -> 0.062061129
A18: Dec | B18: 1353583 | C18: 1074639 | D18: 979969 | E18: =B18-C18 -> 278944 | F18: =(B18-C18)/C18 -> 0.25956996 | G18: =(C18-D18) -> 94670 | H18: =(C18-D18)/D18 -> 0.096605097 | L18: 1353583 | M18: =B18-D18 -> 373614 | N18: =(B18-D18)/D18 -> 0.38125084
A19: Jan | B19: 1039316 | C19: =D19*1.1 -> 762835.7 | D19: 693487 | E19: =B19-C19 -> 276480.3 | F19: =(B19-C19)/C19 -> 0.36243755 | G19: =(C19-D19) -> 69348.7 | H19: =(C19-D19)/D19 -> 0.1 | L19: 1039316 | M19: =B19-D19 -> 345829 | N19: =(B19-D19)/D19 -> 0.4986813
A20: Feb | B20: 2032270 | C20: =D20*1.1 -> 1590482.3 | D20: 1445893 | E20: =B20-C20 -> 441787.7 | F20: =(B20-C20)/C20 -> 0.27776964 | G20: =(C20-D20) -> 144589.3 | H20: =(C20-D20)/D20 -> 0.1 | L20: 2032270 | M20: =B20-D20 -> 586377 | N20: =(B20-D20)/D20 -> 0.40554661
A21: Mar | B21: 1805608 | C21: =D21*1.1 -> 1752617.9 | D21: 1593289 | E21: =B21-C21 -> 52990.1 | F21: =(B21-C21)/C21 -> 0.030234828 | G21: =(C21-D21) -> 159328.9 | H21: =(C21-D21)/D21 -> 0.1 | L21: 1805608 | M21: =B21-D21 -> 212319 | N21: =(B21-D21)/D21 -> 0.13325831
A22: Apr | B22: 1145562 | C22: =D22*1.1 -> 1300503.6 | D22: 1182276 | E22: =B22-C22 -> -154941.6 | F22: =(B22-C22)/C22 -> -0.11913969 | G22: =(C22-D22) -> 118227.6 | H22: =(C22-D22)/D22 -> 0.1 | L22: 1145562 | M22: =B22-D22 -> -36714 | N22: =(B22-D22)/D22 -> -0.031053663
A23: May | B23: 1022011 | C23: =D23*1.1 -> 507736.9 | D23: 461579 | E23: =B23-C23 -> 514274.1 | F23: =(B23-C23)/C23 -> 1.0128752 | G23: =(C23-D23) -> 46157.9 | H23: =(C23-D23)/D23 -> 0.1 | L23: 1022011 | M23: =B23-D23 -> 560432 | N23: =(B23-D23)/D23 -> 1.2141627
A24: Apr | B24: 1244430 | C24: =D24*1.1 -> 1522590.3 | D24: 1384173 | E24: =B24-C24 -> -278160.3 | F24: =(B24-C24)/C24 -> -0.18268887 | G24: =(C24-D24) -> 138417.3 | H24: =(C24-D24)/D24 -> 0.1 | K24: =B24-L24 -> 0 | L24: 1244430 | M24: =B24-D24 -> -139743 | N24: =(B24-D24)/D24 -> -0.10095776
A25: May | B25: 282761 | C25: =D25*1.1 -> 1417482 | D25: 1288620 | E25: =B25-C25 -> -1134721 | F25: =(B25-C25)/C25 -> -0.80051881 | G25: =(C25-D25) -> 128862 | H25: =(C25-D25)/D25 -> 0.1 | K25: =B25-L25 -> 0 | L25: 282761 | M25: =B25-D25 -> -1005859 | N25: =(B25-D25)/D25 -> -0.78057069
A26: June | B26: 108882 | C26: =D26*1.1 -> 818774 | D26: 744340 | E26: =B26-C26 -> -709892 | F26: =(B26-C26)/C26 -> -0.86701825 | G26: =(C26-D26) -> 74434 | H26: =(C26-D26)/D26 -> 0.1 | K26: =B26-L26 -> 0 | L26: 108882 | M26: =B26-D26 -> -635458 | N26: =(B26-D26)/D26 -> -0.85372007
A27: July | B27: 1267953 | C27: =D27*1.1 -> 939474.8 | D27: 854068 | E27: =B27-C27 -> 328478.2 | F27: =(B27-C27)/C27 -> 0.34964025 | G27: =(C27-D27) -> 85406.8 | H27: =(C27-D27)/D27 -> 0.1 | L27: 1267953 | M27: =B27-D27 -> 413885 | N27: =(B27-D27)/D27 -> 0.48460427
A28: August | B28: 300416 | C28: =D28*1.1 -> 417312.5 | D28: 379375 | E28: =B28-C28 -> -116896.5 | F28: =(B28-C28)/C28 -> -0.28011742 | G28: =(C28-D28) -> 37937.5 | H28: =(C28-D28)/D28 -> 0.1 | L28: 300416 | M28: =B28-D28 -> -78959 | N28: =(B28-D28)/D28 -> -0.20812916
A29: September | B29: 484160 | C29: =D29*1.1 -> 628629.1 | D29: 571481 | E29: =B29-C29 -> -144469.1 | F29: =(B29-C29)/C29 -> -0.22981612 | G29: =(C29-D29) -> 57148.1 | H29: =(C29-D29)/D29 -> 0.1 | K29: =B29-L29 -> 0 | L29: 484160 | M29: =B29-D29 -> -87321 | N29: =(B29-D29)/D29 -> -0.15279773
A30: October | B30: 403884 | C30: =D30*1.1 -> 730540.8 | D30: 664128 | E30: =B30-C30 -> -326656.8 | F30: =(B30-C30)/C30 -> -0.44714381 | G30: =(C30-D30) -> 66412.8 | H30: =(C30-D30)/D30 -> 0.1 | K30: =B30-L30 -> 0 | L30: 403884 | M30: =B30-D30 -> -260244 | N30: =(B30-D30)/D30 -> -0.3918582
A31: November | B31: 1196163 | C31: =D31*1.1 -> 1536906.8 | D31: 1397188 | E31: =B31-C31 -> -340743.8 | F31: =(B31-C31)/C31 -> -0.22170752 | G31: =(C31-D31) -> 139718.8 | H31: =(C31-D31)/D31 -> 0.1 | K31: =B31-L31 -> 0 | L31: 1196163 | M31: =B31-D31 -> -201025 | N31: =(B31-D31)/D31 -> -0.14387828
A32: December | B32: 1310080 | C32: =D32*1.1 -> 1936268.4 | D32: 1760244 | E32: =B32-C32 -> -626188.4 | F32: =(B32-C32)/C32 -> -0.32339959 | G32: =(C32-D32) -> 176024.4 | H32: =(C32-D32)/D32 -> 0.1 | K32: =B32-L32 -> 0 | L32: 1310080 | M32: =B32-D32 -> -450164 | N32: =(B32-D32)/D32 -> -0.25573955
A33: January | B33: 1659145 | C33: =D33*1.1 -> 1825997.8 | D33: 1659998 | E33: =B33-C33 -> -166852.8 | F33: -0.61325998 | G33: 350895.35 | H33: 0.1 | K33: =B33-L33 -> 0 | L33: 1659145 | M33: =B33-D33 -> -853 | N33: -0.57458598
A34: Feb | B34: 1879453 | C34: =D34*1.1 -> 1819609 | D34: 1654190 | E34: =B34-C34 -> 59844 | F34: =(B34-C34)/C34 -> 0.032888384 | G34: =(C34-D34) -> 165419 | H34: =(C34-D34)/D34 -> 0.1 | K34: =B34-L34 -> 0 | L34: 1879453 | M34: =B34-D34 -> 225263 | N34: =(B34-D34)/D34 -> 0.13617722
A35: March | B35: 1257902 | C35: =D35*1.1 -> 1439953.9 | D35: 1309049 | E35: =B35-C35 -> -182051.9 | F35: =(B35-C35)/C35 -> -0.12642898 | G35: =(C35-D35) -> 130904.9 | H35: =(C35-D35)/D35 -> 0.1 | K35: =B35-L35 -> 0 | L35: 1257902 | M35: =B35-D35 -> -51147 | N35: =(B35-D35)/D35 -> -0.039071876
A36: Apr | B36: 641964 | C36: 552499.2 | D36: 502272 | E36: =B36-C36 -> 89464.8 | F36: 0.032714618 | G36: 50227.2 | H36: 0.1 | K36: =B36-L36 -> 0 | L36: 641964 | M36: =B36-D36 -> 139692 | N36: =(B36-D36)/D36 -> 0.27812022
A37: May | B37: 291306 | C37: =D37*1.1 -> 343454.1 | D37: 312231 | E37: =B37-C37 -> -52148.1 | F37: =(B37-C37)/C37 -> -0.15183426 | G37: =(C37-D37) -> 31223.1 | H37: =(C37-D37)/D37 -> 0.1 | K37: =B37-L37 -> 0 | L37: 291306 | M37: =B37-D37 -> -20925 | N37: =(B37-D37)/D37 -> -0.067017689
A38: June | B38: 345442 | C38: 350000 | D38: 0 | E38: =B38-C38 -> -4558 | F38: =(B38-C38)/C38 -> -0.013022857 | G38: =(C38-D38) -> 350000 | H38: =(C38-D38)/D38 -> #DIV/0! | K38: =B38-L38 -> 0 | L38: 345442 | M38: =B38-D38 -> 345442 | N38: =(B38-D38)/D38 -> #DIV/0!
A39: July | B39: 245810 | C39: =D39*1.1 -> 398643.3 | D39: 362403 | E39: =B39-C39 -> -152833.3 | F39: =(B39-C39)/C39 -> -0.38338359 | G39: =(C39-D39) -> 36240.3 | H39: =(C39-D39)/D39 -> 0.1 | K39: =B39-L39 -> 0 | L39: 245810 | M39: =B39-D39 -> -116593 | N39: =(B39-D39)/D39 -> -0.32172195
A40: Aug | B40: 493056 | C40: =D40*1.1 -> 330457.6 | D40: 300416 | E40: =B40-C40 -> 162598.4 | F40: =(B40-C40)/C40 -> 0.49204013 | G40: =(C40-D40) -> 30041.6 | H40: =(C40-D40)/D40 -> 0.1 | K40: =B40-L40 -> 0 | L40: 493056 | M40: =B40-D40 -> 192640 | N40: =(B40-D40)/D40 -> 0.64124414
A41: Sept | B41: 693980 | C41: =D41*1.1 -> 547079.5 | D41: 497345 | E41: =B41-C41 -> 146900.5 | F41: =(B41-C41)/C41 -> 0.26851765 | G41: =(C41-D41) -> 49734.5 | H41: =(C41-D41)/D41 -> 0.1 | K41: =B41-L41 -> 0 | L41: 693980 | M41: =B41-D41 -> 196635 | N41: =(B41-D41)/D41 -> 0.39536941
A42: Oct | B42: 614185 | C42: =D42*1.1 -> 494970.3 | D42: 449973 | E42: =B42-C42 -> 119214.7 | F42: =(B42-C42)/C42 -> 0.24085223 | G42: =(C42-D42) -> 44997.3 | H42: =(C42-D42)/D42 -> 0.1 | K42: =B42-L42 -> 0 | L42: 614185 | M42: =B42-D42 -> 164212 | N42: =(B42-D42)/D42 -> 0.36493745
A43: Nov | B43: 1253995.8 | C43: =D43*1.1 -> 1316659.3 | D43: 1196963 | E43: =B43-C43 -> -62663.47 | F43: =(B43-C43)/C43 -> -0.047592775 | G43: =(C43-D43) -> 119696.3 | H43: =(C43-D43)/D43 -> 0.1 | K43: =B43-L43 -> 0 | L43: 1253995.8 | M43: =B43-D43 -> 57032.83 | N43: =(B43-D43)/D43 -> 0.047647947 | O43: 1191028 | P43: =B43-O43 -> 62967.83
A44: Dec | B44: 1298292.3 | C44: =D44*1.1 -> 1441088 | D44: 1310080 | E44: =B44-C44 -> -142795.7 | F44: =(B44-C44)/C44 -> -0.099088813 | G44: =(C44-D44) -> 131008 | H44: =(C44-D44)/D44 -> 0.1 | K44: =B44-L44 -> 0 | L44: 1298292.3 | M44: =B44-D44 -> -11787.7 | N44: =(B44-D44)/D44 -> -0.0089976948 | O44: 1245578 | P44: =B44-O44 -> 52714.3
A45: Jan | B45: 1427559 | C45: =D45*1.1 -> 1825059.6 | D45: 1659145.1 | E45: =B45-C45 -> -397500.62 | F45: =(B45-C45)/C45 -> -0.21780144 | G45: =(C45-D45) -> 165914.51 | H45: =(C45-D45)/D45 -> 0.1 | K45: =B45-L45 -> 0 | L45: 1427559 | M45: =B45-D45 -> -231586.11 | N45: =(B45-D45)/D45 -> -0.13958159 | O45: 1488076 | P45: =B45-O45 -> -60517
A46: Feb | B46: 1326567 | C46: =D46*1.1 -> 2067398.3 | D46: 1879453 | E46: =B46-C46 -> -740831.3 | F46: =(B46-C46)/C46 -> -0.3583399 | G46: =(C46-D46) -> 187945.3 | H46: =(C46-D46)/D46 -> 0.1 | K46: =B46-L46 -> 0 | L46: 1326567 | M46: =B46-D46 -> -552886 | N46: =(B46-D46)/D46 -> -0.29417389 | O46: 1449686 | P46: =B46-O46 -> -123119
A47: Mar | B47: 1088477.2 | C47: =D47*1.1 -> 2067398.3 | D47: 1879453 | E47: =B47-C47 -> -978921.12 | F47: =(B47-C47)/C47 -> -0.47350388 | G47: =(C47-D47) -> 187945.3 | H47: =(C47-D47)/D47 -> 0.1 | K47: =B47-L47 -> 0 | L47: 1088477.2 | M47: =B47-D47 -> -790975.82 | N47: =(B47-D47)/D47 -> -0.42085427 | O47: 770876 | P47: =B47-O47 -> 317601.18
A48: Apr | B48: 692652.76 | C48: =D48*1.1 -> 706160.4 | D48: 641964 | E48: =B48-C48 -> -13507.64 | F48: =(B48-C48)/C48 -> -0.019128289 | G48: =(C48-D48) -> 64196.4 | H48: =(C48-D48)/D48 -> 0.1 | K48: =B48-L48 -> 0 | L48: 692652.76 | M48: =B48-D48 -> 50688.76 | N48: =(B48-D48)/D48 -> 0.078958882 | O48: 570574 | P48: =B48-O48 -> 122078.76
A49: May | B49: 377716 | C49: =D49*1.1 -> 320436.6 | D49: 291306 | E49: =B49-C49 -> 57279.4 | F49: =(B49-C49)/C49 -> 0.17875424 | G49: =(C49-D49) -> 29130.6 | H49: =(C49-D49)/D49 -> 0.1 | K49: =B49-L49 -> 0 | L49: 377716 | M49: =B49-D49 -> 86410 | N49: =(B49-D49)/D49 -> 0.29662966
A50: June | B50: 428676.17 | C50: =D50*1.1 -> 379986.2 | D50: 345442 | E50: =B50-C50 -> 48689.97 | F50: =(B50-C50)/C50 -> 0.12813615 | G50: =(C50-D50) -> 34544.2 | H50: =(C50-D50)/D50 -> 0.1 | K50: =B50-L50 -> 0 | L50: 428676.17 | M50: =B50-D50 -> 83234.17 | N50: =(B50-D50)/D50 -> 0.24094977
A51: July | B51: 412177 | C51: =D51*1.1 -> 270391 | D51: 245810 | E51: =B51-C51 -> 141786 | F51: =(B51-C51)/C51 -> 0.52437396 | G51: =(C51-D51) -> 24581 | H51: =(C51-D51)/D51 -> 0.1 | K51: =B51-L51 -> 0 | L51: 412177 | M51: =B51-D51 -> 166367 | N51: =(B51-D51)/D51 -> 0.67681136
A52: Aug | B52: 675819 | C52: =D52*1.1 -> 542361.6 | D52: 493056 | E52: =B52-C52 -> 133457.4 | F52: =(B52-C52)/C52 -> 0.2460672 | G52: =(C52-D52) -> 49305.6 | H52: =(C52-D52)/D52 -> 0.1 | K52: =B52-L52 -> 0 | L52: 675819 | M52: =B52-D52 -> 182763 | N52: =(B52-D52)/D52 -> 0.37067392
A53: Sep | B53: 1003569 | C53: =D53*1.1 -> 763378 | D53: 693980 | E53: =B53-C53 -> 240191 | F53: =(B53-C53)/C53 -> 0.31464229 | G53: =(C53-D53) -> 69398 | H53: =(C53-D53)/D53 -> 0.1 | K53: =B53-L53 -> 0 | L53: 1003569 | M53: =B53-D53 -> 309589 | N53: =(B53-D53)/D53 -> 0.44610652 | Q53: 1003569
A54: Oct | B54: 781187 | C54: =D54*1.1 -> 675603.5 | D54: 614185 | E54: =B54-C54 -> 105583.5 | F54: =(B54-C54)/C54 -> 0.15628027 | G54: =(C54-D54) -> 61418.5 | H54: =(C54-D54)/D54 -> 0.1 | K54: =B54-L54 -> 0 | L54: 781187 | M54: =B54-D54 -> 167002 | N54: =(B54-D54)/D54 -> 0.2719083 | Q54: 588356.37 | R54: =B54-Q54 -> 192830.63
A55: Nov | B55: 1355145.6 | C55: =D55*1.1 -> 1378718 | D55: 1253380 | E55: =B55-C55 -> -23572.37 | F55: =(B55-C55)/C55 -> -0.017097311 | G55: =(C55-D55) -> 125338 | H55: =(C55-D55)/D55 -> 0.1 | K55: =B55-L55 -> 6208.69 | L55: 1348936.9 | M55: =B55-D55 -> 101765.63 | N55: =(B55-D55)/D55 -> 0.081192958 | Q55: 1137132 | R55: =B55-Q55 -> 218013.63
A56: Dec | B56: 1229367.8 | C56: =D56*1.1 -> 1428121.2 | D56: 1298292 | E56: =B56-C56 -> -198753.44 | F56: =(B56-C56)/C56 -> -0.13917127 | G56: =(C56-D56) -> 129829.2 | H56: =(C56-D56)/D56 -> 0.1 | K56: =B56-L56 -> 22011.97 | L56: 1207355.8 | M56: =B56-D56 -> -68924.24 | N56: =(B56-D56)/D56 -> -0.053088396 | Q56: 1137132 | R56: =B56-Q56 -> 92235.76 | S56: 1194362 | T56: =B56-S56 -> 35005.76
A57: Jan | B57: 1716022.6 | C57: =D57*1.1 -> 1570314.9 | D57: 1427559 | E57: =B57-C57 -> 145707.73 | F57: =(B57-C57)/C57 -> 0.09278886 | G57: =(C57-D57) -> 142755.9 | H57: =(C57-D57)/D57 -> 0.1 | K57: =B57-L57 -> 146161.73 | L57: 1569860.9 | M57: =B57-D57 -> 288463.63 | N57: =(B57-D57)/D57 -> 0.20206775 | Q57: 1290932 | R57: =B57-Q57 -> 425090.63 | S57: 1478137 | T57: =B57-S57 -> 237885.63
A58: Feb | B58: 1372678.4 | C58: =D58*1.1 -> 1628535.7 | D58: 1480487 | E58: =B58-C58 -> -255857.33 | F58: =(B58-C58)/C58 -> -0.15710882 | G58: =(C58-D58) -> 148048.7 | H58: =(C58-D58)/D58 -> 0.1 | K58: =B58-L58 -> 45735.6 | L58: 1326942.8 | M58: =B58-D58 -> -107808.63 | N58: =(B58-D58)/D58 -> -0.072819707 | Q58: 796680 | R58: =B58-Q58 -> 575998.37 | S58: 905664 | T58: =B58-S58 -> 467014.37
A59: Mar | B59: 680212.62 | C59: =D59*1.1 -> 1195124.7 | D59: 1086477 | E59: =B59-C59 -> -514912.08 | F59: =(B59-C59)/C59 -> -0.43084381 | G59: =(C59-D59) -> 108647.7 | H59: =(C59-D59)/D59 -> 0.1 | K59: =B59-L59 -> 59860.97 | L59: 620351.65 | M59: =B59-D59 -> -406264.38 | N59: =(B59-D59)/D59 -> -0.37392819 | Q59: 237285 | R59: =B59-Q59 -> 442927.62 | S59: 360101 | T59: =B59-S59 -> 320111.62
A60: Apr | B60: 226419.77 | C60: =D60*1.1 -> 735468.8 | D60: 668608 | E60: =B60-C60 -> -509049.03 | F60: =(B60-C60)/C60 -> -0.69214225 | G60: =(C60-D60) -> 66860.8 | H60: =(C60-D60)/D60 -> 0.1 | K60: =B60-L60 -> 35853 | L60: 190566.77 | M60: =B60-D60 -> -442188.23 | N60: =(B60-D60)/D60 -> -0.66135647 | Q60: 61799.69 | R60: =B60-Q60 -> 164620.08 | S60: 127423 | T60: =B60-S60 -> 98996.77
B61: =SUM(B53:B60) -> 8364602.8 | C61: =SUM(C53:C60) -> 9375264.8 | D61: =SUM(D53:D60) -> 8522968 | E61: =B61-C61 -> -1010662 | G61: =(C61-D61) -> 852296.8 | H61: =(C61-D61)/D61 -> 0.1 | K61: =SUM(K51:K60) -> 315831.96 | L61: =SUM(L53:L60) -> 8048770.8 | M61: =B61-D61 -> -158365.22 | N61: =(B61-D61)/D61 -> -0.018580994 | Q61: =SUM(Q53:Q60) -> 6252886.1 | R61: =B61-Q61 -> 2111716.7
A62: Occupancy
B63: OTB @ 09 Dec 2019 | D63: LY Actual | E63: Variance to LY | I63: Variance last 7 days | J63: as @ 03 June 2014 | K63: Variance last 14 days | L63: OTB @ 25 Nov 2019 | M63: Actual vrs LY | Q63: OTB @ 8 Nov 2018 | R63: Variance OTB vrs LY OTB
A64: Mar | B64: 0.88 | C64: 2852 | D64: 0.92 | E64: 2905 | G64: -0.04 | I64: =B64-J64 -> -365.12 | J64: 366 | L64: 0.88 | M64: =B64-D64 -> -0.04 | N64: =(B64-D64)/D64 -> -0.043478261
A65: Apr | B65: 0.71 | C65: 2202 | D65: 0.6 | E65: 1827 | G65: 0.11 | I65: =B65-J65 -> -365.29 | J65: 366 | L65: 0.71 | M65: =B65-D65 -> 0.11 | N65: =(B65-D65)/D65 -> 0.18333333
A66: May | B66: 0.63 | C66: 2050 | D66: 0.63 | E66: 1956 | G66: 0 | I66: =B66-J66 -> -365.37 | J66: 366 | L66: 0.63 | M66: =B66-D66 -> 0 | N66: =(B66-D66)/D66 -> 0
A67: Jun | B67: 0.57 | C67: 1827 | D67: 0.52 | E67: 1558 | G67: 0.05 | I67: =B67-J67 -> -365.43 | J67: 366 | L67: 0.57 | M67: =B67-D67 -> 0.05 | N67: =(B67-D67)/D67 -> 0.096153846
A68: July | B68: 0.69 | C68: 2227 | D68: 0.55 | E68: 1714 | G68: 0.14 | I68: =B68-J68 -> -365.31 | J68: 366 | L68: 0.69 | M68: =B68-D68 -> 0.14 | N68: =(B68-D68)/D68 -> 0.25454545
A69: Aug | B69: 0.67 | C69: 2153 | D69: 0.56 | E69: 1761 | G69: 0.11 | I69: =B69-J69 -> -479.33 | J69: 480 | L69: 0.67 | M69: =B69-D69 -> 0.11 | N69: =(B69-D69)/D69 -> 0.19642857
A70: Sept | B70: 0.67 | D70: 0.64 | E70: 1945 | G70: 0.03 | I70: =B70-J70 -> -793.33 | J70: 794 | L70: 0.67 | M70: =B70-D70 -> 0.03 | N70: =(B70-D70)/D70 -> 0.046875
A71: Oct | B71: 0.84 | D71: 0.75 | E71: 2304 | G71: 0.09 | I71: =B71-J71 -> -386.16 | J71: 387 | L71: 0.84 | M71: =B71-D71 -> 0.09 | N71: =(B71-D71)/D71 -> 0.12
A72: Nov | B72: 0.87 | D72: 0.91 | E72: 2736 | G72: -0.04 | I72: =B72-J72 -> -357.13 | J72: 358 | L72: 0.87 | M72: =B72-D72 -> -0.04 | N72: =(B72-D72)/D72 -> -0.043956044
A73: Dec | B73: 0.89 | D73: 0.88 | E73: 2820 | G73: 0.01 | L73: 0.89 | M73: =B73-D73 -> 0.01 | N73: =(B73-D73)/D73 -> 0.011363636
A74: Jan | B74: 0.82 | D74: 0.85 | E74: 2747 | G74: 0.28 | L74: 0.82 | M74: =B74-D74 -> -0.03 | N74: =(B74-D74)/D74 -> -0.035294118
A75: Feb | B75: 0.94 | D75: 0.92 | E75: 2717 | G75: 0.02 | L75: 0.94 | M75: =B75-D75 -> 0.02 | N75: =(B75-D75)/D75 -> 0.02173913
A76: Oct | B76: 0.52 | C76: 1070 | D76: 0.57 | E76: 1490 | G76: -0.05 | L76: 0.52 | M76: =B76-D76 -> -0.05 | N76: =(B76-D76)/D76 -> -0.087719298
A77: Nov | B77: 0.72 | C77: 1808 | D77: 0.69 | E77: 1744 | G77: 0.03 | L77: 0.72 | M77: =B77-D77 -> 0.03 | N77: =(B77-D77)/D77 -> 0.043478261
A78: Dec | B78: 0.53 | C78: 1384 | D78: 0.59 | E78: 1415 | G78: -0.06 | L78: 0.53 | M78: =B78-D78 -> -0.06 | N78: =(B78-D78)/D78 -> -0.10169492
A79: Jan | B79: 0.47 | C79: 1212 | D79: 0.47 | E79: 1004 | G79: 0 | L79: 0.47 | M79: =B79-D79 -> 0 | N79: =(B79-D79)/D79 -> 0
A80: Feb | B80: 0.83 | C80: 2050 | D80: 0.68 | E80: 1563 | G80: 0.12 | L80: 0.83 | M80: =B80-D80 -> 0.15 | N80: =(B80-D80)/D80 -> 0.22058824
A81: Mar | B81: 0.72 | C81: 1887 | D81: 0.73 | E81: 1896 | L81: 0.72 | M81: =B81-D81 -> -0.01 | N81: =(B81-D81)/D81 -> -0.01369863
A82: Apr | B82: 0.62 | C82: 1558 | D82: 0.66 | E82: 1612 | L82: 0.62 | M82: =B82-D82 -> -0.04 | N82: =(B82-D82)/D82 -> -0.060606061
A83: May | B83: 0.5 | C83: 1293 | D83: 0.63 | E83: 701 | L83: 0.5 | M83: =B83-D83 -> -0.13 | N83: =(B83-D83)/D83 -> -0.20634921
A84: Apr | B84: 0.304 | C84: 371 | D84: 0.353 | E84: 424 | G84: =B84-D84 -> -0.049 | K84: 0.04 | L84: 0.304 | M84: =B84-D84 -> -0.049 | N84: =(B84-D84)/D84 -> -0.1388102
A85: May | B85: 0.19 | C85: 247 | D85: 0.3 | E85: 349 | G85: =B85-D85 -> -0.11 | K85: 0.08 | L85: 0.19 | M85: =B85-D85 -> -0.11 | N85: =(B85-D85)/D85 -> -0.36666667
A86: June | B86: 0.088 | C86: 110 | D86: 0.138 | E86: 166 | G86: =B86-D86 -> -0.05 | K86: 0.002 | L86: 0.088 | M86: =B86-D86 -> -0.05 | N86: =(B86-D86)/D86 -> -0.36231884
A87: July | B87: 0.274 | C87: 347 | D87: 0.183 | E87: 230 | G87: =B87-D87 -> 0.091 | L87: 0.274 | M87: =B87-D87 -> 0.091 | N87: =(B87-D87)/D87 -> 0.49726776
A88: August | B88: 0.22 | C88: 283 | D88: 0.2906 | E88: 356 | G88: =B88-D88 -> -0.0706 | L88: 0.22 | M88: =B88-D88 -> -0.0706 | N88: =(B88-D88)/D88 -> -0.24294563
A89: September | B89: 0.33 | D89: 0.443 | E89: 513 | G89: =B89-D89 -> -0.113 | K89: 0.03 | L89: 0.33 | M89: =B89-D89 -> -0.113 | N89: =(B89-D89)/D89 -> -0.25507901
A90: November | B90: 0.62 | D90: 0.697 | K90: 0 | L90: 0.62 | M90: =B90-D90 -> -0.077 | N90: =(B90-D90)/D90 -> -0.11047346
A91: December | B91: 0.49 | D91: 0.585 | K91: -0.01 | L91: 0.49 | M91: =B91-D91 -> -0.095 | N91: =(B91-D91)/D91 -> -0.16239316
A92: January | B92: 0.62 | D92: 0.816 | K92: 0.01 | L92: 0.62 | M92: =B92-D92 -> -0.196 | N92: =(B92-D92)/D92 -> -0.24019608
A93: Feb | B93: 0.84 | D93: 0.93 | L93: 0.84 | M93: =B93-D93 -> -0.09 | N93: =(B93-D93)/D93 -> -0.096774194
A94: March | B94: 0.64 | D94: 0.77 | K94: 0.03 | L94: 0.64 | M94: =B94-D94 -> -0.13 | N94: -0.57458598
A95: Apr | B95: 0.39 | D95: 0.3 | L95: 0.39 | M95: =B95-D95 -> 0.09 | N95: =(B95-D95)/D95 -> 0.3
A96: May | B96: 0.28 | D96: 0.206 | K96: 0.02 | L96: 0.28 | M96: =B96-D96 -> 0.074 | N96: =(B96-D96)/D96 -> 0.3592233
A97: June | B97: 0.3 | D97: loss | K97: 0.01 | L97: 0.3 | M97: =B97-D97 -> #VALUE! | N97: =(B97-D97)/D97 -> #VALUE!
A98: July | B98: 0.247 | K98: =L98-B98 -> 0 | L98: 0.247 | M98: =B98-D98 -> 0.247 | N98: =(B98-D98)/D98 -> #DIV/0!
A99: Aug | B99: 0.39 | D99: 0.22 | E99: 0.17 | K99: =B99-L99 -> 0 | L99: 0.39 | M99: =B99-D99 -> 0.17 | N99: =(B99-D99)/D99 -> 0.77272727
A100: Sept | B100: 0.59 | D100: 0.35 | E100: 0.16 | K100: =B100-L100 -> 0 | L100: 0.59 | M100: =B100-D100 -> 0.24 | N100: =(B100-D100)/D100 -> 0.68571429
...

Sheet Revenue
A2: Grande Roche Revenue On the Books @ 14 August 2026
B3: OTB 14.08.26 | C3: OTB 29.07.26 | D3: Variance | E3: Last Year Actual | F3: OTB vs LY Actual | G3: Budget / Target | H3: Variance last 7 days | I3: as @ 03 June 2014 | J3: OTB vs Target | K3: as @ 8 Nov 2017 | L3: Variance 2018 vrs 2017 | M3: OTB @ 8 Nov 2018 | N3: LY Actal vs Target | O3: OTB 25.05.22 | P3: Variance OTB Current vs LY
A4: 46204 | B4: 435432.83 | C4: 432236.3 | D4: =B4-C4 -> 3196.5217 | E4: 863725.25 | F4: =B4-E4 -> -428292.43 | N4: =E4-G4 -> 863725.25 | O4: 294981.16 | P4: =B4-O4 -> 140451.67 | Q4: =(B4-E4)/E4 -> -0.49586651
A5: 46235 | B5: 351047.55 | C5: 325201.4 | D5: =B5-C5 -> 25846.148 | E5: 727787.78 | F5: =B5-E5 -> -376740.23 | N5: =E5-G5 -> 727787.78 | O5: 294981.16 | P5: =B5-O5 -> 56066.388 | Q5: =(B5-E5)/E5 -> -0.51765122
A6: 46266 | B6: 1769805.8 | C6: 1772264.3 | D6: =B6-C6 -> -2458.5217 | E6: 740532.12 | F6: 119243.9 | N6: 740532.12 | O6: 294981.16 | P6: 564794.86 | Q6: 0.16102461
A7: 46296 | B7: 1145575.6 | C7: 1123059.8 | D7: =B7-C7 -> 22515.843 | E7: 1689533.9 | F7: =B7-E7 -> -543958.28 | N7: =E7-G7 -> 1689533.9 | O7: 294981.16 | P7: =B7-O7 -> 850594.46 | Q7: =(B7-E7)/E7 -> -0.3219576
A8: 46327 | B8: 2324453.2 | C8: 1920241.7 | D8: =B8-C8 -> 404211.48 | E8: 2489720.7 | F8: =B8-E8 -> -165267.57 | N8: =E8-G8 -> 2489720.7 | O8: 294981.16 | P8: =B8-O8 -> 2029472 | Q8: =(B8-E8)/E8 -> -0.066379961
A9: 46357 | B9: 1371059.3 | C9: 1224549.7 | D9: =B9-C9 -> 146509.63 | E9: 2575263.1 | F9: =B9-E9 -> -1204203.8 | N9: =E9-G9 -> 2575263.1 | O9: 294981.16 | P9: =B9-O9 -> 1076078.2 | Q9: =(B9-E9)/E9 -> -0.46760418
A10: 46388 | B10: 1956805 | E10: 3549116.3 | F10: =B10-E10 -> -1592311.3 | N10: =E10-G10 -> 3549116.3 | O10: 294981.16 | P10: =B10-O10 -> 1661823.8 | Q10: =(B10-E10)/E10 -> -0.44865007
A11: TOTAL | B11: =SUM(B4:B10) -> 9354179.3 | C11: =SUM(C4:C10) -> 6797553.2 | D11: =SUM(D4:D10) -> 599821.1 | E11: =SUM(E4:E10) -> 12635679 | F11: =B11-E11 -> -3281499.9 | G11: 1508477 | J11: =B11-G11 -> 7845702.2 | N11: =E11-G11 -> 11127202 | O11: 294981.16 | P11: =B11-O11 -> 9059198.1
A12: Occupancy
B13: OTB 14.08.26 | C13: OTB 29.07.26 | D13: Variance | E13: Last Year Actual | F13: OTB vs LY Actual | G13: Room Nights | K13: as @ 8 Nov 2017 | L13: Variance 2018 vrs 2017 | M13: OTB @ 8 Nov 2018 | N13: LY Actal vs Target | O13: OTB 25.05.22 | P13: Variance OTB Current vs LY
A14: 46204 | B14: 0.1238 | C14: 0.1238 | D14: =B14-C14 -> 0 | E14: 0.252 | F14: =B14-E14 -> -0.1282 | G14: 66 | O14: 0.0947 | P14: =#REF!-O14 -> #REF!
A15: 46235 | B15: 0.101 | C15: 0.092 | D15: =B15-C15 -> 0.009 | E15: 0.2541 | F15: =B15-E15 -> -0.1531 | G15: 66 | O15: 0.0947 | P15: =#REF!-O15 -> #REF!
A16: 46266 | B16: 0.356 | C16: 0.348 | D16: =B16-C16 -> 0.008 | E16: 0.239 | F16: =B16-E16 -> 0.117 | G16: 66 | O16: 0.0947 | P16: =#REF!-O16 -> #REF!
A17: 46296 | B17: 0.327 | C17: 0.284 | D17: =B17-C17 -> 0.043 | E17: 0.277 | F17: =B17-E17 -> 0.05 | G17: 66 | O17: 0.0947 | P17: =#REF!-O17 -> #REF!
A18: 46327 | B18: 0.423 | C18: 0.365 | D18: =B18-C18 -> 0.058 | E18: 0.499 | F18: =B18-E18 -> -0.076 | G18: 66 | O18: 0.0947 | P18: =#REF!-O18 -> #REF!
A19: 46357 | B19: 0.254 | C19: 0.229 | D19: =B19-C19 -> 0.025 | E19: 0.463 | F19: =B19-E19 -> -0.209 | G19: 66 | O19: 0.0947 | P19: =#REF!-O19 -> #REF!
A20: 46388 | B20: 0.377 | E20: 0.663 | F20: =B20-E20 -> -0.286 | G20: 66 | O20: 0.0947 | P20: =#REF!-O20 -> #REF!
A21: Average Room Rate
B22: OTB 14.08.26 | C22: OTB 29.07.26 | D22: Variance | E22: Last Year Actual | F22: OTB vs LY Actual | K22: as @ 8 Nov 2017 | L22: Variance 2018 vrs 2017 | M22: OTB @ 8 Nov 2018 | N22: LY Actal vs Target | O22: OTB 25.05.22 | P22: Variance OTB Current vs LY
A23: 46204 | B23: 3690.1087 | C23: 3663.0195 | D23: =B23-C23 -> 27.089167 | E23: 3855.9163 | F23: =B23-E23 -> -165.80761 | O23: 3241.55 | P23: =B23-O23 -> 448.5587 | Q23: =(B23-E23)/E23 -> -0.043000832
A24: 46235 | B24: 3734.5484 | C24: 3737.9471 | D24: =B24-C24 -> -3.3987453 | E24: 3465.6561 | F24: =B24-E24 -> 268.89227 | O24: 3241.55 | P24: =B24-O24 -> 492.99838
A25: 46266 | B25: 5346.8452 | C25: 5469.9515 | D25: =B25-C25 -> -123.10629 | E25: 3509.6309 | F25: =B25-E25 -> 1837.2143 | O25: 3241.55 | P25: =B25-O25 -> 2105.2952
A26: 46296 | B26: 3648.33 | C26: 4113.7721 | D26: =B26-C26 -> -465.44207 | E26: 4100.8104 | F26: =B26-E26 -> -452.48043 | O26: 3241.55 | P26: =B26-O26 -> 406.77999
A27: 46327 | B27: 5914.6391 | C27: 5664.4298 | D27: =B27-C27 -> 250.20934 | E27: 5483.9664 | F27: =B27-E27 -> 430.67274 | O27: 3241.55 | P27: =B27-O27 -> 2673.0891
A28: 46357 | B28: 5619.0955 | C28: 5566.1349 | D28: =B28-C28 -> 52.960644 | E28: 5852.8707 | F28: =B28-E28 -> -233.77519 | O28: 3241.55 | P28: =B28-O28 -> 2377.5455
A29: 46388 | B29: 5406 | E29: 5780.3197 | F29: =B29-E29 -> -374.31967 | O29: 3241.55 | P29: =B29-O29 -> 2164.45
A30: RevPAR
B31: OTB 14.08.26 | C31: OTB 29.07.26 | D31: Variance | E31: Last Year Actual | F31: OTB vs LY Actual | K31: as @ 8 Nov 2017 | L31: Variance 2018 vrs 2017 | M31: OTB @ 8 Nov 2018 | N31: LY Actal vs Target
A32: 46204 | B32: =B4/931 -> 467.70443 | C32: =C4/931 -> 464.271 | D32: =B32-C32 -> 3.4334283 | E32: =E4/961 -> 898.77758 | F32: =B32-E32 -> -431.07315
A33: 46235 | B33: =B5/931 -> 377.06504 | C33: =C5/931 -> 349.30333 | D33: =B33-C33 -> 27.761706 | E33: =E4/961 -> 898.77758 | F33: =B33-E33 -> -521.71254
A34: 46266 | B34: =B6/930 -> 1903.017 | C34: =C6/930 -> 1905.6605 | D34: =B34-C34 -> -2.6435718 | E34: =E6/930 -> 796.2711 | F34: =B34-E34 -> 1106.7459
A35: 46296 | B35: =B7/930 -> 1231.8017 | C35: =C7/930 -> 1207.5912 | D35: =B35-C35 -> 24.210584 | E35: =E7/930 -> 1816.7031 | F35: =B35-E35 -> -584.90137
A36: 46327 | B36: =B8/930 -> 2499.412 | C36: =C8/930 -> 2064.776 | D36: =B36-C36 -> 434.636 | E36: =E8/930 -> 2677.1191 | F36: =B36-E36 -> -177.70706
A37: 46357 | B37: =B9/930 -> 1474.2573 | C37: =C9/930 -> 1316.7201 | D37: =B37-C37 -> 157.53724 | E37: =E9/930 -> 2769.1001 | F37: =B37-E37 -> -1294.8428
A38: 46388 | B38: =B10/930 -> 2104.0914 | E38: =E10/930 -> 3816.2541 | F38: =B38-E38 -> -1712.1627

Sheet Historical Stats
A1: Revenue | B1: 2015 | C1: 2016 | D1: 2017 | E1: 2018 | F1: 2019 | G1: 2020 | H1: 2021 | I1: 2022 | J1: 2023 | K1: 2024 | L1: 2024 vs 2023 | M1: 2025 | N1: 2025 vs 2024 | O1: 2026 | P1: 2026 vs 2025
A2: Jan | B2: 1718793 | C2: 2023712 | D2: 2418238 | E2: 1623338 | F2: 1207727 | G2: 1522489 | H2: 72956 | I2: 659046 | J2: 2498047 | K2: 2485056 | L2: =K2-J2 -> -12991 | M2: 3204276 | N2: =M2-K2 -> 719220 | O2: 3549116.3 | P2: =O2-M2 -> 344840.28
A3: Feb | B3: 1765442 | C3: 1975466 | D3: 2216803 | E3: 2361566 | F3: 1612636 | G3: 1444683 | H3: 83348 | I3: 840294 | J3: 2499745 | K3: 3228558 | L3: =K3-J3 -> 728813 | M3: 2887163 | N3: =M3-K3 -> -341395 | O3: 3704860.7 | P3: =O3-M3 -> 817697.68
A4: Mar | B4: 1471651 | C4: 1659573 | D4: 1463345 | E4: 1408186 | F4: 1175922 | G4: 602778 | H4: 277529 | I4: 1467641 | J4: 1749406 | K4: 2361474 | L4: =K4-J4 -> 612068 | M4: 2027095 | N4: =M4-K4 -> -334379 | O4: 2617605.3 | P4: =O4-M4 -> 590510.31
A5: Apr | B5: 824985 | C5: 968707 | D5: 1008032 | E5: 728074 | F5: 613675 | G5: 0 | H5: 224332 | I5: 574007 | J5: 1086555 | K5: 1265502 | L5: =K5-J5 -> 178947 | M5: 907467 | N5: =M5-K5 -> -358035 | O5: 1256934.5 | P5: =O5-M5 -> 349467.46
A6: May | B6: 459536 | C6: 618319 | D6: 565371 | E6: 550572 | F6: 375263 | G6: 0 | H6: 219470 | I6: 807859 | J6: 654864 | K6: 1103983 | L6: =K6-J6 -> 449119 | M6: 924687 | N6: =M6-K6 -> -179296 | O6: 1047829.8 | P6: =O6-M6 -> 123142.77
A7: Jun | B7: 214357 | C7: 242401 | D7: 74892 | E7: 17834 | F7: 0 | G7: 0 | H7: 110446 | I7: 512847 | J7: 696645 | K7: 563280 | L7: =K7-J7 -> -133365 | M7: 110096.24 | N7: =M7-K7 -> -453183.76 | O7: 156811.45 | P7: =O7-M7 -> 46715.209
A8: Jul | B8: 332063 | C8: 531416 | D8: 374229 | E8: 454148 | F8: 153553 | G8: 0 | H8: 9730 | I8: 307176 | J8: 494973 | K8: 312573 | L8: =K8-J8 -> -182400 | M8: 791881 | N8: =M8-K8 -> 479308 | O8: 435432.83 | P8: =O8-M8 -> -356448.17
A9: Aug | B9: 537492 | C9: 623992 | D9: 570476 | E9: 599899 | F9: 208432 | G9: 97630 | H9: 124240 | I9: 683405 | J9: 915373 | K9: 679553 | L9: =K9-J9 -> -235820 | M9: 727788 | N9: =M9-K9 -> 48235 | P9: =O9-M9 -> -727788
A10: Sept | B10: 620453 | C10: 742639 | D10: 862336 | E10: 632926 | F10: 447850 | G10: 91121 | H10: 166491 | I10: 533400 | J10: 1119922 | K10: 731645 | L10: =K10-J10 -> -388277 | M10: 740532 | N10: =M10-K10 -> 8887 | P10: =O10-M10 -> -740532
A11: Oct | B11: 620453 | C11: 1265295 | D11: 1190523 | E11: 1026027 | F11: 702864 | G11: 23158 | H11: 417374 | I11: 888602 | K11: 1449720 | L11: =K11-J11 -> 1449720 | M11: 1689533.9 | N11: =M11-K11 -> 239813.9 | P11: =O11-M11 -> -1689533.9
A12: Nov | B12: 1690415 | C12: 2330335 | D12: 2072040 | E12: 1420642 | F12: 985451 | G12: 194846 | H12: 896516 | I12: 1295261 | J12: 2266072 | K12: 2219563 | L12: =K12-J12 -> -46509 | M12: 2476242 | N12: =M12-K12 -> 256679 | P12: =O12-M12 -> -2476242
A13: Dec | B13: 1556105 | C13: 1772437 | D13: 1870761 | E13: 1217273 | F13: 1115715 | G13: 101357 | H13: 545030 | I13: 2355614 | J13: 2209046 | K13: 2918132 | L13: =K13-J13 -> 709086 | M13: 2575263.1 | N13: =M13-K13 -> -342868.88 | P13: =O13-M13 -> -2575263.1
A14: TOTAL | B14: =SUM(B2:B13) -> 11811745 | C14: =SUM(C2:C13) -> 14754292 | D14: =SUM(D2:D13) -> 14687046 | E14: =SUM(E2:E13) -> 12040485 | F14: =SUM(F2:F13) -> 8599088 | G14: =SUM(G2:G13) -> 4078062 | H14: =SUM(H2:H13) -> 3147462 | I14: =SUM(I2:I13) -> 10925152 | ... K14: =SUM(K2:K13) -> 19319039 | L14: =K14-J14 -> 3128391 | M14: =SUM(M2:M13) -> 19062024 | N14: =M14-K14 -> -257014.74 | O14: =SUM(O2:O13) -> 12768591 | P14: =O14-M14 -> -6293433.5
A15: Occupancy | B15: 2015 | C15: 2016 | D15: 2017 | E15: 2018 | F15: 2019 | G15: 2020 | H15: 2021 | I15: 2022 | J15: 2023 | K15: 2024 | L15: 2024 vs 2023 | M15: 2025 | N15: 2025 vs 2024 | O15: 2026 | P15: 2026 vs 2025
A16: Jan | B16: 0.7614 | C16: 0.7192 | D16: 0.7353 | E16: 0.5209 | F16: 0.3927 | G16: 0.481 | H16: 0.0387 | I16: 0.2169 | J16: 0.5551 | K16: 0.5203 | L16: =K16-J16 -> -0.0348 | M16: 0.589 | N16: =M16-K16 -> 0.0687 | O16: 0.6543 | P16: =O16-M16 -> 0.0653
A17: Feb | B17: 0.861 | C17: 0.7919 | D17: 0.815 | E17: 0.7672 | F17: 0.5218 | G17: 0.4826 | H17: 0.033 | I17: 0.27 | J17: 0.6778 | K17: 0.7041 | L17: =K17-J17 -> 0.0263 | M17: 0.6509 | N17: =M17-K17 -> -0.0532 | O17: 0.7405 | P17: =O17-M17 -> 0.0896
A18: Mar | B18: 0.7459 | C18: 0.6601 | D18: 0.5558 | E18: 0.4968 | F18: 0.4215 | G18: 0.3579 | H18: 0.1181 | I18: 0.5366 | J18: 0.5665 | K18: 0.5702 | L18: =K18-J18 -> 0.0037 | M18: 0.4745 | N18: =M18-K18 -> -0.0957 | O18: 0.5629 | P18: =O18-M18 -> 0.0884
A19: Apr | B19: 0.6369 | C19: 0.6059 | D19: 0.4583 | E19: 0.3829 | F19: 0.3196 | G19: 0 | H19: 0.103 | I19: 0.207 | J19: 0.4155 | K19: 0.3473 | L19: =K19-J19 -> -0.0682 | M19: 0.229 | N19: =M19-K19 -> -0.1183 | O19: 0.3151 | P19: =O19-M19 -> 0.0861
A20: May | B20: 0.4011 | C20: 0.4182 | D20: 0.3017 | E20: 0.2756 | F20: 0.2312 | G20: 0 | H20: 0.1065 | I20: 0.2994 | J20: 0.3777 | K20: 0.3392 | L20: =K20-J20 -> -0.0385 | M20: 0.2633 | N20: =M20-K20 -> -0.0759 | O20: 0.2868 | P20: =O20-M20 -> 0.0235
A21: Jun | B21: 0.228 | C21: 0.2401 | D21: 0.4266 | E21: 0.0114 | F21: 0 | G21: 0 | H21: 0.0536 | I21: 0.1914 | J21: 0.3695 | K21: 0.19 | L21: =K21-J21 -> -0.1795 | M21: 0.0495 | N21: =M21-K21 -> -0.1405 | O21: 0.0528 | P21: =O21-M21 -> 0.0033
A22: Jul | B22: 0.2153 | C22: 0.3753 | D22: 0.2899 | E22: 0.1927 | F22: 0.161 | G22: 0 | H22: 0.0258 | I22: 0.3899 | J22: 0.2479 | K22: 0.107 | L22: =K22-J22 -> -0.1409 | M22: 0.223 | N22: =M22-K22 -> 0.116 | O22: 0.1238 | P22: =O22-M22 -> -0.0992
A23: Aug | B23: 0.4023 | C23: 0.3521 | D23: 0.3392 | E23: 0.3238 | F23: 0.2301 | G23: 1 | H23: 0.088 | I23: 0.4005 | J23: 0.4811 | K23: 0.2237 | L23: =K23-J23 -> -0.2574 | M23: 0.229 | N23: =M23-K23 -> 0.0053 | P23: =O23-M23 -> -0.229
A24: Sept | B24: 0.439 | C24: 0.4562 | D24: 0.485 | E24: 0.3278 | F24: 0.3369 | G24: 1 | H24: 0.0704 | I24: 0.2268 | J24: 0.4116 | K24: 0.227 | L24: =K24-J24 -> -0.1846 | M24: 0.2484 | N24: =M24-K24 -> 0.0214 | P24: =O24-M24 -> -0.2484
A25: Oct | B25: 0.439 | C25: 0.6685 | D25: 0.5691 | E25: 0.4905 | F25: 0.442 | G25: 0.0909 | H25: 0.1899 | I25: 0.2836 | K25: 0.3673 | L25: =K25-J25 -> 0.3673 | M25: 0.439 | N25: =M25-K25 -> 0.0717 | P25: =O25-M25 -> -0.439
A26: Nov | B26: 0.7596 | C26: 0.826 | D26: 0.6709 | E26: 0.4587 | F26: 0.3701 | G26: 0.1099 | H26: 0.247 | I26: 0.3296 | J26: 0.5602 | K26: 0.4946 | L26: =K26-J26 -> -0.0656 | M26: 0.489 | N26: =M26-K26 -> -0.0056 | P26: =O26-M26 -> -0.489
A27: Dec | B27: 0.5898 | C27: 0.6107 | D27: 0.5154 | E27: 0.3499 | F27: 0.364 | G27: 0.0474 | H27: 0.1513 | I27: 0.5363 | J27: 0.4964 | K27: 0.5328 | L27: =K27-J27 -> 0.0364 | M27: 0.4632 | N27: =M27-K27 -> -0.0696 | P27: =O27-M27 -> -0.4632
A28: TOTAL | B28: =SUM(B16:B27)/12 -> 0.53994167 | C28: =SUM(C16:C27)/12 -> 0.56035 | D28: =SUM(D16:D27)/12 -> 0.51351667 | E28: =SUM(E16:E27)/12 -> 0.38318333 | F28: =SUM(F16:F27)/12 -> 0.31590833 | G28: =SUM(G16:G27)/12 -> 0.297475 | H28: =SUM(H16:H27)/12 -> 0.10210833 | I28: =SUM(I16:I27)/12 -> 0.324 | J28: =SUM(J16:J27)/11 -> 0.46902727 | K28: =SUM(K16:K27)/12 -> 0.38529167 | L28: =K28-J28 -> -0.083735606 | M28: =SUM(M16:M27)/12 -> 0.36231667 | N28: =M28-K28 -> -0.022975 | O28: =SUM(O16:O27)/6 -> 0.45603333 | P28: =O28-M28 -> 0.093716667
A29: ADR | B29: 2015 | C29: 2016 | D29: 2017 | E29: 2018 | F29: 2019 | G29: 2020 | H29: 2021 | I29: 2022 | J29: 2023 | K29: 2024 | L29: 2024 vs 2023 | M29: 2025 | N29: 2025 vs 2024 | O29: 2026 | P29: 2026 vs 2025
A30: Jan | B30: 2516 | C30: 2687 | D30: 3076 | E30: 2956 | F30: 2960 | G30: 3346 | H30: 2026 | I30: 3414 | J30: 4722 | K30: 4970 | L30: =K30-J30 -> 248 | M30: 5661.27 | N30: =M30-K30 -> 691.27 | O30: 5780.3197 | P30: =O30-M30 -> 119.04967
A31: Feb | B31: 2272 | C31: 2460 | D31: 2795 | E31: 3157 | F31: 3366 | G31: 3602 | H31: 2976 | I31: 3718 | J31: 4385 | K31: 5100 | L31: =K31-J31 -> 715 | M31: 5110.02 | N31: =M31-K31 -> 10.02 | O31: 5806.9917 | P31: =O31-M31 -> 696.97166
A32: Mar | B32: 2180 | C32: 2469 | D32: 2426 | E32: 2612 | F32: 2806 | G32: 3107 | H32: 2477 | I32: 3641 | J32: 3450 | K32: 4309 | L32: =K32-J32 -> 859 | M32: 4445.39 | N32: =M32-K32 -> 136.39 | O32: 4874.4978 | P32: =O32-M32 -> 429.10779
A33: Apr | B33: 1465 | C33: 1800 | D33: 2108 | E33: 1811 | F33: 1923 | G33: 0 | H33: 2412 | I33: 3224 | J33: 2851 | K33: 3918 | L33: =K33-J33 -> 1067 | M33: 4260.41 | N33: =M33-K33 -> 342.41 | O33: 4290 | P33: =O33-M33 -> 29.59
A34: May | B34: 1272 | C34: 1530 | D34: 1728 | E34: 1841 | F34: 1653 | G34: 0 | H34: 2172 | I34: 2864 | J34: 1804 | K34: 3386 | L34: =K34-J34 -> 1582 | M34: 3654.89 | N34: =M34-K34 -> 268.89 | O34: 3838 | P34: =O34-M34 -> 183.11
A35: Jun | B35: 1134 | C35: 1731 | D35: 1227 | E35: 1486 | F35: 0 | G35: 0 | H35: 2300 | I35: 2897 | J35: 2067 | K35: 3182.38 | L35: =K35-J35 -> 1115.38 | M35: 2393.3966 | N35: =M35-K35 -> -788.9834 | O35: 3200.2337 | P35: =O35-M35 -> 806.83712
A36: Jul | B36: 1573 | C36: 1312 | D36: 1218 | E36: 2193 | F36: 1476 | G36: 0 | H36: 2432 | I36: 2477 | J36: 2115 | K36: 3034.69 | L36: =K36-J36 -> 919.69 | M36: 3535.19 | N36: =M36-K36 -> 500.5 | O36: 3690.1087 | P36: =O36-M36 -> 154.9187
A37: Aug | B37: 1273 | C37: 1633 | D37: 1728 | E37: 1759 | F37: 1680 | G37: 2169 | H37: 1592 | I37: 2648 | J37: 2878 | K37: 3160.71 | L37: =K37-J37 -> 282.71 | M37: 3465.66 | N37: =M37-K37 -> 304.95 | P37: =O37-M37 -> -3465.66
A38: Sept | B38: 1449 | C38: 1550 | D38: 1774 | E38: 1872 | F38: 1777 | G38: 2169 | H38: 2729 | I38: 2540 | J38: 3209 | K38: 3167.29 | L38: =K38-J38 -> -41.71 | M38: 3509.63 | N38: =M38-K38 -> 342.34 | P38: =O38-M38 -> -3509.63
A39: Oct | B39: 1449 | C39: 1757 | D39: 1980 | E39: 1976 | F39: 1920 | G39: 1929 | H39: 2358 | I39: 3340 | K39: 4106.86 | L39: =K39-J39 -> 4106.86 | M39: 4100.81 | N39: =M39-K39 -> -6.05 | P39: =O39-M39 -> -4100.81
A40: Nov | B40: 2184 | C40: 2596 | D40: 3033 | E40: 3009 | F40: 2941 | G40: 2706 | H40: 4020 | I40: 4375 | J40: 4349 | K40: 4825.14 | L40: =K40-J40 -> 476.14 | M40: 2662.6258 | N40: =M40-K40 -> -2162.5142 | P40: =O40-M40 -> -2662.6258
A41: Dec | B41: 2481 | C41: 2868 | D41: 3389 | E41: 3254 | F41: 3254 | G41: 2598 | H41: 3921 | I41: 4692 | J41: 4621 | K41: 5699.48 | L41: =K41-J41 -> 1078.48 | M41: 5852.8707 | N41: =M41-K41 -> 153.39073 | P41: =O41-M41 -> -5852.8707
A42: TOTAL | B42: =SUM(B30:B41)/12 -> 1770.6667 | C42: =SUM(C30:C41)/12 -> 2032.75 | D42: =SUM(D30:D41)/12 -> 2206.8333 | E42: =SUM(E30:E41)/12 -> 2327.1667 | F42: =SUM(F30:F41)/12 -> 2146.3333 | G42: =SUM(G30:G41)/12 -> 1802.1667 | H42: =SUM(H30:H41)/12 -> 2617.9167 | I42: =SUM(I30:I41)/12 -> 3319.1667 | J42: =SUM(J30:J41)/11 -> 3313.7273 | K42: =SUM(K30:K41)/12 -> 4071.6292 | L42: =K42-J42 -> 757.90189 | M42: =SUM(M30:M41)/9 -> 5405.7959 | N42: =M42-K42 -> 1334.1667 | O42: =SUM(O30:O41)/6 -> 5246.6919 | P42: =O42-M42 -> -159.10398
A43: June 2017 - closed from 6-30 June
A44: June 2018 - closed from 5-30 June
A45: June 2019 - closed 1-30 June
A46: March 2020 - closed lock down 26-30 March
A47: April 2020 - closed lock down 1-30 April
A48: May 2020 - closed lockdown 1-31 May
A49: June 2020 - closed
A50: July 2020 - closed
A51: August 2020 - closed 1-25 August. All rom sblocked in a way that reports 100% occupancy.
A52: September 2020 - closed 5-30 Sept. All rom sblocked in a way that reports 100% occupanc
A53: July 2021 - closed 1-29 July
A54: July 2022 - a week here or there closed. Some nights on 100% which is not possible when compared to revenue

Sheet Sheet4
A1: Booking reference | B1: Guest names | C1: Check-in | D1: Check-out | E1: Channel | F1: Affiliated Channel | G1: Referral | H1: Room | I1: Booked-on date | J1: Modified-on date | K1: Cancelled-on date | L1: Booking status | M1: Occupancy | N1: Total price | O1: Connectivity status | P1: Connectivity last sent at | Q1: Guest title | R1: Guest name | S1: Guest first name | T1: Guest last name | U1: Guest address | V1: Guest address2 | W1: Guest state | X1: Guest postcode | Y1: Guest country | Z1: Guest email | AA1: Guest phone | AB1: GDPR consent | AC1: GDPR consent date | AD1: Promo code
A2: 567284087 | B2: Victoria Moya | C2: 45889 | D2: 45894 | E2: Agoda | F2: Private Sale | H2: 1 x Legacy Suite | I2: 45880.406 | K2: 45880.445 | L2: Cancelled | M2: 2 - 0 - 0 | N2: ZAR 21627.55 | O2: Delivered | P2: 45880.447 | Q2: -
A3: 1970859923 | B3: Janis Oberbrunner | C3: 46033 | D3: 46036 | E3: Agoda | F3: Retail | H3: 1 x Terrace Suite | I3: 46029.471 | K3: 46034.328 | L3: Cancelled | M3: 2 - 0 - 0 | N3: ZAR 42498.00 | O3: Delivered | P3: 46034.334 | Q3: -
A4: 1972277093 | B4: Lauriane Stehr | C4: 46037 | D4: 46041 | E4: Agoda | F4: Retail | H4: 1 x Terrace Suite | I4: 46033.712 | K4: 46038.374 | L4: Cancelled | M4: 2 - 0 - 0 | N4: ZAR 56664.00 | O4: Delivered | P4: 46038.377 | Q4: -
A5: 620361463 | B5: TEST TEST | C5: 46072 | D5: 46073 | E5: Agoda | F5: Private Sale | H5: 1 x Heritage Suite | I5: 46045.447 | K5: 46045.449 | L5: Cancelled | M5: 1 - 0 - 0 | N5: ZAR 8921.80 | O5: Delivered | P5: 46045.456 | Q5: -
A6: 1 x Terrace Suite - Grande Reserve Experience" | B6: 45822.554 | E6: Booked | F6: 4 - 0 - 0 | G6: ZAR 10340.00 | H6: Delivered | I6: 45822.56 | K6: Babalwa Nyoka | L6: Babalwa | M6: Nyoka | N6: Babalwa.nyoka@gmail.com | O6: 90 Ashley Drive | Q6: 3610 | R6: South Africa | S6: Babalwa.nyoka@gmail.com | T6: 728774036 | U6: FALSE | V6: 2025-06-14T00:00:00.000Z
A7: 1 x Terrace Suite - Book Direct save 15%" | B7: 45832.828 | E7: Booked | F7: 4 - 0 - 0 | G7: ZAR 44409.00 | H7: Delivered | I7: 45832.834 | K7: Mlungisi Kwini | L7: Mlungisi | M7: Kwini | N7: 204 Anderson Avenue | O7: Northcliff | Q7: 2195 | R7: South Africa | S7: mlungisi.kwini@lukhanyo.com | T7: 823301640 | U7: TRUE | V7: 2025-06-24T00:00:00.000Z
A8: 1 x Terrace Suite - Book Direct save 15%" | B8: 45832.839 | E8: Booked | F8: 4 - 0 - 0 | G8: ZAR 10766.00 | H8: Delivered | I8: 45832.841 | K8: Mlungisi Kwini | L8: Mlungisi | M8: Kwini | N8: 204 Anderson Avenue | O8: Northcliff | Q8: 2195 | R8: South Africa | S8: mlungisi.kwini@lukhanyo.com | T8: 823301640 | U8: TRUE | V8: 2025-06-24T00:00:00.000Z
A9: 1 x Heritage Suite - Book Direct save 15%" | B9: 45834.418 | E9: Booked | F9: 4 - 0 - 0 | G9: ZAR 15202.00 | H9: Delivered | I9: 45834.421 | K9: Julian Naik | L9: Julian | M9: Naik | N9: 15 Rimal, 334 Bryanston Drive | Q9: 2192 | R9: South Africa | S9: julian@spiritsandbubbles.co.za | T9: 27825626099 | U9: FALSE | V9: 2025-06-26T00:00:00.000Z
A10: 1 x Heritage Suite - Book Direct save 15%" | B10: 45876.872 | E10: Booked | F10: 36528 | G10: ZAR 25934.00 | H10: Delivered | I10: 45876.876 | K10: Morten Sommerfeldt | L10: Morten | M10: Sommerfeldt | N10: Prins Constantins Vej 5 | P10: Copenhagen | Q10: 2000 | R10: Denmark | S10: morten.westergaard@gmail.com | T10: 4528558665 | U10: FALSE | V10: 2025-08-07T00:00:00.000Z
A11: 1 x Studio - General - Breakfast included - Domestic" | B11: 45939.41 | E11: Booked | F11: 13 - 0 - 0 | G11: ZAR 77246.46 | H11: Delivered | I11: 45939.415 | J11: -
A12: 1 x Studio - Non-refundable - Breakfast included - Non-refundable" | B12: 45953.887 | E12: Booked | F12: 36559 | G12: ZAR 27246.80 | H12: Delivered | I12: 45953.889 | J12: -
A13: 1 x Legacy Room - General - Breakfast included - United Kingdom" | B13: 45974.642 | E13: Booked | F13: 3 - 0 - 0 | G13: ZAR 49183.20 | H13: Delivered | I13: 45974.647 | J13: -
A14: 1 x Legacy Room - General - Breakfast included - European Economic Area" | B14: 45978.65 | E14: Booked | F14: 2 - 0 - 0 | G14: ZAR 109296.00 | H14: Delivered | I14: 45978.655 | J14: -
A15: 1 x Garden Suite - Partially refundable - Breakfast included - Flexible 5 days" | B15: 46009.064 | E15: Booked | F15: 4 - 0 - 0 | G15: ZAR 20319.62 | H15: Delivered | I15: 46009.068 | J15: -
A16: 1 x Legacy Room - Non-refundable - Breakfast included - Non-refundable" | B16: 46024.515 | E16: Booked | F16: 36560 | G16: ZAR 9338.95 | H16: Delivered | I16: 46024.52 | J16: -
A17: 1 x Terrace Suite - General - Breakfast included" | B17: 46037.413 | E17: Booked | F17: 4 - 0 - 0 | G17: ZAR 40373.10 | H17: Delivered | I17: 46037.417 | J17: -
A18: 1 x Heritage Suite - Book Direct save 15%" | B18: 46037.868 | E18: Booked | F18: 4 - 0 - 0 | G18: ZAR 25338.00 | H18: Delivered | I18: 46037.872 | K18: Valery Borisov | L18: Valery | M18: Borisov | N18: 48B Regent‚Äôs Park Road | Q18: NW17SX | R18: United Kingdom | S18: borisovvn@yahoo.com | T18: 447586328973 | U18: FALSE | V18: 2026-01-15T00:00:00.000Z
A19: 1 x Terrace Suite - General - Breakfast included" | B19: 46044.723 | E19: Booked | F19: 3 - 0 - 0 | G19: ZAR 54648.00 | H19: Delivered | I19: 46044.726 | J19: -
A20: 5693386589 | B20: Frank Tippmann, | C20: 45939 | D20: 45945 | E20: Booking.com | F20: BDC | H20: 1 x Duplex Suite - General - Breakfast included - European Economic Area | I20: 45814.54 | L20: Booked | M20: 36527 | N20: ZAR 34228.80 | O20: Delivered | P20: 45814.544 | Q20: -
A21: 6794248259 | B21: Luke Cassell | C21: 45819 | D21: 45820 | E21: Booking.com | F21: BDC | H21: 1 x Studio - General - Breakfast included - Getaway Deal | I21: 45816.595 | L21: Booked | M21: 2 - 0 - 0 | N21: ZAR 3656.70 | O21: Delivered | P21: 45816.6 | Q21: -
A22: 6640931778 | B22: Stephen Rich | C22: 46073 | D22: 46075 | E22: Booking.com | F22: BDC | H22: 1 x Studio - General - Breakfast included - Domestic | I22: 45818.016 | K22: 46037.579 | L22: Cancelled | M22: 2 - 0 - 0 | N22: ZAR 15183.00 | O22: Delivered | P22: 46037.582 | Q22: -
A23: 5655435537 | B23: Ivo Schepers | C23: 45972 | D23: 45973 | E23: Booking.com | F23: BDC | H23: 1 x Studio - General - Breakfast included - European Economic Area | I23: 45819.375 | L23: Booked | M23: 2 - 0 - 0 | N23: ZAR 6832.80 | O23: Delivered | P23: 45819.379 | Q23: -
A24: 5665130610 | B24: Iain Burgess | C24: 45944 | D24: 45946 | E24: Booking.com | F24: BDC | H24: 1 x Studio - General - Breakfast included - United Kingdom | I24: 45821.444 | L24: Booked | M24: 2 - 0 - 0 | N24: ZAR 10578.60 | O24: Delivered | P24: 45821.447 | Q24: -
A25: 5357215519 | B25: Sfiso Mazibuko | C25: 45828 | D25: 45830 | E25: Booking.com | F25: BDC | H25: 1 x Studio - General - Breakfast included - Getaway Deal | I25: 45821.943 | L25: Booked | M25: 2 - 0 - 0 | N25: ZAR 7770.70 | O25: Delivered | P25: 45821.946 | Q25: -
A26: 5686314473 | B26: Helmut Richter | C26: 46018 | D26: 46021 | E26: Booking.com | F26: BDC | H26: 1 x Studio - General - Breakfast included - European Economic Area | I26: 45822.487 | K26: 45824.368 | L26: Cancelled | M26: 2 - 0 - 0 | N26: ZAR 18979.20 | O26: Delivered | P26: 45824.371 | Q26: -
A27: 5955611653 | B27: Sandra McDiarmid | C27: 46012 | D27: 46018 | E27: Booking.com | F27: BDC | H27: 1 x Studio - General - Breakfast included - Domestic | I27: 45823.668 | K27: 45824.605 | L27: Cancelled | M27: 2 - 0 - 0 | N27: ZAR 39476.70 | O27: Delivered | P27: 45824.611 | Q27: -
A28: 6755179000 | B28: Theo Basson, Christine Basson | C28: 45870 | D28: 45872 | E28: Booking.com | F28: BDC | H28: 2 x Studio - General - Breakfast included - Getaway Deal | I28: 45824.414 | L28: Booked | M28: 4 - 0 - 0 | N28: ZAR 18285.20 | O28: Delivered | P28: 45824.418 | Q28: -
A29: 5700688008 | B29: Kebonye Aubrey Kgwaadira | C29: 45826 | D29: 45830 | E29: Booking.com | F29: BDC | H29: 1 x Suite with Terrace - General - Breakfast included - Getaway Deal | I29: 45825.582 | L29: Booked | M29: 2 - 0 - 0 | N29: ZAR 21753.20 | O29: Delivered | P29: 45825.587 | Q29: -
A30: 5899806030 | B30: Gil Givoni | C30: 45907 | D30: 45911 | E30: Booking.com | F30: BDC | H30: 1 x Studio - General - Breakfast included - Getaway Deal | I30: 45833.882 | L30: Booked | M30: 1 - 0 - 0 | N30: ZAR 18316.65 | O30: Delivered | P30: 45833.886 | Q30: -
A31: 6259891503 | B31: Fiona Reynolds | C31: 46006 | D31: 46008 | E31: Booking.com | F31: BDC | H31: 2 x Studio - General - Breakfast included - Mobile(App) Rate | I31: 45834.336 | K31: 45973.44 | L31: Cancelled | M31: 4 - 0 - 0 | N31: ZAR 25812.00 | O31: Delivered | P31: 45973.444 | Q31: -
A32: 5583792421 | B32: Lara Klebor | C32: 46024 | D32: 46026 | E32: Booking.com | F32: BDC | H32: 3 x Studio - General - Breakfast included - European Economic Area | I32: 45835.461 | L32: Booked | M32: 5 - 0 - 0 | N32: ZAR 38718.00 | O32: Delivered | P32: 45835.464 | Q32: -
A33: 6405365691 | B33: Roland Vogt | C33: 45918 | D33: 45920 | E33: Booking.com | F33: BDC | H33: 1 x Duplex Suite - General - Breakfast included - Getaway Deal | I33: 45835.907 | L33: Booked | M33: 2 - 0 - 0 | N33: ZAR 10775.45 | O33: Delivered | P33: 45835.912 | Q33: -
A34: 5426292376 | B34: Holly Littlewood | C34: 45953 | D34: 45956 | E34: Booking.com | F34: BDC | H34: 1 x Duplex Suite - General - Breakfast included - United Kingdom | I34: 45837.914 | L34: Booked | M34: 2 - 0 - 0 | N34: ZAR 17115.30 | O34: Delivered | P34: 45837.917 | Q34: -
A35: 6981190735 | B35: Helge Weber | C35: 46011 | D35: 46018 | E35: Booking.com | F35: BDC | H35: 2 x Studio - General - Breakfast included - European Economic Area | I35: 45838.371 | L35: Booked | M35: 3 - 0 - 0 | N35: ZAR 94136.40 | O35: Delivered | P35: 45838.376 | Q35: -
A36: 6798414745 | B36: sophia korduner | C36: 46012 | D36: 46013 | E36: Booking.com | F36: BDC | H36: 1 x Studio - General - Breakfast included - European Economic Area | I36: 45838.918 | K36: 45948.397 | L36: Cancelled | M36: 2 - 0 - 0 | N36: ZAR 6832.80 | O36: Delivered | P36: 45948.4 | Q36: -
A37: 6463303278 | B37: Sabine Amelung-Hildebrand | C37: 46036 | D37: 46038 | E37: Booking.com | F37: BDC | H37: 1 x Suite with Terrace - General - Breakfast included - European Economic Area | I37: 45840.061 | J37: 45840.997 | K37: 46004.914 | L37: Cancelled | M37: 2 - 0 - 0 | N37: ZAR 21249.00 | O37: Delivered | P37: 46004.917 | Q37: -
A38: 6114200722 | B38: HANNA KALIADA | C38: 45977 | D38: 45979 | E38: Booking.com | F38: BDC | H38: 1 x Studio - General - Breakfast included - Mobile(App) Rate | I38: 45841.992 | K38: 45842.041 | L38: Cancelled | M38: 2 - 0 - 0 | N38: ZAR 15183.00 | O38: Delivered | P38: 45842.044 | Q38: -
A39: 6759759726 | B39: HANNA KALIADA | C39: 45977 | D39: 45980 | E39: Booking.com | F39: BDC | H39: 1 x Studio - General - Breakfast included - Mobile(App) Rate | I39: 45842.04 | K39: 45935.954 | L39: Cancelled | M39: 2 - 0 - 0 | N39: ZAR 22015.80 | O39: Delivered | P39: 45935.958 | Q39: -
A40: 5983995454 | B40: Krishnee Murugan, Rajendra Balmakhun | C40: 45847 | D40: 45848 | E40: Booking.com | F40: BDC | H40: 1 x Studio - General - Breakfast included - Getaway Deal | I40: 45843.489 | L40: Booked | M40: 1 - 0 - 0 | N40: ZAR 4114.00 | O40: Delivered | P40: 45843.491 | Q40: -
A41: 5983985236 | B41: Sanne Huntjens | C41: 45922 | D41: 45923 | E41: Booking.com | F41: BDC | H41: 1 x Duplex Suite - General - Breakfast included - Getaway Deal | I41: 45844.033 | L41: Booked | M41: 2 - 0 - 0 | N41: ZAR 4788.90 | O41: Delivered | P41: 45844.039 | Q41: -
A42: 5173571331 | B42: Monika Nuechter | C42: 46082 | D42: 46084 | E42: Booking.com | F42: BDC | H42: 1 x Studio - General - Breakfast included - European Economic Area | I42: 45844.711 | L42: Booked | M42: 2 - 0 - 0 | N42: ZAR 12906.00 | O42: Delivered | P42: 45844.715 | Q42: -
A43: 5578142796 | B43: Tadhg Brennan | C43: 46101 | D43: 46104 | E43: Booking.com | F43: BDC | H43: 1 x Studio - General - Breakfast included - European Economic Area | I43: 45844.955 | K43: 46076.635 | L43: Cancelled | M43: 2 - 0 - 0 | N43: ZAR 15487.20 | O43: Delivered | P43: 46076.638 | Q43: -
A44: 5173549672 | B44: Krishnee Murugan, Firdhose Coovadia | C44: 45847 | D44: 45848 | E44: Booking.com | F44: BDC | H44: 1 x Studio - General - Breakfast included - Getaway Deal | I44: 45845.589 | L44: Booked | M44: 1 - 0 - 0 | N44: ZAR 4114.00 | O44: Delivered | P44: 45845.592 | Q44: -
A45: 5048061322 | B45: Merle Matthews | C45: 45871 | D45: 45872 | E45: Booking.com | F45: BDC | H45: 2 x Studio - General - Breakfast included - Getaway Deal | I45: 45846.929 | L45: Booked | M45: 2 - 0 - 0 | N45: ZAR 9142.60 | O45: Delivered | P45: 45846.935 | Q45: -
A46: 6493567054 | B46: Craig Bosch | C46: 45857 | D46: 45858 | E46: Booking.com | F46: BDC | H46: 1 x Studio - General - Breakfast included - Domestic | I46: 45848.718 | L46: Booked | M46: 2 - 0 - 0 | N46: ZAR 3871.80 | O46: Delivered | P46: 45848.724 | Q46: -
A47: 5936377075 | B47: Martina Hacker | C47: 46062 | D47: 46065 | E47: Booking.com | F47: BDC | H47: 1 x Studio - General - Breakfast included - European Economic Area | I47: 45849.547 | K47: 45855.801 | L47: Cancelled | M47: 2 - 0 - 0 | N47: ZAR 18219.60 | O47: Delivered | P47: 45855.805 | Q47: -
A48: 5220284127 | B48: Angelica Wekwete | C48: 45958 | D48: 45961 | E48: Booking.com | F48: BDC | H48: 1 x Studio - General - Breakfast included - Mobile(App) Rate | I48: 45849.664 | K48: 45925.68 | L48: Cancelled | M48: 2 - 0 - 0 | N48: ZAR 17043.30 | O48: Delivered | P48: 45925.682 | Q48: -
A49: 6997808780 | B49: Viviane Berchtold | C49: 45990 | D49: 45992 | E49: Booking.com | F49: BDC | H49: 1 x Studio - General - Breakfast included - Mobile(App) Rate | I49: 45849.865 | K49: 45874.869 | L49: Cancelled | M49: 2 - 0 - 0 | N49: ZAR 15183.00 | O49: Delivered | P49: 45874.872 | Q49: -
A50: 5515685126 | B50: Christian Gerber | C50: 45870 | D50: 45873 | E50: Booking.com | F50: BDC | H50: 1 x Duplex Suite - General - Breakfast included - Getaway Deal | I50: 45853.246 | L50: Booked | M50: 1 - 0 - 0 | N50: ZAR 13804.00 | O50: Delivered | P50: 45853.248 | Q50: -
A51: 6930843731 | B51: Linda Fowler | C51: 46000 | D51: 46003 | E51: Booking.com | F51: BDC | H51: 1 x Suite with Terrace - General - Breakfast included - United Kingdom | I51: 45853.91 | K51: 45872.475 | L51: Cancelled | M51: 2 - 0 - 0 | N51: ZAR 30811.50 | O51: Delivered | P51: 45872.478 | Q51: -
A52: 5695099447 | B52: Martina Hacker | C52: 46062 | D52: 46065 | E52: Booking.com | F52: BDC | H52: 1 x Studio - General - Breakfast included - European Economic Area | I52: 45855.807 | L52: Booked | M52: 2 - 0 - 0 | N52: ZAR 18979.20 | O52: Delivered | P52: 45855.812 | Q52: -
A53: 5318200120 | B53: Abdulkarim Alotaibi | C53: 45857 | D53: 45858 | E53: Booking.com | F53: BDC | H53: 1 x Studio - Last Minute NoCC Free Cancellation - Breakfast included - Getaway Deal | I53: 45857.483 | L53: Booked | M53: 2 - 0 - 0 | N53: ZAR 3656.70 | O53: Delivered | P53: 45857.488 | Q53: -
A54: 5220167394 | B54: Markus van der Merwe, Markus MN van der Merwe, | C54: 45884 | D54: 45886 | E54: Booking.com | F54: BDC | H54: 2 x Suite with Terrace - General - Breakfast included - Getaway Deal | I54: 45859.338 | L54: Booked | M54: 36558 | N54: ZAR 23033.30 | O54: Delivered | P54: 45859.34 | Q54: -
A55: 5650458299 | B55: Floyd Lebatie | C55: 45866 | D55: 45867 | E55: Booking.com | F55: BDC | H55: 1 x Studio - General - Breakfast included - Getaway Deal | I55: 45859.601 | L55: Booked | M55: 1 - 0 - 0 | N55: ZAR 3656.70 | O55: Delivered | P55: 45859.604 | Q55: -
A56: 5531625113 | B56: Vuyokazi Bikwana | C56: 45932 | D56: 45933 | E56: Booking.com | F56: BDC | H56: 1 x Studio - General - Breakfast included - Domestic | I56: 45860.46 | K56: 45864.891 | L56: Cancelled | M56: 2 - 0 - 0 | N56: ZAR 5877.00 | O56: Delivered | P56: 45864.895 | Q56: -
A57: 5508435483 | B57: Jean Visser, Hennie Visser | C57: 45869 | D57: 45870 | E57: Booking.com | F57: BDC | H57: 1 x Suite with Terrace - General - Breakfast included - Getaway Deal | I57: 45861.458 | L57: Booked | M57: 2 - 0 - 0 | N57: ZAR 5757.90 | O57: Delivered | P57: 45861.462 | Q57: -
A58: 6230423477 | B58: Lisa Stokland | C58: 46024 | D58: 46026 | E58: Booking.com | F58: BDC | H58: 1 x Studio - General - Breakfast included - United Kingdom | I58: 45862.973 | K58: 45864.454 | L58: Cancelled | M58: 2 - 0 - 0 | N58: ZAR 13665.60 | O58: Delivered | P58: 45864.46 | Q58: -
A59: 5838244850 | B59: Konstantinos Terzis | C59: 46024 | D59: 46026 | E59: Booking.com | F59: BDC | H59: 1 x Studio - General - Breakfast included - European Economic Area | I59: 45862.975 | K59: 45964.628 | L59: Cancelled | M59: 2 - 0 - 0 | N59: ZAR 13665.60 | O59: Delivered | P59: 45964.633 | Q59: -
A60: 5673461464 | B60: David Sandoval | C60: 46024 | D60: 46026 | E60: Booking.com | F60: BDC | H60: 1 x Duplex Suite - General - Breakfast included - Mobile(App) Rate | I60: 45862.978 | K60: 45863.866 | L60: Cancelled | M60: 2 - 0 - 0 | N60: ZAR 14702.40 | O60: Delivered | P60: 45863.869 | Q60: -
A61: 6876224456 | B61: Thom Anderson | C61: 46024 | D61: 46026 | E61: Booking.com | F61: BDC | H61: 1 x Duplex Suite - General - Breakfast included | I61: 45863.371 | K61: 45992.252 | L61: Cancelled | M61: 2 - 0 - 0 | N61: ZAR 18150.00 | O61: Delivered | P61: 45992.257 | Q61: -
A62: 5134309634 | B62: Claudio Merlo, | C62: 45872 | D62: 45875 | E62: Booking.com | F62: BDC | H62: 1 x Duplex Suite - General - Breakfast included - Getaway Deal | I62: 45863.611 | L62: Booked | M62: 36526 | N62: ZAR 12325.00 | O62: Delivered | P62: 45863.615 | Q62: -
A63: 5198348952 | B63: Letitia Theron | C63: 45868 | D63: 45870 | E63: Booking.com | F63: BDC | H63: 1 x Studio - General - Breakfast included - Getaway Deal | I63: 45863.874 | L63: Booked | M63: 2 - 0 - 0 | N63: ZAR 8685.30 | O63: Delivered | P63: 45863.876 | Q63: -
A64: 5132559571 | B64: Uwe Mosberger | C64: 45902 | D64: 45904 | E64: Booking.com | F64: BDC | H64: 1 x Studio - General - Breakfast included - Getaway Deal | I64: 45864.671 | L64: Booked | M64: 2 - 0 - 0 | N64: ZAR 8880.80 | O64: Delivered | P64: 45864.676 | Q64: -
A65: 6234656403 | B65: Claudio Merlo, | C65: 45879 | D65: 45882 | E65: Booking.com | F65: BDC | H65: 1 x Duplex Suite - General - Breakfast included - Getaway Deal | I65: 45866.433 | L65: Booked | M65: 36526 | N65: ZAR 11832.00 | O65: Delivered | P65: 45866.436 | Q65: -
A66: 5531775661 | B66: Meera Anand | C66: 46024 | D66: 46026 | E66: Booking.com | F66: BDC | H66: 1 x Duplex Suite - General - Breakfast included - Mobile(App) Rate | I66: 45866.639 | K66: 45956.906 | L66: Cancelled | M66: 2 - 0 - 0 | N66: ZAR 16335.00 | O66: Delivered | P66: 45956.911 | Q66: -
A67: 6499083761 | B67: Emma Pakenham | C67: 46157 | D67: 46159 | E67: Booking.com | F67: BDC | H67: 1 x Legacy Room - General - Breakfast included - United Kingdom | I67: 45866.665 | J67: 46018.986 | L67: Modified | M67: 2 - 0 - 0 | N67: ZAR 10038.50 | O67: Delivered | P67: 46018.988 | Q67: -
A68: 5457454166 | B68: Marie Jund | C68: 45975 | D68: 45977 | E68: Booking.com | F68: BDC | H68: 1 x Studio - General - Breakfast included - European Economic Area | I68: 45867.711 | L68: Booked | M68: 2 - 0 - 0 | N68: ZAR 15183.00 | O68: Delivered | P68: 45867.714 | Q68: -
A69: 6544307413 | B69: Mlungisi Kwini, Mvandaba Kwini, Noah Kwini | C69: 45940 | D69: 45942 | E69: Booking.com | F69: BDC | H69: 2 x Studio - General - Breakfast included - Domestic | I69: 45867.762 | L69: Booked | M69: 2 - 0 - 0 | N69: ZAR 22332.60 | O69: Delivered | P69: 45867.768 | Q69: -
A70: 6014216652 | B70: Mlungisi Kwini, Xolisa Bangazi | C70: 45941 | D70: 45942 | E70: Booking.com | F70: BDC | H70: 1 x Suite with Terrace - General - Breakfast included - Domestic | I70: 45867.764 | L70: Booked | M70: 2 - 0 - 0 | N70: ZAR 7402.50 | O70: Delivered | P70: 45867.768 | Q70: -
A71: 6512576000 | B71: Tom Walker, | C71: 46084 | D71: 46089 | E71: Booking.com | F71: BDC | H71: 1 x Duplex Suite - General - Breakfast included - United Kingdom | I71: 45867.831 | K71: 46029.603 | L71: Cancelled | M71: 36527 | N71: ZAR 33586.20 | O71: Delivered | P71: 46029.608 | Q71: -
A72: 5827638662 | B72: Estelle Louw | C72: 45870 | D72: 45871 | E72: Booking.com | F72: BDC | H72: 1 x Studio - General - Breakfast included - Getaway Deal | I72: 45868.414 | L72: Booked | M72: 2 - 0 - 0 | N72: ZAR 4571.30 | O72: Delivered | P72: 45868.417 | Q72: -
A73: 6512540871 | B73: Diana Iakovenko | C73: 45953 | D73: 45955 | E73: Booking.com | F73: BDC | H73: 1 x Studio - General - Breakfast included - Russia | I73: 45868.421 | K73: 45886.903 | L73: Cancelled | M73: 2 - 0 - 0 | N73: ZAR 11166.30 | O73: Delivered | P73: 45886.906 | Q73: -
A74: 5672997986 | B74: Dawn Murphy | C74: 46022 | D74: 46023 | E74: Booking.com | F74: BDC | H74: 1 x Studio - General - Breakfast included | I74: 45868.595 | K74: 45868.731 | L74: Cancelled | M74: 2 - 0 - 0 | N74: ZAR 8435.00 | O74: Delivered | P74: 45868.734 | Q74: -
A75: 6507221371 | B75: Bernie Burness | C75: 45881 | D75: 45884 | E75: Booking.com | F75: BDC | H75: 1 x Studio - General - Breakfast included - Getaway Deal | I75: 45868.756 | L75: Booked | M75: 2 - 0 - 0 | N75: ZAR 10970.10 | O75: Delivered | P75: 45868.76 | Q75: -
A76: 6757991890 | B76: Federico Trincavelli | C76: 45888 | D76: 45891 | E76: Booking.com | F76: BDC | H76: 1 x Studio - General - Breakfast included - Getaway Deal | I76: 45869.663 | L76: Booked | M76: 1 - 0 - 0 | N76: ZAR 11427.40 | O76: Delivered | P76: 45869.667 | Q76: -
A77: 5713978343 | B77: Walter Fleitmann, | C77: 45871 | D77: 45872 | E77: Booking.com | F77: BDC | H77: 1 x Duplex Suite - Last Minute NoCC Free Cancellation - Breakfast included - Getaway Deal | I77: 45870.29 | L77: Booked | M77: 36527 | N77: ZAR 4930.00 | O77: Delivered | P77: 45870.295 | Q77: -
A78: 5918527070 | B78: Heloise Brink, Albe Geldenhuys Leo Geldenhuys, Charl en Heloise Brink, Luca Geldenhuys Marianne Fourie, Leon en Ezanne Reinach, Chris en Yolanda Maree | C78: 45955 | D78: 45956 | E78: Booking.com | F78: BDC | H78: 4 x Studio - General - Breakfast included - Domestic
A79: 5898156494 | B79: Katie Morton | C79: 46100 | D79: 46103 | E79: Booking.com | F79: BDC | H79: 1 x Studio - General - Breakfast included - United Kingdom | I79: 45870.581 | L79: Booked | M79: 2 - 0 - 0 | N79: ZAR 17423.10 | O79: Delivered | P79: 45870.586 | Q79: -
A80: 6381637911 | B80: Cliona Christle | C80: 45881 | D80: 45883 | E80: Booking.com | F80: BDC | H80: 1 x Suite with Terrace - General - Breakfast included - Getaway Deal | I80: 45870.834 | L80: Booked | M80: 2 - 0 - 0 | N80: ZAR 10876.60 | O80: Delivered | P80: 45870.838 | Q80: -
A81: 5769566829 | B81: Mlungisi Kwini, Lukhanyo Kwini | C81: 45877 | D81: 45880 | E81: Booking.com | F81: BDC | H81: 2 x Suite with Terrace - General - Breakfast included - Getaway Deal | I81: 45871.781 | L81: Booked | M81: 2 - 0 - 0 | N81: ZAR 37107.60 | O81: Delivered | P81: 45871.785 | Q81: -
A82: 6493724300 | B82: Zillah Schutte-Nel, | C82: 45898 | D82: 45900 | E82: Booking.com | F82: BDC | H82: 1 x Duplex Suite - General - Breakfast included - Getaway Deal | I82: 45872.655 | L82: Booked | M82: 36558 | N82: ZAR 11665.40 | O82: Delivered | P82: 45872.658 | Q82: -
A83: 6517425437 | B83: chipo veremu | C83: 45958 | D83: 45961 | E83: Booking.com | F83: BDC | H83: 1 x Suite with Terrace - General - Breakfast included - United Kingdom | I83: 45872.68 | K83: 45917.836 | L83: Cancelled | M83: 2 - 0 - 0 | N83: ZAR 23852.70 | O83: Delivered | P83: 45917.838 | Q83: -
A84: 6680618343 | B84: Oliver Briggs | C84: 45982 | D84: 45985 | E84: Booking.com | F84: BDC | H84: 1 x Studio - General - Breakfast included - Domestic | I84: 45872.696 | L84: Booked | M84: 2 - 0 - 0 | N84: ZAR 20498.40 | O84: Delivered | P84: 45872.699 | Q84: -
A85: 6022441761 | B85: Mlungisi Kwini, Zizipho Khweni | C85: 45877 | D85: 45879 | E85: Booking.com | F85: BDC | H85: 1 x Suite with Terrace - General - Breakfast included - Getaway Deal | I85: 45873.861 | L85: Booked | M85: 2 - 0 - 0 | N85: ZAR 12795.90 | O85: Delivered | P85: 45873.866 | Q85: -
A86: 5247740969 | B86: Henning Du Toit | C86: 45954 | D86: 45956 | E86: Booking.com | F86: BDC | H86: 1 x Duplex Suite - General - Breakfast included | I86: 45874.356 | L86: Booked | M86: 2 - 0 - 0 | N86: ZAR 14086.00 | O86: Delivered | P86: 45874.36 | Q86: -
A87: 6609995357 | B87: Belinda Easterbrook | C87: 46101 | D87: 46104 | E87: Booking.com | F87: BDC | H87: 1 x Studio - General - Breakfast included - Domestic | I87: 45874.819 | K87: 46068.821 | L87: Cancelled | M87: 2 - 0 - 0 | N87: ZAR 16777.80 | O87: Delivered | P87: 46068.827 | Q87: -
A88: 5941879223 | B88: Viviane Berchtold | C88: 45967 | D88: 45969 | E88: Booking.com | F88: BDC | H88: 1 x Studio - General - Breakfast included | I88: 45874.885 | K88: 45874.887 | L88: Cancelled | M88: 2 - 0 - 0 | N88: ZAR 16870.00 | O88: Delivered | P88: 45874.891 | Q88: -
A89: 6966304464 | B89: Viviane Berchtold | C89: 45967 | D89: 45969 | E89: Booking.com | F89: BDC | H89: 1 x Studio - General - Breakfast included - Mobile(App) Rate | I89: 45874.888 | L89: Booked | M89: 2 - 0 - 0 | N89: ZAR 15183.00 | O89: Delivered | P89: 45874.891 | Q89: -
A90: 6938222973 | B90: christian kuehnle | C90: 45984 | D90: 45986 | E90: Booking.com | F90: BDC | H90: 1 x Studio - General - Breakfast included - European Economic Area | I90: 45874.908 | K90: 45886.843 | L90: Cancelled | M90: 2 - 0 - 0 | N90: ZAR 12906.00 | O90: Delivered | P90: 45886.849 | Q90: -
A91: 6813271658 | B91: Daniel Opperman | C91: 45910 | D91: 45911 | E91: Booking.com | F91: BDC | H91: 1 x Studio - General - Breakfast included - Getaway Deal | I91: 45875.53 | L91: Booked | M91: 2 - 0 - 0 | N91: ZAR 4440.40 | O91: Delivered | P91: 45875.535 | Q91: -
A92: 6813283244 | B92: Trudy Mosterd | C92: 46072 | D92: 46075 | E92: Booking.com | F92: BDC | H92: 1 x Suite with Terrace - General - Breakfast included - European Economic Area | I92: 45875.564 | L92: Booked | M92: 2 - 0 - 0 | N92: ZAR 28687.50 | O92: Delivered | P92: 45875.569 | Q92: -
A93: 6939549593 | B93: Patricia Schmid | C93: 45901 | D93: 45902 | E93: Booking.com | F93: BDC | H93: 1 x Studio - General - Breakfast included - Getaway Deal | I93: 45877.736 | L93: Booked | M93: 2 - 0 - 0 | N93: ZAR 4440.40 | O93: Delivered | P93: 45877.739 | Q93: -
A94: 6067328679 | B94: sandy Flint | C94: 45878 | D94: 45879 | E94: Booking.com | F94: BDC | H94: 1 x Duplex Suite - Last Minute NoCC Free Cancellation - Breakfast included - Getaway Deal | I94: 45877.794 | K94: 45878.633 | L94: Cancelled | M94: 1 - 0 - 0 | N94: ZAR 4930.00 | O94: Delivered | P94: 45878.638 | Q94: -
A95: 5543592412 | B95: Desire Muller | C95: 45878 | D95: 45879 | E95: Booking.com | F95: BDC | H95: 1 x Studio - Last Minute NoCC Free Cancellation - Breakfast included - Getaway Deal | I95: 45878.451 | L95: Booked | M95: 2 - 0 - 0 | N95: ZAR 5028.60 | O95: Delivered | P95: 45878.456 | Q95: -
A96: 6545109730 | B96: Cliona Christle | C96: 45880 | D96: 45881 | E96: Booking.com | F96: BDC | H96: 1 x Studio - General - Breakfast included - Getaway Deal | I96: 45878.528 | L96: Booked | M96: 2 - 0 - 0 | N96: ZAR 4114.00 | O96: Delivered | P96: 45878.533 | Q96: -
A97: 6786093929 | B97: Xolani Manjo | C97: 45878 | D97: 45880 | E97: Booking.com | F97: BDC | H97: 1 x Studio - Last Minute NoCC Free Cancellation - Breakfast included - Getaway Deal | I97: 45878.597 | K97: 45880.414 | L97: Cancelled | M97: 2 - 0 - 0 | N97: ZAR 9599.90 | O97: Delivered | P97: 45880.418 | Q97: -
A98: 5606585924 | B98: Mark Culley | C98: 45975 | D98: 45981 | E98: Booking.com | F98: BDC | H98: 1 x Suite with Terrace - General - Breakfast included - United Kingdom | I98: 45878.81 | L98: Booked | M98: 2 - 0 - 0 | N98: ZAR 61623.00 | O98: Delivered | P98: 45878.815 | Q98: -
A99: 5449219706 | B99: Jackie De Wet | C99: 45892 | D99: 45895 | E99: Booking.com | F99: BDC | H99: 1 x Studio - General - Breakfast included - Getaway Deal | I99: 45879.434 | L99: Booked | M99: 2 - 0 - 0 | N99: ZAR 10970.10 | O99: Delivered | P99: 45879.439 | Q99: -
A100: 6315767245 | B100: SIMON RUBIN | C100: 45881 | D100: 45882 | E100: Booking.com | F100: BDC | H100: 1 x Studio - Last Minute NoCC Free Cancellation - Breakfast included - Getaway Deal | I100: 45880.605 | L100: Booked | M100: 1 - 0 - 0 | N100: ZAR 3702.60 | O100: Delivered | P100: 45880.611 | Q100: -
...

Sheet 24.08.2020
A1: Devonvale Revenue Report 6 August 2020
B2: OTB 2020/2021 @ 24 Aug 2020 | C2: OTB 2020/2021 @ 06 August 2020 | D2: Variance 24 Aug vs 6 Aug | E2: Actual 2019/2020 | F2: 24 Aug 2020 vs 2019/2020 | G2: Actual 2018/2019 | H2: Variance last 7 days | I2: as @ 03 June 2014 | J2: 2019/2020 vs 2018/2019 | K2: as @ 8 Nov 2017 | L2: Variance 2018 vrs 2017 | M2: OTB @ 8 Nov 2018 | N2: Actual 2017/2018 | O2: Variance last 7 days | P2: as @ 03 June 2014 | Q2: 2018/2019 vs 2017/18
A3: Mar | B3: 976369 | C3: 976369 | E3: 800133 | F3: =C3-#REF! -> #REF! | G3: =(#REF!-E3) -> #REF! | H3: =C3-I3 -> 815149 | I3: 161220 | J3: =C3-E3 -> 176236 | K3: 1191028 | N3: =(#REF!-L3) -> #REF! | O3: =K3-P3 -> 1029808 | P3: 161220 | Q3: =K3-L3 -> 1191028
A4: Apr | B4: 766954 | C4: 766954 | E4: 501706 | F4: =C4-#REF! -> #REF! | G4: =(#REF!-E4) -> #REF! | H4: =C4-I4 -> 605734 | I4: 161220 | J4: =C4-E4 -> 265248 | K4: 1245578 | N4: =(#REF!-L4) -> #REF! | O4: =K4-P4 -> 1084358 | P4: 161220 | Q4: =K4-L4 -> 1245578
A5: May | B5: 644339 | C5: 644339 | E5: 529349 | F5: =C5-#REF! -> #REF! | G5: =(#REF!-E5) -> #REF! | H5: =C5-I5 -> 483119 | I5: 161220 | J5: =C5-E5 -> 114990 | K5: 1488076 | N5: =(#REF!-L5) -> #REF! | O5: =K5-P5 -> 1326856 | P5: 161220 | Q5: =K5-L5 -> 1488076
A6: Jun | B6: 530924 | C6: 530924 | E6: 364107 | F6: =C6-#REF! -> #REF! | G6: =(#REF!-E6) -> #REF! | H6: =C6-I6 -> 369704 | I6: 161220 | J6: =C6-E6 -> 166817 | K6: 1449686 | N6: =(#REF!-L6) -> #REF! | O6: =K6-P6 -> 1288466 | P6: 161220 | Q6: =K6-L6 -> 1449686
A7: July | B7: 658052 | C7: 658052 | E7: 442478 | F7: =C7-#REF! -> #REF! | G7: =(#REF!-E7) -> #REF! | H7: =C7-I7 -> 496832 | I7: 161220 | J7: =C7-E7 -> 215574 | K7: 770876 | N7: =(#REF!-L7) -> #REF! | O7: =K7-P7 -> 609656 | P7: 161220 | Q7: =K7-L7 -> 770876
A8: Aug | B8: 648180 | C8: 648180 | E8: 436658 | F8: =C8-#REF! -> #REF! | G8: =(#REF!-E8) -> #REF! | H8: =C8-I8 -> 438056 | I8: 210124 | J8: =C8-E8 -> 211522 | K8: 570574 | N8: =(#REF!-L8) -> #REF! | O8: =K8-P8 -> 360450 | P8: 210124 | Q8: =K8-L8 -> 570574
A9: Sept | B9: =310920.68+365482.43 -> 676403.11 | C9: =310920.68+365482.43 -> 676403.11 | E9: 544088 | F9: =C9-#REF! -> #REF! | G9: =(#REF!-E9) -> #REF! | H9: =C9-I9 -> 387627.11 | I9: 288776 | J9: =C9-E9 -> 132315.11 | N9: =(#REF!-L9) -> #REF! | O9: =K9-P9 -> -288776 | P9: 288776 | Q9: =K9-L9 -> 0
A10: Oct | B10: 910865 | C10: 910865 | E10: 635793 | F10: =C10-#REF! -> #REF! | G10: =(#REF!-E10) -> #REF! | H10: =C10-I10 -> 697139 | I10: 213726 | J10: =C10-E10 -> 275072 | N10: =(#REF!-L10) -> #REF! | O10: =K10-P10 -> -213726 | P10: 213726 | Q10: =K10-L10 -> 0
A11: Nov | B11: 1045436 | C11: 1045436 | E11: 770879 | F11: =C11-#REF! -> #REF! | G11: =(#REF!-E11) -> #REF! | H11: =C11-I11 -> 884526 | I11: 160910 | J11: =C11-E11 -> 274557 | N11: =(#REF!-L11) -> #REF! | O11: =K11-P11 -> -160910 | P11: 160910 | Q11: =K11-L11 -> 0
A12: Dec | B12: 1178518 | C12: 1178518 | E12: 946659 | F12: =C12-#REF! -> #REF! | G12: =(#REF!-E12) -> #REF! | J12: =C12-E12 -> 231859 | N12: =(#REF!-L12) -> #REF! | Q12: =K12-L12 -> 0
A13: Jan | B13: 1117894 | C13: 1117894 | E13: 936359 | F13: =C13-#REF! -> #REF! | G13: =(#REF!-E13) -> #REF! | J13: =C13-E13 -> 181535 | N13: =(#REF!-L13) -> #REF! | Q13: =K13-L13 -> 0
A14: Feb | B14: 1103333 | C14: 1103333 | E14: 906676 | F14: =C14-#REF! -> #REF! | G14: =(#REF!-E14) -> #REF! | J14: =C14-E14 -> 196657 | N14: =(#REF!-L14) -> #REF! | Q14: =K14-L14 -> 0
A15: Fin Year | B15: =SUM(B3:B14) -> 10257267 | C15: =SUM(C3:C14) -> 10257267 | E15: =SUM(E3:E14) -> 7814885 | F15: =SUM(F3:F14) -> #REF! | G15: =SUM(G3:G14) -> #REF! | J15: =C15-E15 -> 2442382.1 | N15: =SUM(N3:N14) -> #REF! | Q15: =K15-L15 -> 0
A16: Oct | B16: 1187356 | C16: 1187356 | E16: 915852 | F16: =C16-#REF! -> #REF! | G16: =(#REF!-E16) -> #REF! | J16: =C16-E16 -> 271504 | N16: =(#REF!-L16) -> #REF! | Q16: =K16-L16 -> 0
A17: Nov | B17: 1465604 | C17: 1465604 | E17: 1379962 | F17: =C17-#REF! -> #REF! | G17: =(#REF!-E17) -> #REF! | J17: =C17-E17 -> 85642 | N17: =(#REF!-L17) -> #REF! | Q17: =K17-L17 -> 0
A18: Dec | B18: 1353583 | C18: 1353583 | E18: 979969 | F18: =C18-#REF! -> #REF! | G18: =(#REF!-E18) -> #REF! | J18: =C18-E18 -> 373614 | N18: =(#REF!-L18) -> #REF! | Q18: =K18-L18 -> 0
A19: Jan | B19: 1039316 | C19: 1039316 | E19: 693487 | F19: =C19-#REF! -> #REF! | G19: =(#REF!-E19) -> #REF! | J19: =C19-E19 -> 345829 | N19: =(#REF!-L19) -> #REF! | Q19: =K19-L19 -> 0
A20: Feb | B20: 2032270 | C20: 2032270 | E20: 1445893 | F20: =C20-#REF! -> #REF! | G20: =(#REF!-E20) -> #REF! | J20: =C20-E20 -> 586377 | N20: =(#REF!-L20) -> #REF! | Q20: =K20-L20 -> 0
A21: Mar | B21: 1805608 | C21: 1805608 | E21: 1593289 | F21: =C21-#REF! -> #REF! | G21: =(#REF!-E21) -> #REF! | J21: =C21-E21 -> 212319 | N21: =(#REF!-L21) -> #REF! | Q21: =K21-L21 -> 0
A22: Apr | B22: 1145562 | C22: 1145562 | E22: 1182276 | F22: =C22-#REF! -> #REF! | G22: =(#REF!-E22) -> #REF! | J22: =C22-E22 -> -36714 | N22: =(#REF!-L22) -> #REF! | Q22: =K22-L22 -> 0
A23: May | B23: 1022011 | C23: 1022011 | E23: 461579 | F23: =C23-#REF! -> #REF! | G23: =(#REF!-E23) -> #REF! | J23: =C23-E23 -> 560432 | N23: =(#REF!-L23) -> #REF! | Q23: =K23-L23 -> 0
A24: Apr | B24: 1244430 | C24: 1244430 | E24: 1384173 | F24: =C24-#REF! -> #REF! | G24: =(#REF!-E24) -> #REF! | J24: =C24-E24 -> -139743 | N24: =(#REF!-L24) -> #REF! | Q24: =K24-L24 -> 0
A25: May | B25: 282761 | C25: 282761 | E25: 1288620 | F25: =C25-#REF! -> #REF! | G25: =(#REF!-E25) -> #REF! | J25: =C25-E25 -> -1005859 | N25: =(#REF!-L25) -> #REF! | Q25: =K25-L25 -> 0
A26: June | B26: 108882 | C26: 108882 | E26: 744340 | F26: =C26-#REF! -> #REF! | G26: =(#REF!-E26) -> #REF! | J26: =C26-E26 -> -635458 | N26: =(#REF!-L26) -> #REF! | Q26: =K26-L26 -> 0
A27: July | B27: 1267953 | C27: 1267953 | E27: 854068 | F27: =C27-#REF! -> #REF! | G27: =(#REF!-E27) -> #REF! | J27: =C27-E27 -> 413885 | N27: =(#REF!-L27) -> #REF! | Q27: =K27-L27 -> 0
... A32: December | B32: 1310080 | C32: 1310080 | E32: 1760244 | F32: =C32-#REF! -> #REF! | G32: =(#REF!-E32) -> #REF! | J32: =C32-E32 -> -450164 | N32: =(#REF!-L32) -> #REF! | Q32: =K32-L32 -> 0
A33: January | B33: 1659145 | C33: 1659145 | E33: 1659998 | F33: =C33-#REF! -> #REF! | G33: 350895.35 | J33: =C33-E33 -> -853 | N33: 350895.35 | Q33: =K33-L33 -> 0
A34: Feb | B34: 1879453 | C34: 1879453 | E34: 1654190 | F34: =C34-#REF! -> #REF! | G34: =(#REF!-E34) -> #REF! | J34: =C34-E34 -> 225263 | N34: =(#REF!-L34) -> #REF! | Q34: =K34-L34 -> 0
A35: March | B35: 1257902 | C35: 1257902 | E35: 1309049 | F35: =C35-#REF! -> #REF! | G35: =(#REF!-E35) -> #REF! | J35: =C35-E35 -> -51147 | N35: =(#REF!-L35) -> #REF! | Q35: =K35-L35 -> 0
A36: Apr | B36: 641964 | C36: 641964 | E36: 502272 | F36: =C36-#REF! -> #REF! | G36: 50227.2 | J36: =C36-E36 -> 139692 | N36: 50227.2 | Q36: =K36-L36 -> 0
A37: May | B37: 291306 | C37: 291306 | E37: 312231 | F37: =C37-#REF! -> #REF! | G37: =(#REF!-E37) -> #REF! | J37: =C37-E37 -> -20925 | N37: =(#REF!-L37) -> #REF! | Q37: =K37-L37 -> 0
A38: June | B38: 345442 | C38: 345442 | E38: 0 | F38: =C38-#REF! -> #REF! | G38: =(#REF!-E38) -> #REF! | J38: =C38-E38 -> 345442 | N38: =(#REF!-L38) -> #REF! | Q38: =K38-L38 -> 0
A39: July | B39: 245810 | C39: 245810 | E39: 362403 | F39: =C39-#REF! -> #REF! | G39: =(#REF!-E39) -> #REF! | J39: =C39-E39 -> -116593 | N39: =(#REF!-L39) -> #REF! | Q39: =K39-L39 -> 0
A40: Aug | B40: 493056 | C40: 493056 | E40: 300416 | F40: =C40-#REF! -> #REF! | G40: =(#REF!-E40) -> #REF! | J40: =C40-E40 -> 192640 | N40: =(#REF!-L40) -> #REF! | Q40: =K40-L40 -> 0
A41: Sept | B41: 693980 | C41: 693980 | E41: 497345 | F41: =C41-#REF! -> #REF! | G41: =(#REF!-E41) -> #REF! | J41: =C41-E41 -> 196635 | N41: =(#REF!-L41) -> #REF! | Q41: =K41-L41 -> 0
A42: Oct | B42: 614185 | C42: 614185 | E42: 449973 | F42: =C42-#REF! -> #REF! | G42: =(#REF!-E42) -> #REF! | J42: =C42-E42 -> 164212 | N42: =(#REF!-L42) -> #REF! | Q42: =K42-L42 -> 0
A43: Nov | B43: 1253995.8 | C43: 1253995.8 | E43: 1196963 | F43: =C43-#REF! -> #REF! | G43: =(#REF!-E43) -> #REF! | J43: =C43-E43 -> 57032.83 | K43: 1191028 | L43: =C43-K43 -> 62967.83 | N43: =(#REF!-L43) -> #REF! | Q43: =K43-L43 -> 1128060.2
A44: Dec | B44: 1298292.3 | C44: 1298292.3 | E44: 1310080 | F44: =C44-#REF! -> #REF! | G44: =(#REF!-E44) -> #REF! | J44: =C44-E44 -> -11787.7 | K44: 1245578 | L44: =C44-K44 -> 52714.3 | N44: =(#REF!-L44) -> #REF! | Q44: =K44-L44 -> 1192863.7
A45: Jan | B45: 1427559 | C45: 1427559 | E45: 1659145.1 | F45: =C45-#REF! -> #REF! | G45: =(#REF!-E45) -> #REF! | J45: =C45-E45 -> -231586.11 | K45: 1488076 | L45: =C45-K45 -> -60517 | N45: =(#REF!-L45) -> #REF! | Q45: =K45-L45 -> 1548593
A46: Feb | B46: 1326567 | C46: 1326567 | E46: 1879453 | F46: =C46-#REF! -> #REF! | G46: =(#REF!-E46) -> #REF! | J46: =C46-E46 -> -552886 | K46: 1449686 | L46: =C46-K46 -> -123119 | N46: =(#REF!-L46) -> #REF! | Q46: =K46-L46 -> 1572805
A47: Mar | B47: 1088477.2 | C47: 1088477.2 | E47: 1879453 | F47: =C47-#REF! -> #REF! | G47: =(#REF!-E47) -> #REF! | J47: =C47-E47 -> -790975.82 | K47: 770876 | L47: =C47-K47 -> 317601.18 | N47: =(#REF!-L47) -> #REF! | Q47: =K47-L47 -> 453274.82
A48: Apr | B48: 692652.76 | C48: 692652.76 | E48: 641964 | F48: =C48-#REF! -> #REF! | G48: =(#REF!-E48) -> #REF! | J48: =C48-E48 -> 50688.76 | K48: 570574 | L48: =C48-K48 -> 122078.76 | N48: =(#REF!-L48) -> #REF! | Q48: =K48-L48 -> 448495.24
A49: May | B49: 377716 | C49: 377716 | E49: 291306 | F49: =C49-#REF! -> #REF! | G49: =(#REF!-E49) -> #REF! | J49: =C49-E49 -> 86410 | N49: =(#REF!-L49) -> #REF! | Q49: =K49-L49 -> 0
A50: June | B50: 428676.17 | C50: 428676.17 | E50: 345442 | F50: =C50-#REF! -> #REF! | G50: =(#REF!-E50) -> #REF! | J50: =C50-E50 -> 83234.17 | N50: =(#REF!-L50) -> #REF! | Q50: =K50-L50 -> 0
A51: July | B51: 412177 | C51: 412177 | E51: 245810 | F51: =C51-#REF! -> #REF! | G51: =(#REF!-E51) -> #REF! | J51: =C51-E51 -> 166367 | N51: =(#REF!-L51) -> #REF! | Q51: =K51-L51 -> 0
A52: Aug | B52: 675819 | C52: 675819 | E52: 493056 | F52: =C52-#REF! -> #REF! | G52: =(#REF!-E52) -> #REF! | J52: =C52-E52 -> 182763 | N52: =(#REF!-L52) -> #REF! | Q52: =K52-L52 -> 0
A53: Sep | B53: 1003569 | C53: 1003569 | E53: 693980 | F53: =C53-#REF! -> #REF! | G53: =(#REF!-E53) -> #REF! | J53: =C53-E53 -> 309589 | M53: 1003569 | N53: =(#REF!-L53) -> #REF! | Q53: =K53-L53 -> 0
A54: Oct | B54: 781187 | C54: 781187 | E54: 614185 | F54: =C54-#REF! -> #REF! | G54: =(#REF!-E54) -> #REF! | J54: =C54-E54 -> 167002 | M54: 588356.37 | N54: =(#REF!-L54) -> #REF! | Q54: =K54-L54 -> 0
A55: Nov | B55: 1355145.6 | C55: 1355145.6 | E55: 1253380 | F55: =C55-#REF! -> #REF! | G55: =(#REF!-E55) -> #REF! | J55: =C55-E55 -> 101765.63 | M55: 1137132 | N55: =(#REF!-L55) -> #REF! | Q55: =K55-L55 -> 0
A56: Dec | B56: 1283036 | C56: 1283036 | E56: 1298292 | F56: =C56-#REF! -> #REF! | G56: =(#REF!-E56) -> #REF! | J56: =C56-E56 -> -15256 | M56: 1137132 | N56: =(#REF!-L56) -> #REF! | Q56: =K56-L56 -> 0
A57: Jan | B57: 1625315.8 | C57: 1625315.8 | E57: 1427559 | F57: =C57-#REF! -> #REF! | G57: =(#REF!-E57) -> #REF! | J57: =C57-E57 -> 197756.81 | M57: 1290932 | N57: =(#REF!-L57) -> #REF! | Q57: =K57-L57 -> 0
A58: Feb | B58: 1514471 | C58: 1514471 | E58: 1480487 | F58: =C58-#REF! -> #REF! | G58: =(#REF!-E58) -> #REF! | J58: =C58-E58 -> 33984 | M58: 796680 | N58: =(#REF!-L58) -> #REF! | Q58: =K58-L58 -> 0
A59: Aug | B59: 45758 | C59: 34616 | D59: =B59-C59 -> 11142 | E59: 675819 | F59: =B59-E59 -> -630061 | G59: 493056 | J59: =E59-G59 -> 182763 | M59: 61799.69 | N59: 300416 | Q59: =G59-N59 -> 192640
A60: Sept | B60: 127162 | C60: 133969 | D60: =B60-C60 -> -6807 | E60: 1003569 | F60: =B60-E60 -> -876407 | G60: 697472 | J60: =E60-G60 -> 306097 | N60: 497345 | Q60: =G60-N60 -> 200127
A61: Oct | B61: 192026 | C61: 186267 | D61: =B61-C61 -> 5759 | E61: 777845 | F61: =B61-E61 -> -585819 | G61: 614185 | J61: =E61-G61 -> 163660 | N61: 449973 | Q61: =G61-N61 -> 164212
A62: Nov | B62: 500325 | C62: 500325 | D62: =B62-C62 -> 0 | E62: 1355145 | F62: =B62-E62 -> -854820 | G62: 1253380 | J62: =E62-G62 -> 101765 | N62: 1196163 | Q62: =G62-N62 -> 57217
A63: Dec | B63: 350989 | C63: 342380 | D63: =B63-C63 -> 8609 | E63: 1283036 | F63: =B63-E63 -> -932047 | G63: 1298292 | J63: =E63-G63 -> -15256 | N63: 1310080 | Q63: =G63-N63 -> -11788
A64: Jan | B64: 690410 | C64: 689540 | D64: =B64-C64 -> 870 | E64: 1587254 | F64: =B64-E64 -> -896844 | G64: 1427559 | J64: =E64-G64 -> 159695 | N64: 1659145 | Q64: =G64-N64 -> -231586
A65: Feb | B65: 1145027 | C65: 1145027 | D65: =B65-C65 -> 0 | E65: 1549058 | F65: =B65-E65 -> -404031 | G65: 1480487 | J65: =E65-G65 -> 68571 | N65: 1879453 | Q65: =G65-N65 -> -398966
A66: Mar | B66: 337810 | C66: 337810 | D66: =B66-C66 -> 0 | E66: 812859 | F66: =B66-E66 -> -475049 | G66: 1086477 | J66: =E66-G66 -> -273618 | N66: 1259495 | Q66: =G66-N66 -> -173018
A67: Apr | B67: 185764 | C67: 168441 | D67: =B67-C67 -> 17323 | E67: 13921 | F67: =B67-E67 -> 171843 | G67: 668608 | J67: =E67-G67 -> -654687 | N67: 641964 | Q67: =G67-N67 -> 26644
A68: May | B68: 23448 | C68: 23448 | D68: =B68-C68 -> 0 | E68: 1066 | F68: =B68-E68 -> 22382 | G68: 377714 | J68: =E68-G68 -> -376648 | N68: 291306 | Q68: =G68-N68 -> 86408
A69: Jun | B69: 357815 | C69: 14537 | D69: =B69-C69 -> 343278 | E69: 17978 | F69: =B69-E69 -> 339837 | G69: 428676 | J69: =E69-G69 -> -410698 | N69: 345442 | Q69: =G69-N69 -> 83234
A70: July | B70: 7178 | C70: 7178 | D70: =B70-C70 -> 0 | E70: 27248 | F70: =B70-E70 -> -20070 | G70: 412177 | J70: =E70-G70 -> -384929 | N70: 245810 | Q70: =G70-N70 -> 166367
B71: =SUM(B59:B70) -> 3963712 | C71: =SUM(C59:C70) -> 3583538 | E71: =SUM(E59:E70) -> 9104798 | G71: =SUM(G59:G70) -> 10238083 | M71: =SUM(M53:M70) -> 6015601.1 | N71: =SUM(N59:N70) -> 10076592
A72: Occupancy
B73: OTB 2020/2021 @ 24 Aug 2020 | C73: OTB 2020/2021 @ 06 August 2020 | D73: Variance 24 Aug vs 6 Aug | E73: Actual 2019/2020 | F73: 24 Aug 2020 vs 2019/2020 | G73: Actual 2018/2019 | H73: Variance last 7 days | I73: as @ 03 June 2014 | J73: 2019/2020 vs 2018/2019 | M73: OTB @ 8 Nov 2018 | N73: Actual 2017/2018 | O73: Variance last 7 days | P73: as @ 03 June 2014 | Q73: 2019/2020 vs 2018/2019
A74: Mar | B74: 0.88 | C74: 0.88 | E74: 0.92 | F74: 2905 | G74: -0.04 | H74: =C74-I74 -> -365.12 | I74: 366 | J74: =C74-E74 -> -0.04 | N74: -0.04 | O74: =K74-P74 -> -366 | P74: 366 | Q74: =K74-L74 -> 0
A75: Apr | B75: 0.71 | C75: 0.71 | E75: 0.6 | F75: 1827 | G75: 0.11 | H75: =C75-I75 -> -365.29 | I75: 366 | J75: =C75-E75 -> 0.11 | N75: 0.11 | O75: =K75-P75 -> -366 | P75: 366 | Q75: =K75-L75 -> 0
A76: May | B76: 0.63 | C76: 0.63 | E76: 0.63 | F76: 1956 | G76: 0 | H76: =C76-I76 -> -365.37 | I76: 366 | J76: =C76-E76 -> 0 | N76: 0 | O76: =K76-P76 -> -366 | P76: 366 | Q76: =K76-L76 -> 0
A77: Jun | B77: 0.57 | C77: 0.57 | E77: 0.52 | F77: 1558 | G77: 0.05 | H77: =C77-I77 -> -365.43 | I77: 366 | J77: =C77-E77 -> 0.05 | N77: 0.05 | O77: =K77-P77 -> -366 | P77: 366 | Q77: =K77-L77 -> 0
A78: July | B78: 0.69 | C78: 0.69 | E78: 0.55 | F78: 1714 | G78: 0.14 | H78: =C78-I78 -> -365.31 | I78: 366 | J78: =C78-E78 -> 0.14 | N78: 0.14 | O78: =K78-P78 -> -366 | P78: 366 | Q78: =K78-L78 -> 0
A79: Aug | B79: 0.67 | C79: 0.67 | E79: 0.56 | F79: 1761 | G79: 0.11 | H79: =C79-I79 -> -479.33 | I79: 480 | J79: =C79-E79 -> 0.11 | N79: 0.11 | O79: =K79-P79 -> -480 | P79: 480 | Q79: =K79-L79 -> 0
A80: Sept | B80: 0.67 | C80: 0.67 | E80: 0.64 | F80: 1945 | G80: 0.03 | H80: =C80-I80 -> -793.33 | I80: 794 | J80: =C80-E80 -> 0.03 | N80: 0.03 | O80: =K80-P80 -> -794 | P80: 794 | Q80: =K80-L80 -> 0
A81: Oct | B81: 0.84 | C81: 0.84 | E81: 0.75 | F81: 2304 | G81: 0.09 | H81: =C81-I81 -> -386.16 | I81: 387 | J81: =C81-E81 -> 0.09 | N81: 0.09 | O81: =K81-P81 -> -387 | P81: 387 | Q81: =K81-L81 -> 0
A82: Nov | B82: 0.87 | C82: 0.87 | E82: 0.91 | F82: 2736 | G82: -0.04 | H82: =C82-I82 -> -357.13 | I82: 358 | J82: =C82-E82 -> -0.04 | N82: -0.04 | O82: =K82-P82 -> -358 | P82: 358 | Q82: =K82-L82 -> 0
A83: Dec | B83: 0.89 | C83: 0.89 | E83: 0.88 | F83: 2820 | G83: 0.01 | J83: =C83-E83 -> 0.01 | N83: 0.01 | Q83: =K83-L83 -> 0
A84: Jan | B84: 0.82 | C84: 0.82 | E84: 0.85 | F84: 2747 | G84: 0.28 | J84: =C84-E84 -> -0.03 | N84: 0.28 | Q84: =K84-L84 -> 0
A85: Feb | B85: 0.94 | C85: 0.94 | E85: 0.92 | F85: 2717 | G85: 0.02 | J85: =C85-E85 -> 0.02 | N85: 0.02 | Q85: =K85-L85 -> 0
A86: Oct | B86: 0.52 | C86: 0.52 | E86: 0.57 | F86: 1490 | G86: -0.05 | J86: =C86-E86 -> -0.05 | N86: -0.05 | Q86: =K86-L86 -> 0
A87: Nov | B87: 0.72 | C87: 0.72 | E87: 0.69 | F87: 1744 | G87: 0.03 | J87: =C87-E87 -> 0.03 | N87: 0.03 | Q87: =K87-L87 -> 0
A88: Dec | B88: 0.53 | C88: 0.53 | E88: 0.59 | F88: 1415 | G88: -0.06 | J88: =C88-E88 -> -0.06 | N88: -0.06 | Q88: =K88-L88 -> 0
A89: Jan | B89: 0.47 | C89: 0.47 | E89: 0.47 | F89: 1004 | G89: 0 | J89: =C89-E89 -> 0 | N89: 0 | Q89: =K89-L89 -> 0
A90: Feb | B90: 0.83 | C90: 0.83 | E90: 0.68 | F90: 1563 | G90: 0.12 | J90: =C90-E90 -> 0.15 | N90: 0.12 | Q90: =K90-L90 -> 0
A91: Mar | B91: 0.72 | C91: 0.72 | E91: 0.73 | F91: 1896 | J91: =C91-E91 -> -0.01 | Q91: =K91-L91 -> 0
A92: Apr | B92: 0.62 | C92: 0.62 | E92: 0.66 | F92: 1612 | J92: =C92-E92 -> -0.04 | Q92: =K92-L92 -> 0
A93: May | B93: 0.5 | C93: 0.5 | E93: 0.63 | F93: 701 | J93: =C93-E93 -> -0.13 | Q93: =K93-L93 -> 0
A94: Apr | B94: 0.304 | C94: 0.304 | E94: 0.353 | F94: 424 | G94: =C94-E94 -> -0.049 | J94: =C94-E94 -> -0.049 | N94: =K94-L94 -> 0 | Q94: =K94-L94 -> 0
A95: May | B95: 0.19 | C95: 0.19 | E95: 0.3 | F95: 349 | G95: =C95-E95 -> -0.11 | J95: =C95-E95 -> -0.11 | N95: =K95-L95 -> 0 | Q95: =K95-L95 -> 0
A96: June | B96: 0.088 | C96: 0.088 | E96: 0.138 | F96: 166 | G96: =C96-E96 -> -0.05 | J96: =C96-E96 -> -0.05 | N96: =K96-L96 -> 0 | Q96: =K96-L96 -> 0
A97: July | B97: 0.274 | C97: 0.274 | E97: 0.183 | F97: 230 | G97: =C97-E97 -> 0.091 | J97: =C97-E97 -> 0.091 | N97: =K97-L97 -> 0 | Q97: =K97-L97 -> 0
A98: August | B98: 0.22 | C98: 0.22 | E98: 0.2906 | F98: 356 | G98: =C98-E98 -> -0.0706 | J98: =C98-E98 -> -0.0706 | N98: =K98-L98 -> 0 | Q98: =K98-L98 -> 0
A99: September | B99: 0.33 | C99: 0.33 | E99: 0.443 | F99: 513 | G99: =C99-E99 -> -0.113 | J99: =C99-E99 -> -0.113 | N99: =K99-L99 -> 0 | Q99: =K99-L99 -> 0
A100: November | B100: 0.62 | C100: 0.62 | E100: 0.697 | J100: =C100-E100 -> -0.077 | Q100: =K100-L100 -> 0
A101: December | B101: 0.49 | C101: 0.49 | E101: 0.585 | J101: =C101-E101 -> -0.095 | Q101: =K101-L101 -> 0
A102: January | B102: 0.62 | C102: 0.62 | E102: 0.816 | J102: =C102-E102 -> -0.196 | Q102: =K102-L102 -> 0
A103: Feb | B103: 0.84 | C103: 0.84 | E103: 0.93 | J103: =C103-E103 -> -0.09 | Q103: =K103-L103 -> 0
A104: March | B104: 0.64 | C104: 0.64 | E104: 0.77 | J104: =C104-E104 -> -0.13 | Q104: =K104-L104 -> 0
...

Sheet Revenue 2017 - 2020
A1: Revenue vs previous year
B2: 2017 | C2: 2018 | D2: Variance 2018 vs 2017 | E2: 2019 | F2: Variance 2019 vs 2018 | G2: 2020 | H2: Variance 2020 vs 2019
A3: Jan | B3: 1659998 | C3: 1659145 | D3: =C3-B3 -> -853 | E3: 1427559 | F3: =E3-C3 -> -231586 | G3: 1587254 | H3: =G3-E3 -> 159695
A4: Feb | B4: 1644190 | C4: 1879453 | D4: =C4-B4 -> 235263 | E4: 1480487 | F4: =E4-C4 -> -398966 | G4: 1549058 | H4: =G4-E4 -> 68571
A5: Mar | B5: 1309049 | C5: 1259485 | D5: =C5-B5 -> -49564 | E5: 1086477 | F5: =E5-C5 -> -173008 | G5: 1086477 | H5: =G5-E5 -> 0
A6: Apr | B6: 502272 | C6: 641964 | D6: =C6-B6 -> 139692 | E6: 668608 | F6: =E6-C6 -> 26644 | G6: 668608 | H6: =G6-E6 -> 0
A7: May | B7: 312231 | C7: 291306 | D7: =C7-B7 -> -20925 | E7: 377714 | F7: =E7-C7 -> 86408 | G7: 377714 | H7: =G7-E7 -> 0
A8: Jun | B8: -155924 | C8: 345442 | D8: =C8-B8 -> 501366 | E8: 428767 | F8: =E8-C8 -> 83325 | G8: 428767 | H8: =G8-E8 -> 0
A9: Jul | B9: 362403 | C9: 245810 | D9: =C9-B9 -> -116593 | E9: 412177 | F9: =E9-C9 -> 166367 | G9: 412177 | H9: =G9-E9 -> 0
A10: Aug | B10: 300416 | C10: 493056 | D10: =C10-B10 -> 192640 | E10: 675819 | F10: =E10-C10 -> 182763 | G10: 675819 | H10: =G10-E10 -> 0
A11: Sept | B11: 497345 | C11: 697473 | D11: =C11-B11 -> 200128 | E11: 1003569 | F11: =E11-C11 -> 306096 | G11: 1003569 | H11: =G11-E11 -> 0
A12: Oct | B12: 449973 | C12: 614185 | D12: =C12-B12 -> 164212 | E12: 777843 | F12: =E12-C12 -> 163658 | G12: 777843 | H12: =G12-E12 -> 0
A13: Nov | B13: 1196163 | C13: 1253380 | D13: =C13-B13 -> 57217 | E13: 1355145 | F13: =E13-C13 -> 101765 | G13: 1355145 | H13: =G13-E13 -> 0
A14: Dec | B14: 1310080 | C14: 1298292 | D14: =C14-B14 -> -11788 | E14: 1283036 | F14: =E14-C14 -> -15256 | G14: 1283036 | H14: =G14-E14 -> 0
A15: TOTAL | B15: =SUM(B3:B14) -> 9388196 | C15: =SUM(C3:C14) -> 10678991 | D15: =C15-B15 -> 1290795 | E15: =SUM(E3:E14) -> 10977201 | F15: =E15-C15 -> 298210 | G15: =SUM(G3:G14) -> 11205467 | H15: =G15-E15 -> 228266

Sheet Sheet2
B2: LY Actual | C2: Siteminder
A3: Jan | B3: 1427559 | C3: 610688 | D3: =(C3/B3) -> 0.42778477
A4: Feb | B4: 1480487 | C4: 694688 | D4: =(C4/B4) -> 0.46922938
A5: Mar | B5: 1086477 | C5: 665623 | D5: =(C5/B5) -> 0.61264343
A6: Apr | B6: 668608 | C6: 393062 | D6: =(C6/B6) -> 0.58788109
A7: May | B7: 377714 | C7: 156669 | D7: =(C7/B7) -> 0.41478208
A8: Jun | B8: 428767 | C8: 62068 | D8: =(C8/B8) -> 0.14475927
A9: Jul | B9: 412177 | C9: 150538 | D9: =(C9/B9) -> 0.36522659

Sheet SM Dec 2019 vs 2018
A1: Channel | B1: Number of Reservations | D1: 2019 vs 2018 | E1: Room Nights | G1: 2019 vs 2018 | H1: Avg Lead Time | J1: Avg Length of Stay | L1: Revenue | N1: 2019 vs 2018
B2: 2019 | C2: 2018 | E2: 2019 | F2: 2018 | H2: 2019 | I2: 2018 | J2: 2019 | K2: 2018 | L2: 2019 | M2: 2018
A3: Agoda | B3: 1 | C3: 8 | D3: =B3-C3 -> -7 | E3: 3 | F3: 14 | G3: =E3-F3 -> -11 | H3: 152.00 | I3: 39.25 | J3: 3.00 | K3: 1.75 | L3: 2862.78 | M3: 21273.12 | N3: =L3-M3 -> -18410.34
A4: Booking.com | B4: 20 | C4: 61 | D4: =B4-C4 -> -41 | E4: 59 | F4: 128 | G4: =E4-F4 -> -69 | H4: 64.50 | I4: 22.7 | J4: 2.95 | K4: 2.1 | L4: 153471.91 | M4: 251193.6 | N4: =L4-M4 -> -97721.69
A5: Booking Button | C5: 6 | D5: =B5-C5 -> -6 | F5: 13 | G5: =E5-F5 -> -13 | I5: 12.67 | K5: 2.17 | M5: 48812.8 | N5: =L5-M5 -> -48812.8
A6: Expedia | B6: 1 | C6: 37 | D6: =B6-C6 -> -36 | E6: 2 | F6: 91 | G6: =E6-F6 -> -89 | H6: 16.00 | I6: 40.86 | J6: 2.00 | K6: 2.46 | L6: 7740.14 | M6: 123731.83 | N6: =L6-M6 -> -115991.69
A7: Hotelbeds | B7: 15 | C7: 6 | D7: =B7-C7 -> 9 | E7: 24 | F7: 15 | G7: =E7-F7 -> 9 | H7: 32.80 | I7: 62.33 | J7: 1.60 | K7: 2.5 | L7: 33934.2 | M7: 28539 | N7: =L7-M7 -> 5395.2
A8: HRS | C8: 1 | D8: =B8-C8 -> -1 | F8: 1 | G8: =E8-F8 -> -1 | I8: 11 | K8: 1 | M8: 1292 | N8: =L8-M8 -> -1292
A9: Simple Booking | B9: 17 | D9: =B9-C9 -> 17 | E9: 32 | G9: =E9-F9 -> 32 | H9: 42.47 | J9: 1.88 | L9: 63481.55 | N9: =L9-M9 -> 63481.55
A10: TOTAL | B10: =SUM(B3:B9) -> 54 | C10: =SUM(C3:C9) -> 119 | D10: =B10-C10 -> -65 | E10: =SUM(E3:E9) -> 120 | F10: =SUM(F3:F9) -> 262 | G10: =E10-F10 -> -142 | L10: =SUM(L3:L9) -> 261490.58 | M10: =SUM(M3:M9) -> 474842.35 | N10: =L10-M10 -> -213351.77

Sheet Stats
A1: 2014 | F1: 2015 | K1: 2016
B2: Revenue | C2: Occupancy | D2: AVR | G2: Revenue | H2: Occupancy | I2: AVR | L2: Revenue | M2: Occupancy | N2: AVR
A3: Jan | F3: Jan | G3: 693487 | H3: 0.47 | I3: 691 | K3: Jan | L3: 1039316 | M3: 0.47 | N3: 857
A4: Feb | F4: Feb | G4: 1445893 | H4: 0.68 | I4: 925 | K4: Feb | L4: 2032270 | M4: 0.83 | N4: 991
A5: Mar | F5: Mar | G5: 1593289 | H5: 0.73 | I5: 840 | K5: Mar | L5: 1805608 | M5: 0.72 | N5: 956
A6: Apr | F6: Apr | G6: 1182276 | H6: 0.66 | I6: 733 | K6: Apr | L6: 1145562 | M6: 0.62 | N6: 735
A7: May | F7: May | G7: 461579 | H7: 0.63 | I7: 658 | K7: May
A8: Jun | F8: Jun | G8: 417460 | H8: 0.58 | I8: 580 | K8: Jun
A9: Jul | F9: Jul | G9: 477485 | H9: 0.57 | I9: 672 | K9: Jul
A10: Aug | F10: Aug | G10: 674150 | H10: 0.68 | I10: 698 | K10: Aug
A11: Sept | F11: Sept | G11: 722338 | H11: 0.52 | I11: 675 | K11: Sept
A12: Oct | B12: 915852 | C12: 0.57 | D12: 614 | F12: Oct | G12: 1187356 | H12: 0.52 | I12: 675 | K12: Oct
A13: Nov | B13: 1379962 | C13: 0.69 | D13: 791 | F13: Nov | G13: 1465604 | H13: 0.72 | I13: 810 | K13: Nov
A14: Dec | B14: 979969 | C14: 0.59 | D14: 722 | F14: Dec | G14: 1353583 | H14: 0.53 | I14: 978 | K14: Dec
A17: Siteminder stats @ 19 May 2016
B18: Res | C18: RN | D18: Rev | F18: AVR | H18: LoS
A19: 2015 | B19: 2 | C19: 12 | D19: 32287 | F19: =D19/C19 -> 2690.5833 | H19: 6
A20: 2016 | B20: 53 | C20: 239 | D20: 288690 | F20: =D20/C20 -> 1207.9079 | H20: 4.5

Sheet Studio Revenue
A1: Revenue
B2: as @ 21 April 2015 | C2: Target | D2: LY Actual | E2: 21 April 2015 vrs Target | G2: Target vrs LY | I2: Variance last 7 days | J2: as @ 03 June 2014 | K2: Variance last 7 days | L2: as @ 14 April 2015 | M2: Actual vrs LY
A3: Mar | B3: 976369 | C3: =(D3*1.175) -> 940156.28 | D3: 800133 | E3: =B3-C3 -> 36212.725 | F3: =(B3-C3)/C3 -> 0.038517772 | G3: =(C3-D3) -> 140023.28 | H3: =(C3-D3)/D3 -> 0.175 | I3: =B3-J3 -> 815149 | J3: 161220 | M3: =B3-D3 -> 176236 | N3: =(B3-D3)/D3 -> 0.22025838
A4: Apr | B4: 766954 | C4: =(D4*1.175) -> 589504.55 | D4: 501706 | E4: =B4-C4 -> 177449.45 | F4: =(B4-C4)/C4 -> 0.30101456 | G4: =(C4-D4) -> 87798.55 | H4: =(C4-D4)/D4 -> 0.175 | I4: =B4-J4 -> 605734 | J4: 161220 | M4: =B4-D4 -> 265248 | N4: =(B4-D4)/D4 -> 0.5286921
A5: May | B5: 644339 | C5: =(D5*1.175) -> 621985.08 | D5: 529349 | E5: =B5-C5 -> 22353.925 | F5: =(B5-C5)/C5 -> 0.035939649 | G5: =(C5-D5) -> 92636.075 | H5: =(C5-D5)/D5 -> 0.175 | I5: =B5-J5 -> 483119 | J5: 161220 | M5: =B5-D5 -> 114990 | N5: =(B5-D5)/D5 -> 0.21722909
A6: Jun | B6: 530924 | C6: =(D6*1.175) -> 427825.73 | D6: 364107 | E6: =B6-C6 -> 103098.27 | F6: =(B6-C6)/C6 -> 0.24098194 | G6: =(C6-D6) -> 63718.725 | H6: =(C6-D6)/D6 -> 0.175 | I6: =B6-J6 -> 369704 | J6: 161220 | M6: =B6-D6 -> 166817 | N6: =(B6-D6)/D6 -> 0.45815378
A7: July | B7: 658052 | C7: =(D7*1.175) -> 519911.65 | D7: 442478 | E7: =B7-C7 -> 138140.35 | F7: =(B7-C7)/C7 -> 0.26569966 | G7: =(C7-D7) -> 77433.65 | H7: =(C7-D7)/D7 -> 0.175 | I7: =B7-J7 -> 496832 | J7: 161220 | M7: =B7-D7 -> 215574 | N7: =(B7-D7)/D7 -> 0.4871971
A8: Aug | B8: 648180 | C8: =(D8*1.175) -> 513073.15 | D8: 436658 | E8: =B8-C8 -> 135106.85 | F8: =(B8-C8)/C8 -> 0.26332863 | G8: =(C8-D8) -> 76415.15 | H8: =(C8-D8)/D8 -> 0.175 | I8: =B8-J8 -> 438056 | J8: 210124 | M8: =B8-D8 -> 211522 | N8: =(B8-D8)/D8 -> 0.48441114
A9: Sept | B9: =310920.68+365482.43 -> 676403.11 | C9: =(D9*1.175) -> 639303.4 | D9: 544088 | E9: =B9-C9 -> 37099.71 | F9: =(B9-C9)/C9 -> 0.05803146 | G9: =(C9-D9) -> 95215.4 | H9: =(C9-D9)/D9 -> 0.175 | I9: =B9-J9 -> 387627.11 | J9: 288776 | M9: =B9-D9 -> 132315.11 | N9: =(B9-D9)/D9 -> 0.24318697
A10: Oct | B10: 910865 | C10: =(D10*1.175) -> 747056.78 | D10: 635793 | E10: =B10-C10 -> 163808.22 | F10: =(B10-C10)/C10 -> 0.21927145 | G10: =(C10-D10) -> 111263.78 | H10: =(C10-D10)/D10 -> 0.175 | I10: =B10-J10 -> 697139 | J10: 213726 | M10: =B10-D10 -> 275072 | N10: =(B10-D10)/D10 -> 0.43264396
A11: Nov | B11: 1045436 | C11: =(D11*1.175) -> 905782.83 | D11: 770879 | E11: =B11-C11 -> 139653.17 | F11: =(B11-C11)/C11 -> 0.15417954 | G11: =(C11-D11) -> 134903.83 | H11: =(C11-D11)/D11 -> 0.175 | I11: =B11-J11 -> 884526 | J11: 160910 | M11: =B11-D11 -> 274557 | N11: =(B11-D11)/D11 -> 0.35616095
A12: Dec | B12: 1178518 | C12: =(D12*1.175) -> 1112324.3 | D12: 946659 | E12: =B12-C12 -> 66193.675 | F12: =(B12-C12)/C12 -> 0.05950933 | G12: =(C12-D12) -> 165665.32 | H12: =(C12-D12)/D12 -> 0.175 | M12: =B12-D12 -> 231859 | N12: =(B12-D12)/D12 -> 0.24492346
A13: Jan | B13: 1117894 | C13: =(D13*1.175) -> 1100221.8 | D13: 936359 | E13: =B13-C13 -> 17672.175 | F13: =(B13-C13)/C13 -> 0.016062375 | G13: =(C13-D13) -> 163862.82 | H13: =(C13-D13)/D13 -> 0.175 | M13: =B13-D13 -> 181535 | N13: =(B13-D13)/D13 -> 0.19387329
A14: Feb | B14: 1103333 | C14: =(D14*1.175) -> 1065344.3 | D14: 906676 | E14: =B14-C14 -> 37988.7 | F14: =(B14-C14)/C14 -> 0.035658613 | G14: =(C14-D14) -> 158668.3 | H14: =(C14-D14)/D14 -> 0.175 | M14: =B14-D14 -> 196657 | N14: =(B14-D14)/D14 -> 0.21689887
A15: Fin Year | B15: =SUM(B3:B14) -> 10257267 | C15: =SUM(C3:C14) -> 9182489.9 | D15: =SUM(D3:D14) -> 7814885 | E15: =SUM(E3:E14) -> 1074777.2 | G15: =SUM(G3:G14) -> 1367604.9 | H15: =(C15-D15)/D15 -> 0.175 | K15: =SUM(K12:K14) -> 0 | M15: =B15-D15 -> 2442382.1 | N15: =(B15-D15)/D15 -> 0.3125295
A16: Mar | E16: =B16-C16 -> 0 | F16: =(B16-C16)/C16 -> #DIV/0! | G16: =(C16-D16) -> 0 | H16: =(C16-D16)/D16 -> #DIV/0! | M16: =B16-D16 -> 0 | N16: =(B16-D16)/D16 -> #DIV/0!
A17: April | E17: =B17-C17 -> 0 | F17: =(B17-C17)/C17 -> #DIV/0! | G17: =(C17-D17) -> 0 | H17: =(C17-D17)/D17 -> #DIV/0!
A18: May | E18: =B18-C18 -> 0 | F18: =(B18-C18)/C18 -> #DIV/0! | G18: =(C18-D18) -> 0 | H18: =(C18-D18)/D18 -> #DIV/0!
A19: June | E19: =B19-C19 -> 0 | F19: =(B19-C19)/C19 -> #DIV/0! | G19: =(C19-D19) -> 0 | H19: =(C19-D19)/D19 -> #DIV/0!
A20: July | E20: =B20-C20 -> 0 | F20: =(B20-C20)/C20 -> #DIV/0! | G20: =(C20-D20) -> 0 | H20: =(C20-D20)/D20 -> #DIV/0!
A21: August | E21: =B21-C21 -> 0 | F21: =(B21-C21)/C21 -> #DIV/0! | G21: =(C21-D21) -> 0 | H21: =(C21-D21)/D21 -> #DIV/0!
A22: Sept | E22: =B22-C22 -> 0 | F22: =(B22-C22)/C22 -> #DIV/0! | G22: =(C22-D22) -> 0 | H22: =(C22-D22)/D22 -> #DIV/0!
A23: TOTALS | B23: =SUM(B16:B22) -> 0 | C23: =(D23*1.175) -> 9182489.9 | D23: =SUM(D15+D16+D17+D18+D22) -> 7814885 | E23: =SUM(E7:E22) -> 1810440.1 | G23: =(C23-D23) -> 1367604.9 | H23: =(C23-D23)/D23 -> 0.175 | K23: =SUM(K12+K13+K14+K16+K17+K22) -> 0 | L23: =SUM(L10:L22) -> 0
A24: Occupancy
B25: as @ 21 April 2015 | D25: LY Actual | G25: Current vrs LY Actual | I25: Variance last 7 days | J25: as @ 03 June 2014 | K25: Variance last 7 days | L25: as @ 14 April 2015
A26: Mar | B26: 0.88 | C26: 2852 | D26: 0.92 | E26: 2905 | G26: -0.04 | I26: =B26-J26 -> -365.12 | J26: 366
A27: Apr | B27: 0.71 | C27: 2202 | D27: 0.6 | E27: 1827 | G27: 0.11 | I27: =B27-J27 -> -365.29 | J27: 366
A28: May | B28: 0.63 | C28: 2050 | D28: 0.63 | E28: 1956 | G28: 0 | I28: =B28-J28 -> -365.37 | J28: 366
A29: Jun | B29: 0.57 | C29: 1827 | D29: 0.52 | E29: 1558 | G29: 0.05 | I29: =B29-J29 -> -365.43 | J29: 366
A30: July | B30: 0.69 | C30: 2227 | D30: 0.55 | E30: 1714 | G30: 0.14 | I30: =B30-J30 -> -365.31 | J30: 366
A31: Aug | B31: 0.67 | C31: 2153 | D31: 0.56 | E31: 1761 | G31: 0.11 | I31: =B31-J31 -> -479.33 | J31: 480
A32: Sept | B32: 0.67 | D32: 0.64 | E32: 1945 | G32: 0.03 | I32: =B32-J32 -> -793.33 | J32: 794
A33: Oct | B33: 0.84 | D33: 0.75 | E33: 2304 | G33: 0.09 | I33: =B33-J33 -> -386.16 | J33: 387
A34: Nov | B34: 0.87 | D34: 0.91 | E34: 2736 | G34: -0.04 | I34: =B34-J34 -> -357.13 | J34: 358
A35: Dec | B35: 0.89 | D35: 0.88 | E35: 2820 | G35: 0.01
A36: Jan | B36: 0.82 | D36: 0.85 | E36: 2747 | G36: 0.28
A37: Feb | B37: 0.94 | D37: 0.92 | E37: 2717 | G37: 0.02
A38: Mar
A39: April
A40: May
A41: June
A42: July
A43: August
A44: Sept
B45: Average Room Rate
B46: as @ 21 April 2015 | D46: LY Actual | E46: Variance 2015 vrs 2014 | I46: Variance last 7 days | J46: as @ 03 June 2014 | K46: Variance last 7 days | L46: as @ 14 April 2015
A47: Mar | B47: =B3/C26 -> 342.34537 | D47: =D3/E26 -> 275.43305 | E47: =B47-D47 -> 66.912325 | G47: =(B47-D47)/B47 -> 0.19545269 | I47: =B47-J47 -> -160877.65 | J47: 161220 | L47: 342
A48: Apr | B48: =B4/C27 -> 348.29882 | D48: =D4/E27 -> 274.60646 | E48: =B48-D48 -> 73.692361 | G48: =(B48-D48)/B48 -> 0.21157798 | I48: =B48-J48 -> -160871.7 | J48: 161220 | L48: 348
A49: May | B49: =B5/C28 -> 314.31171 | D49: =D5/E28 -> 270.62832 | E49: =B49-D49 -> 43.683384 | G49: =(B49-D49)/B49 -> 0.13898109 | I49: =B49-J49 -> -160905.69 | J49: 161220 | L49: 314
A50: Jun | B50: =B6/C29 -> 290.5988 | D50: =D6/E29 -> 233.70154 | E50: =B50-D50 -> 56.897255 | G50: =(B50-D50)/B50 -> 0.19579316 | I50: =B50-J50 -> -160929.4 | J50: 161220 | L50: 291
A51: July | B51: =B7/C30 -> 295.4881 | D51: =D7/E30 -> 258.15519 | E51: =B51-D51 -> 37.332908 | G51: =(B51-D51)/B51 -> 0.12634319 | I51: =B51-J51 -> -160924.51 | J51: 161220 | L51: 295
A52: Aug | B52: =B8/C31 -> 301.05899 | D52: =D8/E31 -> 247.96025 | E52: =B52-D52 -> 53.098738 | G52: =(B52-D52)/B52 -> 0.1763732 | I52: =B52-J52 -> -209822.94 | J52: 210124 | L52: 301
A53: Sept | B53: =(398+331)/2 -> 364.5 | D53: 280 | E53: =B53-D53 -> 84.5 | G53: =(B53-D53)/B53 -> 0.23182442 | I53: =B53-J53 -> -288411.5 | J53: 288776 | L53: 365
A54: Oct | B54: =910865/1838 -> 495.57399 | D54: =D10/E33 -> 275.95182 | E54: =B54-D54 -> 219.62217 | G54: =(B54-D54)/B54 -> 0.44316726 | I54: =B54-J54 -> -213230.43 | J54: 213726 | L54: 496
A55: Nov | B55: =1045436/1860 -> 562.06237 | D55: =D11/E34 -> 281.75402 | E55: =B55-D55 -> 280.30835 | G55: =(B55-D55)/B55 -> 0.49871395 | I55: =B55-J55 -> -160347.94 | J55: 160910 | L55: =1038455/1821 -> 570.26634
A56: Dec | B56: =1178518/1966 -> 599.44964 | D56: =D12/E35 -> 335.69468 | E56: =604-336 -> 268 | G56: =(B56-D56)/B56 -> 0.4399952 | L56: =1187159/1966 -> 603.84486
A57: Jan | B57: =989940/1657 -> 597.42909 | D57: =D13/E36 -> 340.86604 | E57: =652-341 -> 311 | G57: =(B57-D57)/B57 -> 0.4294452 | L57: =1117894/1826 -> 612.2092
A58: Feb | B58: =1103333/1889 -> 584.08311 | D58: =D13/E37 -> 344.62974 | E58: =B58-D58 -> 239.45337 | G58: =(B58-D58)/B58 -> 0.40996456 | L58: =1094297/1863 -> 587.38433
A59: Mar
A60: April
A61: May
A62: June
A63: July
A64: August
A65: Sept
B66: =SUM(B59:B65)/6 -> 0 | D66: =SUM(D47:D65)/14 -> 244.24151 | E66: =B66-D66 -> -244.24151 | G66: =(B66-D66)/B66 -> #DIV/0! | L66: =SUM(L59:L65)/6 -> 0

Sheet Marketing
A1: Think about the steps you personally take to book a trip – how much research would it involve? Where would you look and who would you trust? Add these considerations into your marketing efforts to make sure you’re speaking to today’s traveller at each stage of the cycle – including post-stay
A2: If you know a guest has had an amazing time, then encourage them to share that experience online. Your hotel will become part of a ‘friends and family’ discussion, which is a sure-fire way to get in to social media newsfeeds, If you’re delivering the right experience, customers will do the promoting for you via social media
A3: Engaging with travel bloggers might seem daunting but it’s something you should start to mastermind as they can influence many online users and sway booking decisions. Many blogs have bigger readerships than printed magazines so you should stand up and take notice of them. Be authentic and do your research by familiarising yourself with the blog. They will only ever write about topics they’re genuinely interested in. Start by finding a local blogger and build your networking from there,

Sheet Sheet1
A1: Revenue
B2: as @ 15 July 2014 | C2: Target | D2: On the books @ 15 July 2013 | E2: LY Actual | F2: 10 July 2014 vrs Target | H2: Budget vrs LY | J2: 10 July 2014 vrs 10 July 2013 | L2: Variance last 5 days | M2: Variance last 5 days LY | N2: as @ 10 July 2014
A3: July | B3: 844690 | C3: =(E3*1.1) -> 883006.3 | D3: 684439 | E3: 802733 | F3: =B3-C3 -> -38316.3 | G3: =(B3-C3)/B3 -> -0.045361375 | H3: =(C3-E3) -> 80273.3 | I3: =(C3-E3)/E3 -> 0.1 | J3: =B3-D3 -> 160251 | K3: =(B3-D3)/B3 -> 0.18971575 | L3: =B3-N3 -> 83768 | M3: 113035 | N3: 760922
A4: Aug | B4: 462833 | C4: =(E4*1.1) -> 1351227.9 | D4: 440454 | E4: 1228389 | F4: =B4-C4 -> -888394.9 | G4: =(B4-C4)/B4 -> -1.9194718 | H4: =(C4-E4) -> 122838.9 | I4: =(C4-E4)/E4 -> 0.1 | J4: =B4-D4 -> 22379 | K4: =(B4-D4)/B4 -> 0.048352213 | L4: =B4-N4 -> 102498 | M4: 102843 | N4: 360335
A5: Sept | B5: 433577 | C5: =(E5*1.1) -> 1461288.4 | D5: 347674 | E5: 1328444 | F5: =B5-C5 -> -1027711.4 | G5: =(B5-C5)/B5 -> -2.3703088 | H5: =(C5-E5) -> 132844.4 | I5: =(C5-E5)/E5 -> 0.1 | J5: =B5-D5 -> 85903 | K5: =(B5-D5)/B5 -> 0.19812628 | L5: =B5-N5 -> 5183 | M5: 117280 | N5: 428394
A6: Oct | B6: 339556 | C6: =(E6*1.1) -> 1992527.9 | D6: 358447 | E6: 1811389 | F6: =B6-C6 -> -1652971.9 | G6: =(B6-C6)/B6 -> -4.8680391 | H6: =(C6-E6) -> 181138.9 | I6: =(C6-E6)/E6 -> 0.1 | J6: =B6-D6 -> -18891 | K6: =(B6-D6)/B6 -> -0.055634417 | L6: =B6-N6 -> 30284 | M6: 187031 | N6: 309272
A7: Nov | B7: 282250 | C7: =(E7*1.1) -> 2807965.6 | D7: 471607 | E7: 2552696 | F7: =B7-C7 -> -2525715.6 | G7: =(B7-C7)/B7 -> -8.9485052 | H7: =(C7-E7) -> 255269.6 | I7: =(C7-E7)/E7 -> 0.1 | J7: =B7-D7 -> -189357 | K7: =(B7-D7)/B7 -> -0.67088397 | L7: =B7-N7 -> 16220 | M7: 162635 | N7: 266030
A8: Dec | B8: 981863 | C8: =(E8*1.1) -> 3041010.5 | D8: 941195 | E8: 2764555 | F8: =B8-C8 -> -2059147.5 | G8: =(B8-C8)/B8 -> -2.0971841 | H8: =(C8-E8) -> 276455.5 | I8: =(C8-E8)/E8 -> 0.1 | J8: =B8-D8 -> 40668 | K8: =(B8-D8)/B8 -> 0.04141922 | L8: =B8-N8 -> -176282 | M8: 119930 | N8: 1158145
A9: Room Nights
B10: as @ 15 July 2014 | C10: Occ @ 10 July 2014 | D10: On the books @ 15 July 2013 | E10: LY Actual | J10: 10 July 2014 vrs 10 July 2013 | L10: Variance last 5 days | M10: Variance last 5 days LY | N10: as @ 10 July 2014
A11: July | B11: 1218 | C11: 0.43 | D11: 1082 | E11: 1290 | J11: =B11-D11 -> 136 | K11: =(B11-D11)/B11 -> 0.11165846 | L11: =B11-N11 -> 62 | M11: 96 | N11: 1156
A12: Aug | B12: 970 | C12: 0.33 | D12: 720 | E12: 1801 | J12: =B12-D12 -> 250 | K12: =(B12-D12)/B12 -> 0.25773196 | L12: =B12-N12 -> -8 | M12: 21 | N12: 978
A13: Sept | B13: 1187 | C13: 0.42 | D13: 517 | E13: 1840 | J13: =B13-D13 -> 670 | K13: =(B13-D13)/B13 -> 0.56444819 | L13: =B13-N13 -> -1 | M13: 49 | N13: 1188
A14: Oct | B14: 546 | C14: 0.18 | D14: 554 | E14: 1922 | J14: =B14-D14 -> -8 | K14: =(B14-D14)/B14 -> -0.014652015 | L14: =B14-N14 -> 19 | M14: 99 | N14: 527
A15: Nov | B15: 602 | C15: 0.21 | D15: 554 | E15: 2508 | J15: =B15-D15 -> 48 | K15: =(B15-D15)/B15 -> 0.079734219 | L15: =B15-N15 -> 19 | M15: 3 | N15: 583
A16: Dec | B16: 1284 | C16: 0.44 | D16: 941 | E16: 2254 | J16: =B16-D16 -> 343 | K16: =(B16-D16)/B16 -> 0.26713396 | L16: =B16-N16 -> -126 | M16: -5 | N16: 1410
A17: AVR
B18: as @ 15 July 2014 | D18: On the books @ 10 July 2013 | E18: LY Actual | H18: Budget vrs LY | J18: 10 July 2014 vrs 10 July 2013 | L18: Variance last 5 days | M18: Variance last 5 days LY | N18: as @ 10 July 2014
A19: July | B19: 693 | D19: 632.56839 | E19: =E3/E11 -> 622.27364 | J19: =B19-D19 -> 60.431608 | K19: =(B19-D19)/B19 -> 0.087202898 | L19: =B19-N19 -> 34.762976 | M19: 53.05115 | N19: =N3/N11 -> 658.23702
A20: Aug | B20: 477 | D20: 611.74167 | E20: =E4/E12 -> 682.05941 | J20: =B20-D20 -> -134.74167 | K20: =(B20-D20)/B20 -> -0.28247729 | L20: =B20-N20 -> 108.5593 | M20: 128.75025 | N20: =N4/N12 -> 368.4407
A21: Sept | B21: 365 | D21: 672.48356 | E21: =E4/E12 -> 682.05941 | J21: =B21-D21 -> -307.48356 | K21: =(B21-D21)/B21 -> -0.84242071 | L21: =B21-N21 -> 4.3989899 | M21: 180.18869 | N21: =N5/N13 -> 360.60101
A22: Oct | B22: 622 | D22: 647.01625 | E22: =E6/E14 -> 942.45005 | J22: =B22-D22 -> -25.016245 | K22: =(B22-D22)/B22 -> -0.040219044 | L22: =B22-N22 -> 35.14611 | M22: 270.27778 | N22: =N6/N14 -> 586.85389
A23: Nov | B23: 468 | D23: 851.27617 | E23: =E7/E15 -> 1017.8214 | J23: =B23-D23 -> -383.27617 | K23: =(B23-D23)/B23 -> -0.81896618 | L23: =B23-N23 -> 11.687822 | M23: 290.52844 | N23: =N7/N15 -> 456.31218
A24: Dec | B24: 764 | D24: 1000.2072 | E24: =E8/E16 -> 1226.5106 | J24: =B24-D24 -> -236.20723 | K24: =(B24-D24)/B24 -> -0.30917176 | L24: =B24-N24 -> -57.379433 | M24: 132.06241 | N24: =N8/N16 -> 821.37943
